Workbook

Sheet Dashboard
B2: Verified European Aerospace & Defence Technology Transactions
B3: Completed IPO and change-of-control transactions | 2023-01-01 to 2026-08-02 | Strict public-source verification
B5: Completed transactions | C5: =COUNTA('Europe'!A2:A134) | E5: Completion year | F5: Transactions
B6: M&A | C6: =COUNTIF('Europe'!K2:K134,"M&A") | E6: 2023 | F6: =COUNTIF('Europe'!J2:J134,E6)
B7: IPOs | C7: =COUNTIF('Europe'!K2:K134,"IPO") | E7: 2024 | F7: =COUNTIF('Europe'!J2:J134,E7)
B8: Pending pipeline | C8: =COUNTA('Europe_Pending'!A2:A15) | E8: 2025 | F8: =COUNTIF('Europe'!J2:J134,E8)
E9: 2026 | F9: =COUNTIF('Europe'!J2:J134,E9)
B11: Scope and audit controls
B12: Completed population | C12: Europe sheet only; sorted by completion/IPO date.
B13: Pending transactions | C13: Europe_Pending; excluded from completed KPIs.
B14: Exclusions and corrections | C14: Europe_Audit_Log records a decision for every original Europe row.
B15: Source record | C15: Sources_Audit and row-level primary URLs.
B16: Quality control | C16: Checks sheet reconciles IDs, dates, sources, status and Master_Deals.
B17: Completeness limitation | C17: Public sources cannot prove the absence of undisclosed private transactions; no unavailable value has been invented.
B19: Workbook navigation
B20: Europe | C20: Verified completed transactions
B21: Europe_Pending | C21: Announced but uncompleted transactions
B22: Europe_Audit_Log | C22: Every original row's retain/exclude/correct decision
B23: Sources_Audit | C23: Primary-source register
B24: Master_Deals | C24: All regions, with Europe reconciled
B25: Definitions | C25: Approved strict scope and conventions
B26: Checks | C26: Quality-control results

Sheet Master_Deals
A1: Deal ID | B1: Region | C1: Target Country | D1: Target / Asset | E1: Acquirer | F1: Acquirer Country | G1: Seller | H1: Announcement Date | I1: Completion Date | J1: Deal Year | K1: Transaction Type | L1: Deal Structure | M1: Deal Status | N1: Deal Value (USD mn) | O1: Currency | P1: Hardware / Software / Services | Q1: A&D Domain | R1: Inclusion Tier | S1: Relevance Rationale | T1: Reliability | U1: Source URL | V1: Source Type | W1: Notes
A2: ISR-001 | B2: Israel | C2: Israel | D2: Orbit Communication Systems | E2: Kratos Defense & Security Solutions | F2: USA | G2: Public shareholders | H2: 2025-11-04 | I2: Expected 2026 | J2: 2026 | K2: M&A | L2: Full acquisition | M2: Announced | N2: 356.3 | O2: USD | P2: Hardware | Q2: Satellite communications / defense satcom | R2: Core A&D | S2: Israeli satellite-communications and airborne/ground satcom provider with defense and national-security applications. | T2: High | U2: https://www.kratosdefense.com/newsroom/kratos-to-acquire-israel-based-orbit-technologies-ltd-for-356-3-million | V2: Company / reputable press
A3: ISR-002 | B3: Israel | C3: Israel | D3: Sentry CS / Sentrycs | E3: Ondas Holdings | F3: USA | H3: 2025-11-04 | I3: 2025-11-29 | J3: 2025 | K3: M&A | L3: Full acquisition | M3: Completed | O3: USD | P3: Software/Hardware | Q3: Counter-UAS / RF cyber | R3: Core A&D | S3: Counter-drone detection and mitigation for defense, homeland security, airports, and critical infrastructure. | T3: High | U3: https://ir.ondas.com/press-releases/detail/251/ondas-to-acquire-sentrycs-a-global-leader-in-counter-uas | V3: Company / reputable press
A4: ISR-003 | B4: Israel | C4: Israel | D4: Roboteam | E4: Ondas Holdings | F4: USA | H4: 2025-11-25 | I4: 2025-12-17 | J4: 2025 | K4: M&A | L4: Full acquisition | M4: Completed | O4: USD | P4: Hardware | Q4: UGV / tactical robotics | R4: Core A&D | S4: Unmanned ground vehicles for military, EOD, ISR, and hazardous missions. | T4: High | U4: https://ir.ondas.com/press-releases/detail/264/ondas-completes-acquisition-of-roboteam-a-global-leader-in | V4: Company / reputable press
A5: ISR-004 | B5: Israel | C5: Israel | D5: Omnisys | E5: Ondas Holdings | F5: USA | H5: 2026-05-18 | J5: 2026 | K5: M&A | L5: Full acquisition / stock deal | M5: Announced | N5: 200 | O5: USD | P5: Software | Q5: Mission planning / C2 / battlefield optimization | R5: Core A&D | S5: Military mission-planning and operational-optimization software for defense customers. | T5: Medium-High | U5: https://www.calcalistech.com/ctechnews/article/skbzd9dkge | V5: Business press | W5: Very recent; verify closing when announced.
A6: ISR-005 | B6: Israel | C6: Israel | D6: SpearUAV | E6: UVision Air | F6: Israel | H6: 2025-12-08 | J6: 2025 | K6: M&A | L6: Acquisition | M6: Announced / reported | O6: USD | P6: Hardware | Q6: Loitering munitions / tactical UAV | R6: Core A&D | S6: Capsule-launched tactical drones/loitering systems; directly defense-relevant. | T6: Medium-High | U6: https://www.globes.co.il/news/article.aspx?did=1001528671 | V6: Business press | W6: Value undisclosed in public reporting.
A7: ISR-006 | B7: Israel | C7: Israel | D7: Iron Drone | E7: Airobotics / Ondas Holdings | F7: Israel / USA | H7: 2023-03-06 | J7: 2023 | K7: M&A | L7: Acquisition | M7: Completed | O7: USD | P7: Hardware/Software | Q7: Counter-UAS / autonomous drones | R7: Core A&D | S7: Counter-drone interception and autonomous drone capabilities relevant to security and defense. | T7: Medium | U7: https://ir.ondas.com/press-releases/detail/172/ondas-receives-8-0-million-purchase-order-for-iron-drone | V7: Company press release | W7: Use if source URL resolves in browser.
A8: ISR-007 | B8: Israel | C8: Israel | D8: Airobotics | E8: Ondas Holdings | F8: USA | G8: Public shareholders | H8: 2022-07-05 | I8: 2023-01-23 | J8: 2023 | K8: M&A | L8: Full acquisition | M8: Completed | O8: USD | P8: Hardware/Software | Q8: Autonomous drone systems | R8: Adjacent dual-use | S8: Autonomous drones for security, public-safety and critical-infrastructure missions; not a pure defense transaction. | T8: Medium-High | U8: https://ir.ondas.com/press-releases/detail/108/ondas-holdings-completes-acquisition-of-airobotics | V8: Company press release
A9: ISR-008 | B9: Israel | C9: Israel | D9: 4M defense | E9: Ondas Holdings | F9: USA | H9: 2025-09-03 | J9: 2025 | K9: M&A | L9: Acquisition | M9: Announced | O9: USD | P9: Software | Q9: Geospatial / infrastructure intelligence | R9: Adjacent dual-use | S9: Subsurface mapping/geospatial data can support infrastructure, security and resilience use cases; weaker defense fit than UAS/C2. | T9: Medium | U9: https://ir.ondas.com/press-releases/detail/249/ondas-to-acquire-controlling-interest-in-4m-defense | V9: Company press releases index | W9: Check final deal page before publication.
A10: ISR-010 | B10: Israel | C10: USA | D10: DataPath | E10: Gilat Satellite Networks | F10: Israel | G10: DataPath shareholders | H10: 2023-03-09 | I10: 2023-11-15 | J10: 2023 | K10: M&A | L10: Full acquisition | M10: Completed | O10: USD | P10: Hardware/Services | Q10: Satellite communications / defense satcom | R10: Core A&D | S10: US satellite communications systems provider serving defense and government customers acquired by Israeli satcom group. | T10: High | U10: https://www.gilat.com/pressreleases/gilat-completes-acquisition-of-datapath/ | V10: Company press release
A11: ISR-011 | B11: Israel | C11: USA | D11: Stellar Blu Solutions | E11: Gilat Satellite Networks | F11: Israel | H11: 2024-06-17 | I11: 2024-09-18 | J11: 2024 | K11: M&A | L11: Full acquisition | M11: Completed | O11: USD | P11: Hardware | Q11: Aviation connectivity / satcom terminals | R11: Adjacent A&D aerospace | S11: Aviation satcom terminal business relevant to aerospace connectivity; dual-use rather than pure defense. | T11: High | U11: https://www.gilat.com/pressreleases/gilat-completes-acquisition-of-stellar-blu-solutions-llc/ | V11: Company press release
A12: ISR-014 | B12: Israel | C12: Israel | D12: CyberArk | E12: Palo Alto Networks | F12: USA | G12: Public shareholders | H12: 2025-07-30 | I12: Expected FY2026 | J12: 2026 | K12: M&A | L12: Cash-and-stock acquisition | M12: Announced | N12: 25000 | O12: USD | P12: Software | Q12: Identity security / privileged access | R12: Adjacent cyber-security | S12: Large Israeli-founded cybersecurity deal; relevant to defense/security landscape but not pure aerospace/defense. | T12: High | U12: https://www.reuters.com/world/middle-east/palo-altos-25-billion-deal-cyberark-targets-rising-ai-driven-threats-2025-07-30/?utm_source=chatgpt.com | V12: Company press release
A13: ISR-015 | B13: Israel | C13: Israel-founded / USA | D13: Wiz | E13: Google / Alphabet | F13: USA | H13: 2025-03-18 | I13: Pending / approvals | J13: 2025 | K13: M&A | L13: Full acquisition | M13: Announced | N13: 32000 | O13: USD | P13: Software | Q13: Cloud security | R13: Adjacent cyber-security | S13: Israeli-founded cloud security company; relevant as dual-use cyber/security consolidation, not core A&D. | T13: High | U13: https://blog.google/company-news/inside-google/company-announcements/google-agreement-acquire-wiz/?utm_source=chatgpt.com | V13: Company press release
A14: ISR-016 | B14: Israel | C14: Israel | D14: Dig Security | E14: Palo Alto Networks | F14: USA | H14: 2023-10-31 | J14: 2023 | K14: M&A | L14: Acquisition | M14: Completed | N14: 350 | O14: USD | P14: Software | Q14: Cloud data security / DSPM | R14: Adjacent cyber-security | S14: Israeli cybersecurity acquisition; relevant to security/dual-use cyber but not pure defense. | T14: Medium-High | U14: https://www.paloaltonetworks.com/company/press/2023/palo-alto-networks-completes-acquisition-of-dig-security?utm_source=chatgpt.com | V14: Legal adviser / business press | W14: Value usually reported as $300m-$400m; use midpoint.
A15: ISR-017 | B15: Israel | C15: Israel | D15: Talon Cyber Security | E15: Palo Alto Networks | F15: USA | H15: 2023-11-06 | J15: 2023 | K15: M&A | L15: Acquisition | M15: Completed | N15: 625 | O15: USD | P15: Software | Q15: Secure enterprise browser | R15: Adjacent cyber-security | S15: Browser-security acquisition; relevant to cyber/security consolidation. | T15: Medium-High | U15: https://www.calcalistech.com/ctechnews/article/r1hd0o87a?utm_source=chatgpt.com | V15: Business press | W15: Reported value.
A16: ISR-018 | B16: Israel | C16: Israel | D16: Noname Security | E16: Akamai Technologies | F16: USA | H16: 2024-05-07 | I16: 2024-06-25 | J16: 2024 | K16: M&A | L16: Full acquisition | M16: Completed | N16: 450 | O16: USD | P16: Software | Q16: API security | R16: Adjacent cyber-security | S16: API-security platform acquired by major security infrastructure company; dual-use cybersecurity relevance. | T16: High | U16: https://www.akamai.com/newsroom/press-release/akamai-completes-acquisition-of-api-security-company-noname?utm_source=chatgpt.com | V16: Company press release
A17: ISR-019 | B17: Israel | C17: Israel | D17: Perimeter 81 | E17: Check Point Software Technologies | F17: Israel | H17: 2023-08-10 | I17: 2023-09-11 | J17: 2023 | K17: M&A | L17: Acquisition | M17: Completed | N17: 490 | O17: USD | P17: Software | Q17: SASE / network security | R17: Adjacent cyber-security | S17: Israeli network-security/SASE acquisition; relevant to homeland-security and enterprise-cyber landscape. | T17: High | U17: https://www.checkpoint.com/press-releases/check-point-to-acquire-perimeter-81-to-deliver-the-fastest-and-most-secure-sase-solution-in-the-industry/?utm_source=chatgpt.com | V17: Company press release
A18: ISR-020 | B18: Israel | C18: Israel | D18: Ermetic | E18: Tenable | F18: USA | H18: 2023-09-07 | I18: 2023-10-02 | J18: 2023 | K18: M&A | L18: Acquisition | M18: Completed | N18: 265 | O18: USD | P18: Software | Q18: Cloud infrastructure entitlement management | R18: Adjacent cyber-security | S18: Cloud security and identity-risk platform; dual-use cyber relevance. | T18: High | U18: https://www.tenable.com/press-releases/tenable-announces-intent-to-acquire-ermetic?utm_source=chatgpt.com | V18: Company press release
A19: ISR-021 | B19: Israel | C19: Israel | D19: Axis Security | E19: Hewlett Packard Enterprise | F19: USA | H19: 2023-03-02 | I19: 2023-03-31 | J19: 2023 | K19: M&A | L19: Acquisition | M19: Completed | N19: 500 | O19: USD | P19: Software | Q19: SASE / secure access | R19: Adjacent cyber-security | S19: Secure access / edge cybersecurity relevant to security infrastructure; not pure A&D. | T19: Medium-High | U19: https://en.globes.co.il/en/article-hpe-buys-israeli-co-axis-security-for-500m-1001440101?utm_source=chatgpt.com | V19: Company press release | W19: Reported value from business press; official release may not disclose price.
A20: ISR-022 | B20: Israel | C20: Israel | D20: Avalor | E20: Zscaler | F20: USA | H20: 2024-03-13 | I20: 2024-03-26 | J20: 2024 | K20: M&A | L20: Acquisition | M20: Completed | N20: 350 | O20: USD | P20: Software | Q20: Security data fabric / exposure management | R20: Adjacent cyber-security | S20: Israeli security-data platform acquired by Zscaler; relevant to cyber-security consolidation. | T20: High | U20: https://www.calcalistech.com/ctechnews/article/b1jvqdgr6?utm_source=chatgpt.com | V20: Company press release
A21: ISR-023 | B21: Israel | C21: Israel | D21: Gem Security | E21: Wiz | F21: Israel-founded / USA | H21: 2024-04-10 | J21: 2024 | K21: M&A | L21: Acquisition | M21: Completed | N21: 350 | O21: USD | P21: Software | Q21: Cloud detection and response | R21: Adjacent cyber-security | S21: Cloud threat-detection acquisition by Israeli-founded security platform Wiz. | T21: Medium-High | U21: https://www.calcalistech.com/ctechnews/article/bjleedj0t?utm_source=chatgpt.com | V21: Company blog / press
A22: ISR-024 | B22: Israel | C22: Israel | D22: Laminar | E22: Rubrik | F22: USA | H22: 2023-08-08 | J22: 2023 | K22: M&A | L22: Acquisition | M22: Completed | N22: 200 | O22: USD | P22: Software | Q22: Cloud data security | R22: Adjacent cyber-security | S22: Cloud data-security acquisition; dual-use cyber relevance. | T22: High | V22: Company press release | W22: Reported value around $200m-$250m.
A23: ISR-025 | B23: Israel | C23: Israel | D23: Flow Security | E23: CrowdStrike | F23: USA | H23: 2024-03-05 | J23: 2024 | K23: M&A | L23: Acquisition | M23: Completed | N23: 200 | O23: USD | P23: Software | Q23: Cloud data runtime security | R23: Adjacent cyber-security | S23: Cloud data-security acquisition by CrowdStrike; relevant to cyber/security but not pure A&D. | T23: Medium-High | V23: Company press release | W23: Reported value from business press.
A24: ISR-026 | B24: Israel | C24: Israel | D24: Bionic | E24: CrowdStrike | F24: USA | H24: 2023-09-19 | J24: 2023 | K24: M&A | L24: Acquisition | M24: Completed | N24: 350 | O24: USD | P24: Software | Q24: Application security posture management | R24: Adjacent cyber-security | S24: Israeli app-security company acquired by CrowdStrike; security-adjacent. | T24: High | V24: Company press release
A25: ISR-028 | B25: Israel | C25: Israel | D25: Spera Security | E25: Okta | F25: USA | H25: 2023-12-19 | I25: 2024-02-01 | J25: 2024 | K25: M&A | L25: Acquisition | M25: Completed | N25: 110 | O25: USD | P25: Software | Q25: Identity security posture management | R25: Adjacent cyber-security | S25: Identity-security posture management; relevant to cyber/zero-trust security. | T25: High | V25: Company press release
A26: ISR-029 | B26: Israel | C26: Israel | D26: SCADAfence | E26: Honeywell | F26: USA | H26: 2023-07-10 | I26: 2023-08-14 | J26: 2023 | K26: M&A | L26: Acquisition | M26: Completed | O26: USD | P26: Software | Q26: OT / industrial cybersecurity | R26: Adjacent cyber / critical infrastructure | S26: OT cybersecurity for industrial and critical infrastructure environments; strong homeland-security relevance. | T26: High | V26: Company press release
A27: ISR-032 | B27: Israel | C27: Israel | D27: Enso Security | E27: Snyk | F27: UK / USA | H27: 2023-06-20 | J27: 2023 | K27: M&A | L27: Acquisition | M27: Completed | O27: USD | P27: Software | Q27: Application security posture management | R27: Adjacent cyber-security | S27: Israeli application-security posture management acquired by Snyk; cyber-security fit. | T27: High | V27: Company press release
A28: ISR-033 | B28: Israel | C28: Israel | D28: Silk Security | E28: Armis | F28: Israel / USA | H28: 2024-04-17 | J28: 2024 | K28: M&A | L28: Acquisition | M28: Completed | N28: 150 | O28: USD | P28: Software | Q28: Cyber risk prioritization | R28: Adjacent cyber-security | S28: Cyber-risk prioritization platform acquired by Armis; security-adjacent. | T28: High | V28: Company press release | W28: Reported value from business press.
A29: ISR-034 | B29: Israel | C29: Israel | D29: Authomize | E29: Delinea | F29: USA | H29: 2024-01-09 | I29: 2024-02-01 | J29: 2024 | K29: M&A | L29: Acquisition | M29: Completed | O29: USD | P29: Software | Q29: Identity threat detection and response | R29: Adjacent cyber-security | S29: Identity-security and threat-detection acquisition; cyber-security fit. | T29: High | V29: Company press release
A30: USA-040 | B30: USA | C30: USA | D30: Spirit AeroSystems | E30: Boeing | F30: USA | G30: Public shareholders | H30: 2024-07-01 | I30: 2025-12-08 | J30: 2025 | K30: M&A | L30: Full acquisition | M30: Completed | N30: 4700 | O30: USD | P30: Hardware | Q30: Aerospace structures / supply chain | R30: Core aerospace | S30: Major aerospace structures supplier; central to aircraft production supply chain. | T30: High | V30: Company press release / Reuters | W30: Enterprise value often cited around $8.3bn including debt.
A31: USA-041 | B31: USA | C31: USA | D31: CAES Systems | E31: Honeywell | F31: USA | G31: Advent International | H31: 2024-06-20 | I31: 2024-09-04 | J31: 2024 | K31: M&A | L31: Full acquisition | M31: Completed | N31: 1900 | O31: USD | P31: Hardware | Q31: RF electronics / defense electronics | R31: Core A&D | S31: High-reliability RF, antenna and communications electronics used across defense platforms. | T31: High | V31: Company press release
A32: USA-042 | B32: USA | C32: USA | D32: BlueHalo | E32: AeroVironment | F32: USA | G32: Arlington Capital Partners | H32: 2024-11-19 | I32: 2025-05-01 | J32: 2025 | K32: M&A | L32: Stock transaction / merger | M32: Completed | N32: 4100 | O32: USD | P32: Hardware/Software | Q32: C-UAS / directed energy / space / cyber | R32: Core A&D | S32: Creates defense-tech portfolio across uncrewed systems, counter-UAS, directed energy, cyber and space. | T32: High | V32: Company press release
A33: USA-043 | B33: USA | C33: USA | D33: LinQuest | E33: KBR | F33: USA | G33: Madison Dearborn Partners | H33: 2024-07-16 | I33: 2024-09-03 | J33: 2024 | K33: M&A | L33: Full acquisition | M33: Completed | N33: 737 | O33: USD | P33: Services/Software | Q33: National security space / digital integration | R33: Core A&D services | S33: Engineering, data analytics and digital integration for national-security space missions. | T33: High | V33: Company press release
A34: USA-044 | B34: USA | C34: USA | D34: SciTec | E34: Firefly Aerospace | F34: USA | H34: 2025-10-05 | I34: Expected 2025 | J34: 2025 | K34: M&A | L34: Cash and stock acquisition | M34: Announced | N34: 855 | O34: USD | P34: Software/Services | Q34: Missile warning / tracking / remote sensing | R34: Core A&D space | S34: National-security technology company focused on missile warning, tracking, ISR and space defense analytics. | T34: High | V34: Reuters
A35: USA-045 | B35: USA | C35: USA | D35: Stellant Systems | E35: TransDigm Group | F35: USA | G35: Arlington Capital Partners | H35: 2025-12-31 | J35: 2025 | K35: M&A | L35: Full acquisition | M35: Announced | N35: 960 | O35: USD | P35: Hardware | Q35: Electronic components / RF / space | R35: Core A&D | S35: High-power electronic components and subsystems for aerospace, defense, space and satellite applications. | T35: High | V35: Reuters
A36: USA-046 | B36: USA | C36: USA | D36: Raptor Scientific | E36: TransDigm Group | F36: USA | G36: L Squared Capital Partners | H36: 2023-05-30 | I36: 2023-08-09 | J36: 2023 | K36: M&A | L36: Full acquisition | M36: Completed | N36: 655 | O36: USD | P36: Hardware/Services | Q36: Aerospace testing and measurement | R36: Core aerospace/defense | S36: Testing and measurement systems for aerospace and defense platforms. | T36: High | V36: Company press release
A37: USA-047 | B37: USA | C37: USA | D37: Calspan Corporation | E37: TransDigm Group | F37: USA | G37: Public / private owners | H37: 2023-03-14 | I37: 2023-05-08 | J37: 2023 | K37: M&A | L37: Full acquisition | M37: Completed | N37: 725 | O37: USD | P37: Services/Hardware | Q37: Aerospace testing / wind tunnel / flight test | R37: Core aerospace/defense | S37: Aerospace testing and technology-development services for defense and commercial aviation. | T37: High | V37: Company press release
A38: USA-048 | B38: USA | C38: USA | D38: Wencor Group | E38: HEICO Corporation | F38: USA | G38: Warburg Pincus | H38: 2023-05-15 | I38: 2023-08-04 | J38: 2023 | K38: M&A | L38: Full acquisition | M38: Completed | N38: 2050 | O38: USD | P38: Hardware/Services | Q38: Aerospace aftermarket / parts distribution | R38: Core aerospace | S38: Aviation aftermarket components and distribution serving commercial and defense aviation customers. | T38: High | V38: Company press release
A39: USA-050 | B39: USA | C39: USA | D39: Adranos | E39: Anduril Industries | F39: USA | H39: 2023-06-25 | J39: 2023 | K39: M&A | L39: Acquisition | M39: Completed | O39: USD | P39: Hardware | Q39: Solid rocket motors / propulsion | R39: Core A&D | S39: Solid rocket motor and energetic-materials technology for missiles and defense systems. | T39: High | V39: Company press release
A40: USA-051 | B40: USA | C40: USA | D40: Blue Force Technologies | E40: Anduril Industries | F40: USA | H40: 2023-09-07 | J40: 2023 | K40: M&A | L40: Acquisition | M40: Completed | O40: USD | P40: Hardware/Software | Q40: Autonomous aircraft / defense aviation | R40: Core A&D | S40: Developer of autonomous aircraft; fits US defense-tech autonomy and air systems. | T40: High | V40: Company press release
A41: USA-056 | B41: USA | C41: USA | D41: Sealing Technologies | E41: Parsons Corporation | F41: USA | H41: 2023-08-23 | I41: 2023-09-18 | J41: 2023 | K41: M&A | L41: Full acquisition | M41: Completed | N41: 200 | O41: USD | P41: Services/Software | Q41: Cyber / national security | R41: Core A&D services | S41: Cybersecurity and engineering solutions serving defense and intelligence customers. | T41: High | V41: Company press release
A42: USA-057 | B42: USA | C42: USA | D42: IPKeys Power Partners | E42: Parsons Corporation | F42: USA | H42: 2023-04-18 | I42: 2023-05-01 | J42: 2023 | K42: M&A | L42: Full acquisition | M42: Completed | N42: 43 | O42: USD | P42: Software/Services | Q42: Critical infrastructure cyber / grid security | R42: Adjacent critical infrastructure security | S42: Cyber and grid-modernization software with homeland-security/critical-infrastructure relevance. | T42: High | V42: Company press release
A43: USA-060 | B43: USA | C43: USA | D43: Jacobs Critical Mission Solutions + Cyber & Intelligence businesses | E43: Amentum | F43: USA | G43: Jacobs | H43: 2023-11-20 | I43: 2024-09-27 | J43: 2024 | K43: M&A | L43: Reverse Morris Trust / merger | M43: Completed | N43: 13000 | O43: USD | P43: Services | Q43: Government services / national security / space | R43: Core A&D services | S43: Large government-services combination across national security, space, cyber and mission support. | T43: High | V43: Company press release
A44: USA-063 | B44: USA | C44: USA | D44: Safran North American THSA business | E44: Woodward | F44: USA | G44: Safran | H44: 2024-12-23 | I44: Expected 2025 | J44: 2025 | K44: M&A | L44: Divestiture acquisition | M44: Announced | O44: USD | P44: Hardware | Q44: Flight control actuation | R44: Core aerospace/defense | S44: Flight-control actuation assets acquired as remedy related to Safran/Collins deal. | T44: Medium-High | V44: Company press release | W44: Value undisclosed.
A45: USA-064 | B45: USA | C45: USA | D45: Edge Autonomy | E45: Redwire Corporation | F45: USA | H45: 2025-01-20 | I45: 2025-06-13 | J45: 2025 | K45: M&A | L45: Stock/cash merger | M45: Completed | N45: 925 | O45: USD | P45: Hardware/Software | Q45: Unmanned aircraft / space ISR | R45: Core A&D | S45: Unmanned aircraft and autonomy capabilities combined with space infrastructure/ISR business. | T45: High | V45: Company press release
A46: USA-065 | B46: USA | C46: USA | D46: ZIN Technologies | E46: Voyager Space | F46: USA | H46: 2023-03-13 | J46: 2023 | K46: M&A | L46: Acquisition | M46: Completed | O46: USD | P46: Services/Hardware | Q46: Space engineering / human spaceflight | R46: Core aerospace/space | S46: Engineering and mission integration for civil and defense space markets. | T46: High | V46: Company press release
A47: USA-072 | B47: USA | C47: USA | D47: Precision Aviation Group | E47: GenNx360 Capital Partners | F47: USA | H47: 2024-01-09 | J47: 2024 | K47: M&A | L47: Acquisition / investment | M47: Completed | O47: USD | P47: Services | Q47: Aviation MRO / aerospace aftermarket | R47: Core aerospace | S47: MRO and aerospace aftermarket platform with defense/commercial aviation exposure. | T47: Medium | V47: PE press release
A48: USA-073 | B48: USA | C48: USA | D48: Keystone Turbine Services | E48: Precision Aviation Group | F48: USA | H48: 2023-01-10 | J48: 2023 | K48: M&A | L48: Bolt-on acquisition | M48: Completed | O48: USD | P48: Services | Q48: Aviation MRO / engines | R48: Core aerospace | S48: Aviation MRO bolt-on supporting rotorcraft/aviation maintenance markets. | T48: Medium | V48: Company press release
A49: USA-075 | B49: USA | C49: USA | D49: Nobles Worldwide | E49: Ducommun Incorporated | F49: USA | H49: 2023-10-16 | I49: 2023-11-27 | J49: 2023 | K49: M&A | L49: Acquisition | M49: Completed | N49: 77 | O49: USD | P49: Hardware | Q49: Ammunition-feed systems / defense components | R49: Core A&D | S49: Defense components supplier for ammunition feed systems and related products. | T49: High | V49: Company press release
A50: USA-076 | B50: USA | C50: USA | D50: Williams Aerospace & Manufacturing | E50: Cadre Holdings | F50: USA | H50: 2023-01-09 | J50: 2023 | K50: M&A | L50: Acquisition | M50: Completed | O50: USD | P50: Hardware | Q50: Aerospace parts / defense components | R50: Core aerospace/defense | S50: Aerospace and defense manufacturing bolt-on; relevant lower-middle-market A&D consolidation. | T50: Medium | V50: Company press release
A51: USA-078 | B51: USA | C51: USA | D51: Forcepoint Federal | E51: TPG / Francisco Partners-backed Forcepoint Global Governments and Critical Infrastructure | F51: USA | G51: Raytheon Technologies | H51: 2023-01-09 | I51: 2023-02-01 | J51: 2023 | K51: M&A | L51: Divestiture / carve-out | M51: Completed | O51: USD | P51: Software/Services | Q51: Cybersecurity / government security | R51: Core cyber-defense | S51: Government and critical-infrastructure cybersecurity business serving defense/intelligence markets. | T51: Medium-High | V51: Company press release
A52: ROW-111 | B52: Rest_of_World | C52: USA | D52: Philly Shipyard | E52: Hanwha Systems / Hanwha Ocean | F52: South Korea | G52: Aker Capital | H52: 2024-06-20 | I52: 2024-12-19 | J52: 2024 | K52: M&A | L52: Full acquisition | M52: Completed | N52: 100 | O52: USD | P52: Hardware/Services | Q52: Naval shipbuilding / shipyard capacity | R52: Core A&D maritime | S52: Korean defense/shipbuilding group acquires US shipyard capacity; relevant to naval industrial base. | T52: High | V52: Company press release
A53: ROW-112 | B53: Rest_of_World | C53: Estonia | D53: Milrem Robotics | E53: EDGE Group | F53: UAE | G53: Private shareholders | H53: 2023-02-15 | I53: 2023-02-15 | J53: 2023 | K53: M&A | L53: Majority acquisition | M53: Completed | O53: USD | P53: Hardware/Software | Q53: UGV / robotics | R53: Core A&D | S53: UAE defense group acquires European unmanned ground vehicle developer. | T53: High | V53: Company press release
A54: ROW-113 | B54: Rest_of_World | C54: Australia | D54: Sentient Vision Systems | E54: Anduril Industries | F54: USA | H54: 2024-01-18 | J54: 2024 | K54: M&A | L54: Acquisition | M54: Completed | O54: USD | P54: Software/Hardware | Q54: AI imagery / maritime ISR | R54: Core A&D | S54: Australian AI surveillance and ISR company acquired by US defense-tech group. | T54: High | V54: Company press release
A55: ROW-114 | B55: Rest_of_World | C55: Australia | D55: Tesserent | E55: Thales | F55: France | G55: Public shareholders | H55: 2023-06-13 | I55: 2023-10-04 | J55: 2023 | K55: M&A | L55: Full acquisition | M55: Completed | N55: 176 | O55: USD | P55: Software/Services | Q55: Cybersecurity | R55: Adjacent cyber-defense | S55: Australian/NZ cybersecurity provider acquired by Thales; relevant to security/cyber-defense services. | T55: High | V55: Company press release
A56: ROW-119 | B56: Rest_of_World | C56: Israel / UK | D56: SatixFy Space Systems | E56: MDA Space | F56: Canada | G56: SatixFy Communications | H56: 2025-04-01 | I56: 2025-10-01 | J56: 2025 | K56: M&A | L56: Acquisition | M56: Completed | N56: 60 | O56: USD | P56: Hardware | Q56: Satellite payload chips / space systems | R56: Core aerospace/space | S56: Canadian space company acquired digital payload division with satellite communications technology. | T56: Medium-High | V56: Company press release
A57: ROW-120 | B57: Rest_of_World | C57: USA | D57: Electro-Mechanical Corporation | E57: BWX Technologies | F57: USA | H57: 2024-12-16 | I57: 2025-02-03 | J57: 2025 | K57: M&A | L57: Acquisition | M57: Completed | O57: USD | P57: Hardware | Q57: Naval nuclear / electrical equipment | R57: Core A&D maritime | S57: Supplier of electrical equipment for US Navy and nuclear/defense applications. | T57: High | V57: Company press release
A58: ROW-124 | B58: Rest_of_World | C58: Brazil | D58: SIATT | E58: EDGE Group | F58: UAE | G58: SIATT shareholders | H58: 2023-09-29 | I58: 2024-01-01 | J58: 2024 | K58: M&A | L58: Majority stake acquisition | M58: Completed | O58: USD | P58: Hardware/Software | Q58: Smart weapons / missiles | R58: Core A&D | S58: Brazilian smart-weapons and missile-technology company acquired by UAE defense group. | T58: High | V58: Company press release
A59: ROW-125 | B59: Rest_of_World | C59: Switzerland | D59: Anavia | E59: EDGE Group | F59: UAE | G59: Private shareholders | H59: 2023-11-16 | I59: 2023-11-16 | J59: 2023 | K59: M&A | L59: Majority stake acquisition | M59: Completed | O59: USD | P59: Hardware/Software | Q59: VTOL UAS | R59: Core A&D | S59: Swiss unmanned helicopter/UAS company acquired by UAE defense group. | T59: High | V59: Company press release
A60: ROW-126 | B60: Rest_of_World | C60: Poland | D60: FLARIS | E60: EDGE Group | F60: UAE | G60: Private shareholders | H60: 2023-11-16 | I60: 2023-11-16 | J60: 2023 | K60: M&A | L60: Majority stake acquisition | M60: Completed | O60: USD | P60: Hardware | Q60: Light jet / aircraft systems | R60: Adjacent aerospace/defense | S60: Light jet/aerospace platform relevant to aerospace portfolio; weaker direct defense fit. | T60: Medium-High | V60: Company press release
A61: ROW-127 | B61: Rest_of_World | C61: Brazil | D61: Condor Non-Lethal Technologies | E61: EDGE Group | F61: UAE | G61: Private shareholders | H61: 2023-04-12 | I61: 2023-04-12 | J61: 2023 | K61: M&A | L61: Majority stake acquisition | M61: Completed | O61: USD | P61: Hardware | Q61: Non-lethal defense / public security | R61: Core defense/security | S61: Non-lethal weapons and tactical products for security and defense forces. | T61: High | V61: Company press release
A62: ROW-128 | B62: Rest_of_World | C62: Brazil | D62: AKAER | E62: EDGE Group | F62: UAE | G62: Private shareholders | H62: 2023-09-26 | I62: 2023-09-26 | J62: 2023 | K62: M&A | L62: Strategic stake | M62: Completed | O62: USD | P62: Services/Hardware | Q62: Aerospace engineering / defense systems | R62: Core aerospace/defense | S62: Brazilian aerospace engineering company; supports aircraft and defense platforms. | T62: Medium-High | V62: Company press release
B63: Israel | C63: Israel | D63: BIRD Aerosystems | E63: Ondas Holdings | F63: USA | G63: FIMI / shareholders | H63: 2026-03-11 | I63: 2026-03-11 | J63: 2026 | K63: M&A | L63: FULL | M63: Completed / announced as acquired | N63: 133 | O63: USD | P63: Hardware / Software | Q63: Airborne missile protection systems (AMPS), DIRCM, airborne ISR, mission C2 | R63: Core A&D | S63: Adds a true defense / airborne protection transaction, not cyber. Useful for airborne ISR, aircraft protection, and counter-UAS adjacency. | T63: High | U63: https://ir.ondas.com/press-releases/detail/289/ondas-acquires-bird-aerosystems-to-expand-airborne-missile | V63: Company press release + reputable press | W63: Deal value should be marked as reported by press/source support; keep as supplemental addition.
B64: Israel | C64: Israel | D64: INDO Earth Moving Ltd. | E64: Ondas Holdings | F64: USA | G64: INDO shareholders | H64: 2026-03-17 | I64: 2026-03-17 | J64: 2026 | K64: M&A | L64: FULL | M64: Completed / announced as acquired | O64: USD | P64: Hardware / Services | Q64: Military heavy engineering platforms, combat engineering vehicles, lifecycle support | R64: Core A&D / Defense services | S64: Adds non-cyber ground systems / military engineering exposure. Keep value blank to avoid mistaking program value for deal value. | T64: High | U64: https://ir.ondas.com/press-releases/detail/292/ondas-acquires-indo-earth-moving-ltd-following-its-140 | V64: Company press release | W64: Value not disclosed; do not use contract/program value as acquisition value.
B65: Israel | C65: Israel | D65: ThirdEye Systems | E65: EDGE Group | F65: UAE | G65: Public / existing shareholders | H65: 2025-01-28 | I65: Pending shareholder approvals / JV setup | J65: 2025 | K65: M&A / Minority investment | L65: MINORITY — 30% stake + JV | M65: Announced | N65: 10.3 | O65: USD | P65: Hardware / Software | Q65: Electro-optical drone/UAV detection, counter-UAS target identification | R65: Core A&D / Defense-electronics adjacent | S65: Adds a rare non-US strategic defense investment into Israeli counter-drone / EO detection technology. | T65: Medium-High | U65: https://www.calcalistech.com/ctechnews/article/t0k36tepz | V65: Reputable press | W65: Minority investment; do not count as full acquisition.
B66: Israel | C66: Israel | D66: XTEND | E66: JFB Construction Holdings | F66: USA | G66: XTEND shareholders / JFB | H66: 2026-02-17 | I66: Expected mid-2026 | J66: 2026 | K66: Other / SPAC business combination | L66: OTHER — all-stock merger / public listing | M66: Announced / expected close | N66: 1500 | O66: USD | P66: Hardware / Software | Q66: AI-enabled tactical drones, human-guided autonomous systems, defense robotics | R66: Core A&D / Public-market transaction | S66: Adds a major drone/defense robotics transaction. Treat separately from traditional M&A because it is a merger to take XTEND public. | T66: High | U66: https://www.reuters.com/business/aerospace-defense/eric-trump-invests-israeli-drone-maker-xtends-merger-with-florida-construction-2026-02-17/ | V66: Reuters / reputable press | W66: Not classic M&A; classify as Other / public-market business combination.
B67: Israel | C67: Israel | D67: Nimbus Drones Technologies and Marketing Ltd. | E67: Nukkleus Inc. | F67: USA | G67: Elad Defense LLC | H67: 2026-01-15 | I67: 2026-01-15 | J67: 2026 | K67: M&A | L67: FULL | M67: Completed at signing | O67: USD | P67: Hardware / Services | Q67: UAV solutions, Counter-UAS platforms, drone operations/training | R67: Core A&D / UAV & Counter-UAS | S67: Adds a small but very relevant Israeli UAV/counter-UAS acquisition with contract-level source details. | T67: High | U67: https://contracts.justia.com/companies/brilliant-acquisition-corp-10112/contract/1353910/ | V67: Legal contract / transaction agreement | W67: Keep value blank unless consideration is clearly stated in agreement.
B68: Israel | C68: Israel | D68: Aero Sol Aviation Solutions Ltd. | E68: Veloryx | F68: Israel | G68: Aero Sol shareholders | H68: 2026-03-15 | I68: Targeted April 2026 / pending binding agreement | J68: 2026 | K68: M&A / Majority stake | L68: Proposed 70% controlling stake | M68: Advanced negotiations / pending | N68: 9.4 | O68: USD | P68: Hardware / Software | Q68: Tactical ISR drones, sensors, C2, homeland-security unmanned systems | R68: Core/Adjacent A&D — Pending | S68: Interesting non-cyber Israeli drone/control-stake transaction, but mark pending until binding agreement/closing is confirmed. | T68: Medium | U68: https://www.jpost.com/defense-and-tech/article-889954 | V68: Reputable press | W68: Pending / advanced negotiations; do not count as completed M&A.
B69: Israel | C69: Greece | D69: Intracom Defense (IDE) | E69: Israel Aerospace Industries (IAI) | F69: Israel | G69: Intracom Holdings / shareholders | H69: 2023-05-09 | I69: Expected Q2 2023 | J69: 2023 | K69: M&A | L69: MAJORITY — 90.91% stake | M69: Signed / expected close | N69: 66 | O69: USD | P69: Hardware / Software | Q69: Missile launchers, missile subsystems, tactical communications, hybrid generation, NATO defense electronics | R69: Core A&D | S69: Adds a non-cyber Israeli-acquirer transaction. Useful only if the Israel dataset includes Israeli buyers, not just Israeli targets. | T69: Medium-High | U69: https://www.iai.co.il/press/iai-has-acquired-greek-defence-company-intracom-defence/ | V69: Company press release + press estimate | W69: Target country is Greece, not Israel; include only under Israeli-acquirer logic.
B70: Israel | C70: Israel | D70: Gadfin Aero-Logistics Systems | E70: Israel Acquisitions Corp. | F70: USA / Israel SPAC | G70: Gadfin shareholders / SPAC shareholders | H70: 2025-01-27 | I70: Expected H2 2025 / subject to approvals | J70: 2025 | K70: Other / Business combination | L70: OTHER — SPAC / business combination | M70: Announced / pending approvals | N70: 200 | O70: USD | P70: Hardware / Software | Q70: Long-range all-weather drone delivery / UAV logistics | R70: Aerospace / UAV-adjacent, not pure defense | S70: Good supplemental aerospace/UAV row, but classify separately because it is a SPAC-style business combination and not a classic defense acquisition. | T70: Medium-High | U70: https://www.unmannedsystemstechnology.com/2025/02/business-combination-agreement-to-improve-drone-delivery/ | V70: Industry press / business-combination announcement | W70: Treat as aerospace/UAV-adjacent and separate from classic M&A counts.
B71: USA | C71: USA | D71: Maxar Technologies | E71: Advent International | F71: USA | G71: Public shareholders | H71: 44911 | I71: 45049 | J71: 2023 | K71: M&A | L71: Take-private acquisition | M71: Completed | N71: 6400 | O71: USD | P71: Hardware/Software | Q71: Earth observation / geospatial intelligence | R71: Core A&D space | S71: Earth-imagery and geospatial intelligence provider used by defense and intelligence customers. | T71: High | V71: Company press release
B72: USA | C72: USA | D72: Aerojet Rocketdyne | E72: L3Harris Technologies | F72: USA | G72: Public shareholders | H72: 44913 | I72: 45135 | J72: 2023 | K72: M&A | L72: All-cash acquisition | M72: Completed | N72: 4700 | O72: USD | P72: Hardware | Q72: Rocket propulsion / missile systems / space propulsion | R72: Core A&D | S72: Large propulsion acquisition strengthening U.S. missile, space, and hypersonic capabilities. | T72: High | U72: https://investors.l3harris.com/news/news-details/2022/L3Harris-to-Acquire-Aerojet-Rocketdyne-12-18-2022/default.aspx | V72: Company press release | W72: Announced in 2022 but closed in 2023; include only if database uses completion year.
B73: USA | C73: USA | D73: BlackSignal Technologies | E73: Parsons Corporation | F73: USA | G73: Razor's Edge | H73: 2024-07-30 | I73: 2024-08 | J73: 2024 | K73: M&A | L73: Cash acquisition | M73: Completed | N73: 200 | O73: USD | P73: Software/Services | Q73: Electronic warfare / digital signal processing / intelligence | R73: Core A&D | S73: Supports defense and intelligence customers with signal processing, EW and cyber-adjacent mission capabilities. | T73: High | U73: https://investors.parsons.com/news-releases/news-release-details/parsons-acquire-blacksignal-technologies/ | V73: Company press release | W73: Cash purchase price of $200m; forecast 2025 EBITDA multiple disclosed.
B74: USA | C74: USA | D74: Electron Device Business of CPI | E74: TransDigm Group | F74: USA | G74: TJC, L.P. | H74: 2023-11-09 | I74: 2024-06-06 | J74: 2024 | K74: M&A | L74: Cash acquisition | M74: Completed | N74: 1385 | O74: USD | P74: Hardware | Q74: Aerospace & defense electronic components / subsystems | R74: Core A&D | S74: Adds mission-critical electronic components and subsystems serving aerospace and defense end markets. | T74: High | U74: https://transdigmgroupinc.gcs-web.com/news-releases/news-release-details/transdigm-completes-acquisition-electron-device-business/ | V74: Company press release | W74: Company completion page confirms transaction; deal value also referenced in company filings/releases as about $1.385bn.
B75: USA | C75: USA | D75: Trax USA Corp. | E75: AAR Corp. | F75: USA | G75: Private shareholders | H75: 2023-03-20 | I75: 2023-03-20 | J75: 2023 | K75: M&A | L75: Full acquisition | M75: Completed | N75: 120 | O75: USD | P75: Software/Services | Q75: Aircraft MRO / fleet-management software | R75: Aerospace-adjacent | S75: Aviation MRO and fleet-management software; useful for aftermarket/digital MRO trend, but less defense-specific. | T75: Medium-High | U75: https://www.sec.gov/Archives/edgar/data/1750/000141057825000519/air-20250228x10q.htm | V75: SEC filing | W75: AAR 10-Q reports $120m purchase price plus contingent consideration up to $20m.
B76: Israel | C76: Israel | D76: S.P.O. Smart Precision Optics | E76: Ondas Inc. | F76: USA | G76: Shamir Investment Entrepreneurship ACS Ltd. | H76: 2025-08-26 | I76: 2025-10-03 | J76: 2025 | K76: M&A | L76: MINORITY / controlling stake | M76: Completed | N76: 1.78 | O76: USD | P76: Hardware | Q76: Precision optics / missile-defense optics | R76: Core A&D | S76: Precision optics are relevant to electro-optical systems, missile defense and counter-drone applications. | T76: High | U76: https://ir.ondas.com/press-releases/detail/233/ondas-holdings-enters-definitive-agreement-to-acquire | V76: Company press release / SEC filing | W76: Ondas annual report states SPO acquisition completed Oct. 3, 2025; value shown from pasted list, verify against filings if used.
B77: Israel | C77: Israel | D77: Insight Intelligent Sensors | E77: Ondas Inc. | F77: USA | H77: 2025-10-29 | I77: 2025 | J77: 2025 | K77: M&A | L77: MINORITY / controlling stake | M77: Completed | N77: 3.5 | O77: USD | P77: Hardware | Q77: Electro-optical sensors / AI sensing | R77: Core A&D | S77: AI-powered electro-optical sensing strengthens counter-UAS, surveillance and early-warning capabilities. | T77: High | U77: https://www.ondas.com/post/ondas-expands-its-ai-sensing-capabilities-with-the-acquisition-of-a-controlling-interest-in-insight | V77: Company press release | W77: Value from pasted list; source confirms acquisition/relevance, value should be double-checked in filing if needed.
B78: Israel | C78: Israel | D78: Apeiro Motion | E78: Ondas Inc. | F78: USA | H78: 2025-08-18 | I78: 2025 | J78: 2025 | K78: M&A | L78: FULL | M78: Completed | N78: 12 | O78: USD | P78: Hardware | Q78: Ground robotics / fiber-optic UAV-UGV communications | R78: Core A&D | S78: Adds ground robotics and radio-independent UAV/UGV communications capabilities to Ondas Autonomous Systems. | T78: Medium-High | U78: https://ir.ondas.com/press-releases/detail/230/ondas-enters-into-definitive-agreement-to-strengthen | V78: Company press release | W78: Source confirms transaction and strategic rationale; value appears in public reporting and pasted list.
B79: Israel | C79: Israel | D79: Apeiro Motion | E79: Ondas Inc. | F79: USA | H79: 45887 | I79: 2025 | J79: 2025 | K79: M&A | L79: FULL | M79: Completed | N79: 12 | O79: USD | P79: Hardware | Q79: Ground robotics / fiber-optic UAV-UGV communications | R79: Core A&D | S79: Adds ground robotics and radio-independent UAV/UGV communications capabilities to Ondas Autonomous Systems. | T79: Medium-High | U79: https://ir.ondas.com/press-releases/detail/230/ondas-enters-into-definitive-agreement-to-strengthen | V79: Company press release | W79: Source confirms transaction and strategic rationale; value appears in public reporting and pasted list.
B80: Israel | C80: Israel | D80: Opgal | E80: Gevasol Group | F80: Israel | H80: 45870 | I80: 45870 | J80: 2025 | K80: M&A | L80: FULL | M80: Completed | N80: Not disclosed | O80: USD | P80: Hardware | Q80: Infrared / thermal imaging / electro-optics | R80: Defense-adjacent | S80: Opgal develops thermal cameras and electro-optical systems for industrial, HLS/security and defense uses; acquisition is less pure defense but relevant electro-optics. | T80: Medium-High | U80: https://www.opgal.com/blog/%D7%9B%D7%9C%D7%9C%D7%99/gevasol-acquires-opgal-to-expand-portfolio-into-advanced-emission-monitoring-and-reduction-technologies/ | V80: Company announcement | W80: Source focuses on emission monitoring; keep as defense-adjacent, not core A&D.
B81: Israel | C81: Israel | D81: Lulav Space | E81: ParaZero Technologies | F81: Israel / USA | H81: 2025-03-27 | J81: 2025 | K81: M&A / LOI | L81: OTHER | M81: LOI / pending | N81: Not disclosed | O81: USD | P81: Hardware / Software | Q81: Space robotics navigation / counter-drone technologies | R81: Aerospace/UAV-adjacent | S81: Proposed acquisition would bring space-grade navigation, counter-drone and autonomous drone technologies into ParaZero portfolio. | T81: Medium | U81: https://www.nasdaq.com/press-release/parazero-signed-non-binding-letter-intent-acquire-company-specializes-counter-drone | V81: Company / Nasdaq press release | W81: Not a closed deal; use as pipeline/watchlist unless you include LOIs.
B82: Israel | C82: Israel | D82: Get SAT | E82: Thales | F82: France | H82: 2024-05-21 | I82: 2024-05 | J82: 2024 | K82: M&A | L82: FULL | M82: Completed | N82: Not disclosed | O82: USD | P82: Hardware | Q82: Satellite terminals / satcom-on-the-move | R82: Core A&D | S82: Israeli satellite communications company providing terminals for ground, air and maritime applications; acquired by Thales. | T82: High | U82: https://breakingdefense.com/2024/05/amid-influence-of-starlink-thales-buys-israeli-company-get-sat/ | V82: Defense press / reputable press | W82: Deal value not disclosed.
B83: Israel | C83: Israel | D83: General Robotics | E83: SIG Sauer | F83: USA | H83: 2023-03-16 | I83: 2023-03-16 | J83: 2023 | K83: M&A | L83: FULL | M83: Completed | N83: Not disclosed | O83: USD | P83: Hardware | Q83: Remote weapon stations / tactical robotics / anti-drone | R83: Core A&D | S83: Israeli manufacturer of lightweight remote weapon stations and tactical robotics for manned/unmanned platforms and anti-drone applications. | T83: High | U83: https://www.sigsauer.com/blog/sig-sauer-acquires-general-robotics | V83: Company press release | W83: Value not disclosed.
B84: Israel | C84: Israel | D84: Israeli Industrial Batteries | E84: Sunlight Group | F84: Greece / EU | H84: 44971 | I84: 44971 | J84: 2023 | K84: M&A | L84: MINORITY / 51% stake | M84: Completed | N84: Not disclosed | O84: USD | P84: Hardware | Q84: Defense/industrial batteries | R84: Defense-adjacent | S84: Battery company relevant to defense/industrial power supply chain; include only as defense-adjacent, not core platform A&D. | T84: Medium | U84: https://www.linkedin.com/posts/sunlight-group-energy-storage-systems_partnership-acquisition-growth-activity-7031232903506255873-khvk | V84: Company LinkedIn / secondary source | W84: Source says Sunlight acquired 51% stake; no deal value disclosed.
B85: Israel | C85: Israel | D85: DSIT Solutions | E85: IPO / Public listing | F85: Israel | H85: 46093 | I85: 46093 | J85: 2026 | K85: IPO | L85: OTHER | M85: Completed / listed | O85: USD | P85: Hardware | Q85: Underwater defense systems / sonar / ASW | R85: Core A&D public-market transaction | S85: Rafael underwater surveillance subsidiary; sonar, diver detection, ASW and underwater security systems. | T85: Medium-High | U85: https://www.tradingview.com/symbols/TASE-DSIT/ | V85: Market data / company profile | W85: IPO/public-market row, not M&A. Deal value from pasted list was blank; fill only from prospectus/TASE if needed.
B86: Israel | C86: Israel | D86: Smart Shooter | E86: IPO / Public listing | F86: Israel | H86: 46083 | I86: 46083 | J86: 2026 | K86: IPO | L86: OTHER | M86: Completed / listed | N86: 83.8 | O86: USD | P86: Hardware | Q86: Electro-optical fire-control systems | R86: Core A&D public-market transaction | S86: Israeli defense-tech company developing SMASH electro-optical fire-control systems for small arms and drone threats. | T86: Medium-High | U86: https://en.globes.co.il/en/article-smart-shooter-raises-nis-200m-in-tase-ipo-1001536422 | V86: Reputable press | W86: Public-market pricing/IPO; not M&A. Verify USD conversion/valuation before using in totals.
B87: Israel | C87: Israel | D87: Reshef Technologies | E87: IPO / Public listing | F87: Israel | H87: 2025-12 | J87: 2025 | K87: IPO | L87: OTHER | M87: Announced / public-market process | N87: 295.12 | O87: USD | P87: Hardware | Q87: Electronic fuzes / ammunition components | R87: Core A&D public-market transaction | S87: Electronic fuze company linked to artillery, rockets, mortars and loitering munitions; highly defense-relevant. | T87: Medium | U87: https://www.ynetnews.com/business/article/byoezcrbbx | V87: Reputable press | W87: Ynet reports Aryt seeking to take Reshef public; value in pasted list may be market/public pricing and should be verified.
B88: Israel | C88: Israel | D88: RP Optical Lab | E88: IPO / Public listing | F88: Israel | H88: 2025-05 | J88: 2025 | K88: IPO | L88: OTHER | M88: Completed / listed | O88: USD | P88: Hardware | Q88: Electro-optical & thermal imaging | R88: Core A&D public-market transaction | S88: RP Optical develops electro-optical modules and thermal imaging systems for defense, HLS, medical and commercial markets. | T88: Medium | U88: https://market.tase.co.il/en/market_data/security/01222462/major_data | V88: TASE market data | W88: Deal value from pasted list blank; do not force a valuation without prospectus/TASE source.
B89: Israel | C89: Israel | D89: TSG IT Advanced Systems | E89: IPO / Public listing | F89: Israel | H89: 45516 | J89: 2024 | K89: IPO | L89: OTHER | M89: Completed / listed | N89: 16.78 | O89: USD | P89: Software | Q89: C4ISTAR / command-and-control / HLS | R89: Core A&D public-market transaction | S89: TSG provides C4ISTAR, intelligence, HLS and cyber/security systems for defense and government customers. | T89: Medium-High | U89: https://www.gornitzky.com/tsg-%D7%94%D7%A0%D7%A4%D7%A7%D7%AA-%D7%9E%D7%A0%D7%99%D7%95%D7%AA-%D7%9C%D7%A6%D7%99%D7%91%D7%95%D7%A8-ipo/ | V89: Legal advisor / IPO announcement | W89: IPO/public-market row, not M&A.
B90: Israel | C90: Israel | D90: Silynx Communications | E90: IPO / Public listing | F90: Israel / USA | H90: 2024-01 | J90: 2024 | K90: IPO | L90: OTHER | M90: Completed / listed | N90: 5 | O90: USD | P90: Hardware | Q90: Military communications headsets | R90: Core/Defense-adjacent public-market transaction | S90: Rugged tactical headset systems for military/law-enforcement communications and hearing protection. | T90: Medium | U90: https://silynxcom.com/ | V90: Company website / product source | W90: Use for relevance; IPO pricing should be verified against SEC/Nasdaq prospectus if material.
A91: EUR-001 | B91: Europe | C91: France | D91: Exxelia | E91: HEICO Corporation | F91: United States | G91: HLD Europe | H91: Not disclosed | I91: 44931 | J91: 2023 | K91: M&A | L91: Majority/control share acquisition | M91: Completed | N91: 503.996 | O91: USD | P91: Hardware | Q91: Defence Electronics & Sensors | R91: Core A&D | S91: HEICO describes Exxelia as a manufacturer of high-reliability electronic components used predominantly in aerospace and defence applications. | T91: Verified — primary source | U91: https://heico.com/wp-content/uploads/2024/04/AnnualReport_2023.pdf | V91: Verified — primary source | W91: Control acquisition, not 100%; replace the dataset's $501.55m with audited net consideration of $503.996m.
A92: EUR-002 | B92: Europe | C92: United Kingdom | D92: TP Group plc | E92: Science Group plc | F92: United Kingdom | G92: TP Group shareholders | H92: Not disclosed | I92: 44952 | J92: 2023 | K92: M&A | L92: 100% acquisition by court-approved scheme of arrangement | M92: Completed | N92: Not disclosed | O92: Not disclosed | P92: Hardware / Services | Q92: Defence Services & Engineering | R92: Core A&D | S92: Science Group identifies the acquired operations as Defence and Aerospace-focused consulting plus submarine atmosphere-management systems dependent on the UK defence market. | T92: Verified — primary source | U92: https://www.sciencegroup.com/news-detail/audited-results-for-the-year-ended-31-december-2023/ | V92: Verified — primary source | W92: Retain as a completed 100% control acquisition; value left null because cash outflow is not necessarily equivalent to enterprise value.
A93: EUR-003 | B93: Europe | C93: United Kingdom | D93: Westek Technology Ltd | E93: roda computer GmbH | F93: Germany | G93: TP Group plc | H93: Not disclosed | I93: 44955 | J93: 2023 | K93: M&A | L93: 100% share acquisition / corporate divestiture | M93: Completed | N93: Not disclosed | O93: GBP | P93: Hardware | Q93: Defence Computing & Rugged Systems | R93: Core A&D | S93: Westek manufactures rugged computers and related systems for military and other harsh-environment applications; the buyer describes it as serving defence-sector customers. | T93: Verified — primary source | U93: https://www.roda-computer.com/news/current-news/roda-acquires-the-shares-of-westek/ | V93: Verified — primary source | W93: Correct completion date is 29 January 2023, not 1 January 2023.
A94: EUR-004 | B94: Europe | C94: France | D94: Diateam | E94: CY4Gate S.p.A. | F94: Italy | G94: Not disclosed | H94: Not disclosed | I94: 44956 | J94: 2023 | K94: M&A | L94: Majority/control share acquisition | M94: Completed | N94: Not disclosed | O94: EUR | P94: Software / Services | Q94: Cyber & Digital Defence | R94: Core A&D | S94: Diateam develops cyber-range, digital-twin and cyber-warfare capabilities for government and defence customers. | T94: Verified — primary source | U94: https://www.cy4gate.com/assets/Uploads/ENG-CS-CY4gate-closing-Operazione-Diateam-def.pdf | V94: Verified — primary source | W94: Correct structure from full acquisition to acquisition of a 55.33% controlling stake.
A95: EUR-005 | B95: Europe | C95: Sweden | D95: ArcQor AB | E95: W5 Solutions AB | F95: Sweden | G95: Note AB | H95: Not disclosed | I95: 44957 | J95: 2023 | K95: M&A | L95: 100% share acquisition / corporate divestiture | M95: Completed | N95: Not disclosed | O95: Not disclosed | P95: Hardware | Q95: Power, Propulsion & Energy | R95: Core A&D | S95: ArcQor develops rugged power systems and battery chargers for defence applications and was acquired into W5's defence-technology group. | T95: Verified — primary source | U95: https://w5solutions.com/mfn_news/w5-solutions-acquires-arcqor-ab-and-issues-626-342-new-shares/ | V95: Verified — primary source | W95: Retain; transaction and control status are source-verified. No single normalized transaction value is carried into the verified dataset.
A96: EUR-006 | B96: Europe | C96: Estonia | D96: Milrem Robotics | E96: EDGE Group PJSC | F96: United Arab Emirates | G96: Founders, employees and Estonian private investors | H96: 44972 | I96: 44972 | J96: 2023 | K96: M&A | L96: Majority stake | M96: Completed | N96: Not disclosed | O96: Not disclosed | P96: Hardware / Software | Q96: UAVs & Autonomous Systems | R96: Core A&D | S96: Unmanned Ground Systems. Milrem develops and manufactures the THeMIS and Type-X robotic combat and support vehicles for NATO and allied armed forces; defence robotics is its sole business. | T96: Verified — primary source | U96: https://edgegroup.ae/news/edge-acquires-majority-stake-milrem-robotics-europes-leading-developer-robotics-and-autonomous | V96: Verified — primary source | W96: ADDED 2026-08-02: absent from the original workbook and from the audit log. Passes the strict tests — Estonian target, defence robotics as sole business, change of control. Neither party disclosed a separate legal completion date; the announcement date is used and flagged.
A97: EUR-007 | B97: Europe | C97: France | D97: CS Group | E97: Sopra Steria Group SE | F97: France | G97: Yazid Sabeg, Eric Blanc-Garin, Duna & Cie, Cira Holding and the founders of Novidy’s | H97: 44883 | I97: 44985 | J97: 2023 | K97: M&A | L97: Majority stake | M97: Completed | N97: Not disclosed | O97: EUR | P97: Software / Services | Q97: Cyber & Digital Defence | R97: Core A&D | S97: Digital services and critical systems for defence and security, space and energy. CS Group is a French defence and security prime contractor with approximately 2,500 employees. | T97: Verified — primary source | U97: https://www.soprasteria.com/newsroom/press-releases/details/sopra-steria-finalises-its-acquisition-of-a-majority-stake-in-the-share-capital-of-cs-group | V97: Verified — primary source | W97: ADDED 2026-08-02: absent from the original workbook and from the audit log, although CS Group appears in the sheet as an acquirer. Passes the strict tests — French target, defence and security critical systems as primary business, change of control completed inside the window.
A98: EUR-008 | B98: Europe | C98: France | D98: Connectiv-IT SAS | E98: Sopra Steria Group | F98: France | G98: Not disclosed | H98: Not disclosed | I98: 45020 | J98: 2023 | K98: M&A | L98: 100% share acquisition | M98: Completed | N98: Not disclosed | O98: Not disclosed | P98: Software / Services | Q98: Defence Services & Engineering | R98: Core A&D | S98: Connectiv-IT provides software and digital services for aeronautics and defence supply-chain and operational-readiness processes. | T98: Verified — primary source | U98: https://www.soprasteria.com/Content/SopraSteria/soprasteria-2023-12-31-fr-viewer.html | V98: Verified — primary source | W98: Retain; completion and 100% ownership are supported by Sopra Steria reporting.
A99: EUR-009 | B99: Europe | C99: France | D99: Aubert & Duval | E99: AD Holding (Airbus, Safran and Tikehau Capital) | F99: France | G99: Eramet | H99: Not disclosed | I99: 45044 | J99: 2023 | K99: M&A | L99: 100% share acquisition through an equally owned holding company | M99: Completed | N99: Not disclosed | O99: Not disclosed | P99: Hardware | Q99: Aerospace Materials & Components | R99: Core A&D | S99: Aubert & Duval is a strategic manufacturer of high-performance steels, superalloys, titanium and critical parts central to aerospace and defence supply chains. | T99: Verified — primary source | U99: https://www.airbus.com/en/newsroom/press-releases/2023-04-airbus-safran-and-tikehau-capital-finalise-acquisition-of-aubert | V99: Verified — primary source | W99: Confirmed omitted completed control acquisition.
A100: EUR-010 | B100: Europe | C100: Italy | D100: Innovation Design S.r.l. | E100: Foramil S.r.l. / Defence Tech Holding S.p.A. | F100: Italy | G100: Not disclosed | H100: Not disclosed | I100: 45045 | J100: 2023 | K100: M&A | L100: Majority/control share acquisition | M100: Completed | N100: Not disclosed | O100: Not disclosed | P100: Hardware / Software | Q100: Defence Electronics & Sensors | R100: Core A&D | S100: Innovation Design develops and supplies defence electronics and systems through Foramil/Defence Tech. | T100: Verified — primary source | U100: https://tinextadefence.it/en/download/29-04-2023-defence-tech-holding-through-its-subsidiary-foramil-finalises-the-acquisition-of-60-of-innovation-design-s-r-l/ | V100: Verified — primary source | W100: Correct completion date is 29 April 2023 and ownership acquired was 60%, not 100%.
...

Sheet Israel M&A NOT
A1: Count of Target / Asset | B1: Transaction Type
A2: Deal Year | B2: M&A | C2: M&A / LOI | D2: M&A / Majority stake | E2: Merger/Acquisition | F2: Other / SPAC business combination | G2: Total Result
A3: 2023 | B3: 16 | E3: 1 | G3: 17
A4: 2024 | B4: 13 | E4: 1 | G4: 14
A5: 2025 | B5: 17 | C5: 1 | E5: 4 | G5: 22
A6: 2026 | B6: 14 | D6: 1 | F6: 1 | G6: 16
A7: Total Result | B7: 60 | C7: 1 | D7: 1 | E7: 6 | F7: 1 | G7: 69

Sheet Israel M&A Deal Amounts
A1: Sum of Deal Value (USD mn) | B1: Transaction Type
A2: Deal Year | B2: M&A | C2: M&A / LOI | D2: M&A / Majority stake | E2: Merger/Acquisition | F2: Other / SPAC business combination | G2: Total Result
A3: 2023 | B3: 2884.66 | G3: 2884.66
A4: 2024 | B4: 1933.01 | G4: 1933.01
A5: 2025 | B5: 32594.4 | G5: 32594.4
A6: 2026 | B6: 28404.34 | D6: 9.4 | F6: 1500 | G6: 29913.74
A7: Total Result | B7: 65816.41 | D7: 9.4 | F7: 1500 | G7: 67325.81

Sheet Israel
A1: Deal ID | B1: Region | C1: Target Country | D1: Target / Asset | E1: Acquirer | F1: Acquirer Country | G1: Seller | H1: Announcement Date | I1: Completion Date | J1: Deal Year | K1: Transaction Type | L1: Deal Structure | M1: Deal Status | N1: Deal Value (USD mn) | O1: Currency | P1: Hardware / Software / Services | Q1: A&D Domain | R1: Inclusion Tier | S1: Relevance Rationale | T1: Reliability | U1: Source URL | V1: Source Type | W1: Notes | X1: Implied EV/Revenue | Y1: Implied EV/EBITDA | Z1: Deal Size/EBITDA | AA1: EBITDA | AB1: Deal Size/Revenue | AC1: Revenue | AD1: Deal Type 2 | AE1: Post Valuation | AF1: Deal Synopsis | AG1: Financing Status | AH1: Business Status | AI1: Investors | AJ1: Primary PitchBook Industry Code | AK1: Verticals | AL1: Description | AM1: HQ Location | AN1: Company Website
B2: Israel | C2: Israel | D2: Orbit Communication Systems | E2: Kratos Defense & Security Solutions | F2: USA | G2: Public shareholders | H2: 2025-11-04 | I2: Expected 2026 | J2: 2026 | K2: M&A | L2: Full acquisition | M2: Announced | N2: 356.3 | O2: USD | P2: Hardware | Q2: Satellite/Space | R2: Core A&D | S2: Israeli satellite-communications and airborne/ground satcom provider with defense and national-security applications. | T2: High | U2: https://www.kratosdefense.com/newsroom/kratos-to-acquire-israel-based-orbit-technologies-ltd-for-356-3-million | V2: Company / reputable press | X2: 3.81 | Y2: 17 | Z2: 19.12 | AA2: 18.63 | AB2: 4.29 | AC2: 83.03 | AE2: 356.3 | AF2: The company (TAE: ORBI) was acquired by Kratos Defense & Security Solutions (NAS: KTOS) for $356.3 million on March 17, 2026. This acquisition will deepen Kratos Defense & Security Solutions' presence in Israel and expand its reach across global defense and satellite communications markets. | AG2: Corporate Backed or Acquired | AH2: Generating Revenue | AI2: Kratos Defense & Security Solutions (NAS: KTOS) (Eric Demarco) | AJ2: Telecommunications Service Providers | AK2: Space Technology, TMT | AL2: Orbit Technologies Ltd is a provider of airborne communications, satellite-tracking, maritime, ground-station and new space solutions for commercial and government establishments. Its products include Audio Management System, Maritime SATCOM, Airborne Audio Management System, Maritime SATCOM, etc. | AM2: Netanya, Israel | AN2: www.orbit-cs-usa.com
B3: Israel | C3: Israel | D3: Omnisys | E3: Ondas Holdings | F3: USA | H3: 2026-05-18 | J3: 2026 | K3: M&A | L3: Full acquisition / stock deal | M3: Announced | N3: 200 | O3: USD | P3: Software | Q3: C4I/Mission Software | R3: Core A&D | S3: Military mission-planning and operational-optimization software for defense customers. | T3: Medium-High | U3: https://www.calcalistech.com/ctechnews/article/skbzd9dkge | V3: Business press | W3: Very recent; verify closing when announced.
B4: Israel | C4: Israel | D4: CyberArk | E4: Palo Alto Networks | F4: USA | G4: Public shareholders | H4: 2025-07-30 | I4: Expected FY2026 | J4: 2026 | K4: M&A | L4: Cash-and-stock acquisition | M4: Announced | N4: 25000 | O4: USD | P4: Software | Q4: Cybersecurity | R4: Adjacent cyber-security | S4: Large Israeli-founded cybersecurity deal; relevant to defense/security landscape but not pure aerospace/defense. | T4: High | U4: https://www.reuters.com/world/middle-east/palo-altos-25-billion-deal-cyberark-targets-rising-ai-driven-threats-2025-07-30/?utm_source=chatgpt.com | V4: Company press release
B5: Israel | C5: Israel | D5: BIRD Aerosystems | E5: Ondas Holdings | F5: USA | G5: FIMI / shareholders | H5: 2026-03-11 | I5: 2026-03-11 | J5: 2026 | K5: M&A | L5: FULL | M5: Completed / announced as acquired | N5: 133 | O5: USD | P5: Hardware / Software | Q5: Airborne Systems | R5: Core A&D | S5: Adds a true defense / airborne protection transaction, not cyber. Useful for airborne ISR, aircraft protection, and counter-UAS adjacency. | T5: High | U5: https://ir.ondas.com/press-releases/detail/289/ondas-acquires-bird-aerosystems-to-expand-airborne-missile | V5: Company press release + reputable press | W5: Deal value should be marked as reported by press/source support; keep as supplemental addition. | AF5: The company was acquired by Ondas (NAS: ONDS) for an undisclosed amount on March 11, 2026. | AG5: Formerly PE-Backed | AH5: Generating Revenue | AI5: Ondas (NAS: ONDS) (Eric Brock) | AJ5: Air | AK5: Industrials | AL5: Provider of airborne missile protection systems and airborne surveillance services for clients in commercial, governmental, military, and transnational organizations. The company's system engages in developing airborne missile protection systems and airborne surveillance, as well as information and observation applications that provide operational analysis, system design, integration, and installation through ground and flight testing, thereby enabling organizations to receive products that would protect them and ensure the security of their assets. | AM5: Herzliya, Israel | AN5: www.birdaero.com
B6: Israel | C6: Israel | D6: INDO Earth Moving Ltd. | E6: Ondas Holdings | F6: USA | G6: INDO shareholders | H6: 2026-03-17 | I6: 2026-03-17 | J6: 2026 | K6: M&A | L6: FULL | M6: Completed / announced as acquired | N6: Not disclosed | O6: USD | P6: Hardware / Services | Q6: Ground/Robotic Systems | R6: Core A&D / Defense services | S6: Adds non-cyber ground systems / military engineering exposure. Keep value blank to avoid mistaking program value for deal value. | T6: High | U6: https://ir.ondas.com/press-releases/detail/292/ondas-acquires-indo-earth-moving-ltd-following-its-140 | V6: Company press release | W6: Value not disclosed; do not use contract/program value as acquisition value. | AF6: The company was acquired by Ondas (NAS: ONDS) for an undisclosed amount on March 17, 2026. The acquisition represents an important step in the Ondas 's strategy to expand its portfolio of advanced autonomous technologies and robotic systems designed for mission-critical defense and infrastructure operations worldwide. | AG6: Corporate Backed or Acquired | AH6: Generating Revenue | AI6: Ondas (NAS: ONDS) (Eric Brock) | AJ6: Aerospace and Defense | AL6: Provider of heavy engineering equipment procurement and integration services intended to serve military and national infrastructure. The company provides sourcing, engineering integration, testing and lifecycle support of complex platforms and systems. | AM6: Maale Gilboa, Israel
B7: Israel | C7: Israel | D7: XTEND | E7: JFB Construction Holdings | F7: USA | G7: XTEND shareholders / JFB | H7: 2026-02-17 | I7: Expected mid-2026 | J7: 2026 | K7: IPO | L7: OTHER — all-stock merger / public listing | M7: Announced / expected close | N7: 1500 | O7: USD | P7: Hardware / Software | Q7: UAVs/Autonomous Systems | R7: Core A&D / Public-market transaction | S7: Adds a major drone/defense robotics transaction. Treat separately from traditional M&A because it is a merger to take XTEND public. | T7: High | U7: https://www.reuters.com/business/aerospace-defense/eric-trump-invests-israeli-drone-maker-xtends-merger-with-florida-construction-2026-02-17/ | V7: Reuters / reputable press | W7: Not classic M&A; classify as Other / public-market business combination.
B8: Israel | C8: Israel | D8: Nimbus Drones Technologies and Marketing Ltd. | E8: Nukkleus Inc. | F8: USA | G8: Elad Defense LLC | H8: 2026-01-15 | I8: 2026-01-15 | J8: 2026 | K8: M&A | L8: FULL | M8: Completed at signing | N8: 3.25 | O8: USD | P8: Hardware / Services | Q8: UAVs/Autonomous Systems | R8: Core A&D / UAV & Counter-UAS | S8: Adds a small but very relevant Israeli UAV/counter-UAS acquisition with contract-level source details. | T8: High | U8: https://contracts.justia.com/companies/brilliant-acquisition-corp-10112/contract/1353910/ | V8: Legal contract / transaction agreement | W8: Keep value blank unless consideration is clearly stated in agreement. | AC8: 0.94 | AF8: The company was acquired by Nukkleus (NAS: NUKK) for an undisclosed amount on January 16, 2026. The acquisition helps Nukkleus strengthen its defense technology portfolio. | AG8: Corporate Backed or Acquired | AH8: Generating Revenue | AI8: T3 Defense (NAS: DFNS) | AJ8: Aerospace and Defense | AL8: Provider of unmanned aerial vehicle services intended to serve defense and military organizations, public sector agencies, commercial industries, and agricultural clients. The company offers a range of services, including drone and repair laboratory operations, enterprise and consumer unmanned aerial vehicles, mapping and surveying, including orthophotos and three-dimensional models, aerial photography, red-team simulation for defense exercises, licensed drone training and certification, and counter-unmanned aerial systems research and development. | AM8: Netanya, Israel | AN8: nimbusd.co.il
B9: Israel | C9: Israel | D9: Aero Sol Aviation Solutions Ltd. | E9: Veloryx | F9: Israel | G9: Aero Sol shareholders | H9: 2026-03-15 | I9: Targeted April 2026 / pending binding agreement | J9: 2026 | K9: M&A / Majority stake | L9: Proposed 70% controlling stake | M9: Advanced negotiations / pending | N9: 9.4 | O9: USD | P9: Hardware / Software | Q9: UAVs/Autonomous Systems | R9: Core/Adjacent A&D — Pending | S9: Interesting non-cyber Israeli drone/control-stake transaction, but mark pending until binding agreement/closing is confirmed. | T9: Medium | U9: https://www.jpost.com/defense-and-tech/article-889954 | V9: Reputable press | W9: Pending / advanced negotiations; do not count as completed M&A.
B10: Israel | C10: Israel | D10: Sentry CS / Sentrycs | E10: Ondas Holdings | F10: USA | H10: 2025-11-04 | I10: 2025-11-29 | J10: 2025 | K10: M&A | L10: Full acquisition | M10: Completed | N10: 224.6 | O10: USD | P10: Software/Hardware | Q10: UAVs/Autonomous Systems | R10: Core A&D | S10: Counter-drone detection and mitigation for defense, homeland security, airports, and critical infrastructure. | T10: High | U10: https://ir.ondas.com/press-releases/detail/251/ondas-to-acquire-sentrycs-a-global-leader-in-counter-uas | V10: Company / reputable press | AB10: 20.99 | AC10: 10.7 | AE10: 224.6 | AF10: The company was acquired by Ondas Holdings (NAS: ONDS) for $224.6 million on November 17, 2025. | AG10: Formerly PE-Backed | AH10: Generating Revenue | AI10: Ondas (NAS: ONDS) (Eric Brock) | AJ10: Aerospace and Defense | AK10: Manufacturing, Robotics and Drones | AL10: Manufacturer of autonomous counter-drone systems designed to safeguard defense forces, public safety agencies and critical infrastructure from unauthorized aerial threats. The company develops protocol manipulation-based technology that detects, identifies, tracks and safely mitigates rogue drones without interference or collateral damage, enabling clients to secure their airspace. | AM10: Tel Aviv, Israel | AN10: www.sentrycs.com
B11: Israel | C11: Israel | D11: Roboteam | E11: Ondas Holdings | F11: USA | H11: 2025-11-25 | I11: 2025-12-17 | J11: 2025 | K11: M&A | L11: Full acquisition | M11: Completed | N11: 81.7 | O11: USD | P11: Hardware | Q11: Ground/Robotic Systems | R11: Core A&D | S11: Unmanned ground vehicles for military, EOD, ISR, and hazardous missions. | T11: High | U11: https://ir.ondas.com/press-releases/detail/264/ondas-completes-acquisition-of-roboteam-a-global-leader-in | V11: Company / reputable press | AF11: The company was acquired by Ondas Holdings (NAS: ONDS) for an undisclosed amount on December 17, 2025. | AG11: Formerly VC-backed | AH11: Generating Revenue | AI11: Ondas (NAS: ONDS) (Eric Brock) | AJ11: Aerospace and Defense | AK11: Advanced Manufacturing, Robotics and Drones | AL11: Developer of human-driven robot technology designed to offer tactical ground robotic systems. The company's technology designs, develops, and manufactures remote-controlled unmanned UGVs for defense, law enforcement, and public safety missions, enabling militants to get robots that address real human needs and save lives. | AM11: Petah Tikva, Israel | AN11: www.robo-team.com
B12: Israel | C12: Israel | D12: SpearUAV | E12: UVision Air | F12: Israel | H12: 2025-12-08 | J12: 2025 | K12: M&A | L12: Acquisition | M12: Announced / reported | N12: Not disclosed | O12: USD | P12: Hardware | Q12: UAVs/Autonomous Systems | R12: Core A&D | S12: Capsule-launched tactical drones/loitering systems; directly defense-relevant. | T12: Medium-High | U12: https://www.globes.co.il/news/article.aspx?did=1001528671 | V12: Business press | W12: Value undisclosed in public reporting. | AF12: The company was acquired by UVision for an undisclosed amount on November 26, 2025. The acquistion will help the company to sets a precedent for the integration of cutting-edge technologies in defense applications. | AG12: Formerly VC-backed | AH12: Generating Revenue | AI12: UVision Air (Ran Gozali) | AJ12: Aerospace and Defense | AK12: Artificial Intelligence & Machine Learning, Industrials, Robotics and Drones | AL12: Developer of encapsulated aerial weapon systems designed to support maneuvering forces across land, air, and sea operations. The company platform offers AI-enabled personal aerial weapon systems, autonomous or manually controlled deployment options, integration with manned and unmanned vehicles, mesh networking for shared intelligence, and capabilities for instant intelligence, surveillance, reconnaissance, and precision attack missions, providing military organizations and government defense agencies with enhanced battlefield effectiveness, improved operational flexibility, and greater tactical advantage in complex combat environments. | AM12: Tel Aviv, Israel | AN12: www.spearuav.com
B13: Israel | C13: Israel-founded / USA | D13: Wiz | E13: Google / Alphabet | F13: USA | H13: 2025-03-18 | I13: Pending / approvals | J13: 2025 | K13: M&A | L13: Full acquisition | M13: Announced | N13: 32000 | O13: USD | P13: Software | Q13: Cybersecurity | R13: Adjacent cyber-security | S13: Israeli-founded cloud security company; relevant as dual-use cyber/security consolidation, not core A&D. | T13: High | U13: https://blog.google/company-news/inside-google/company-announcements/google-agreement-acquire-wiz/?utm_source=chatgpt.com | V13: Company press release
B14: Israel | C14: Israel | D14: ThirdEye Systems | E14: EDGE Group | F14: UAE | G14: Public / existing shareholders | H14: 2025-01-28 | I14: Pending shareholder approvals / JV setup | J14: 2025 | K14: M&A | L14: MINORITY — 30% stake + JV | M14: Announced | N14: 10.3 | O14: USD | P14: Hardware / Software | Q14: Defense Electronics/Sensors | R14: Core A&D / Defense-electronics adjacent | S14: Adds a rare non-US strategic defense investment into Israeli counter-drone / EO detection technology. | T14: Medium-High | U14: https://www.calcalistech.com/ctechnews/article/t0k36tepz | V14: Reputable press | W14: Minority investment; do not count as full acquisition.
B15: Israel | C15: Israel | D15: Gadfin Aero-Logistics Systems | E15: Israel Acquisitions Corp. | F15: USA / Israel SPAC | G15: Gadfin shareholders / SPAC shareholders | H15: 2025-01-27 | I15: Expected H2 2025 / subject to approvals | J15: 2025 | K15: M&A | L15: OTHER — SPAC / business combination | M15: Announced / pending approvals | N15: 200 | O15: USD | P15: Hardware / Software | Q15: UAVs/Autonomous Systems | R15: Aerospace / UAV-adjacent, not pure defense | S15: Good supplemental aerospace/UAV row, but classify separately because it is a SPAC-style business combination and not a classic defense acquisition. | T15: Medium-High | U15: https://www.unmannedsystemstechnology.com/2025/02/business-combination-agreement-to-improve-drone-delivery/ | V15: Industry press / business-combination announcement | W15: Treat as aerospace/UAV-adjacent and separate from classic M&A counts.
B16: Israel | C16: USA | D16: Stellar Blu Solutions | E16: Gilat Satellite Networks | F16: Israel | H16: 2024-06-17 | I16: 2024-09-18 | J16: 2024 | K16: M&A | L16: Full acquisition | M16: Completed | N16: Not disclosed | O16: USD | P16: Hardware | Q16: Satellite/Space | R16: Adjacent A&D aerospace | S16: Aviation satcom terminal business relevant to aerospace connectivity; dual-use rather than pure defense. | T16: High | U16: https://www.gilat.com/pressreleases/gilat-completes-acquisition-of-stellar-blu-solutions-llc/ | V16: Company press release
B17: Israel | C17: Israel | D17: Noname Security | E17: Akamai Technologies | F17: USA | H17: 2024-05-07 | I17: 2024-06-25 | J17: 2024 | K17: M&A | L17: Full acquisition | M17: Completed | N17: 450 | O17: USD | P17: Software | Q17: Cybersecurity | R17: Adjacent cyber-security | S17: API-security platform acquired by major security infrastructure company; dual-use cybersecurity relevance. | T17: High | U17: https://www.akamai.com/newsroom/press-release/akamai-completes-acquisition-of-api-security-company-noname?utm_source=chatgpt.com | V17: Company press release
B18: Israel | C18: Israel | D18: Gem Security | E18: Wiz | F18: Israel-founded / USA | H18: 2024-04-10 | J18: 2024 | K18: M&A | L18: Acquisition | M18: Completed | N18: 350 | O18: USD | P18: Software | Q18: Cybersecurity | R18: Adjacent cyber-security | S18: Cloud threat-detection acquisition by Israeli-founded security platform Wiz. | T18: Medium-High | U18: https://www.calcalistech.com/ctechnews/article/bjleedj0t?utm_source=chatgpt.com | V18: Company blog / press
B19: Israel | C19: Israel | D19: Flow Security | E19: CrowdStrike | F19: USA | H19: 2024-03-05 | J19: 2024 | K19: M&A | L19: Acquisition | M19: Completed | N19: 200 | O19: USD | P19: Software | Q19: Cybersecurity | R19: Adjacent cyber-security | S19: Cloud data-security acquisition by CrowdStrike; relevant to cyber/security but not pure A&D. | T19: Medium-High | V19: Company press release | W19: Reported value from business press.
B20: Israel | C20: Israel | D20: Spera Security | E20: Okta | F20: USA | H20: 2023-12-19 | I20: 2024-02-01 | J20: 2024 | K20: M&A | L20: Acquisition | M20: Completed | N20: 110 | O20: USD | P20: Software | Q20: Cybersecurity | R20: Adjacent cyber-security | S20: Identity-security posture management; relevant to cyber/zero-trust security. | T20: High | V20: Company press release
B21: Israel | C21: Israel | D21: Silk Security | E21: Armis | F21: Israel / USA | H21: 2024-04-17 | J21: 2024 | K21: M&A | L21: Acquisition | M21: Completed | N21: 150 | O21: USD | P21: Software | Q21: Cybersecurity | R21: Adjacent cyber-security | S21: Cyber-risk prioritization platform acquired by Armis; security-adjacent. | T21: High | V21: Company press release | W21: Reported value from business press.
B22: Israel | C22: Israel | D22: Authomize | E22: Delinea | F22: USA | H22: 2024-01-09 | I22: 2024-02-01 | J22: 2024 | K22: M&A | L22: Acquisition | M22: Completed | N22: Not disclosed | O22: USD | P22: Software | Q22: Cybersecurity | R22: Adjacent cyber-security | S22: Identity-security and threat-detection acquisition; cyber-security fit. | T22: High | V22: Company press release
B23: Israel | C23: Israel | D23: Iron Drone | E23: Airobotics / Ondas Holdings | F23: Israel / USA | H23: 2023-03-06 | J23: 2023 | K23: M&A | L23: Acquisition | M23: Completed | N23: Not disclosed | O23: USD | P23: Hardware/Software | Q23: UAVs/Autonomous Systems | R23: Core A&D | S23: Counter-drone interception and autonomous drone capabilities relevant to security and defense. | T23: Medium | U23: https://ir.ondas.com/press-releases/detail/172/ondas-receives-8-0-million-purchase-order-for-iron-drone | V23: Company press release | W23: Use if source URL resolves in browser. | AF23: The company was acquired by Airobotics (TAE: AIRO) for an undisclosed amount on March 6, 2023. The acquisition integrates counter-drone technology with Airobotics's networked optimus urban drone infrastructure. | AG23: Corporate Backed or Acquired | AH23: Generating Revenue | AI23: Airobotics (Meir Kliner) | AJ23: Automation/Workflow Software | AK23: Robotics and Drones | AL23: Developer of autonomous counter-drone system catering to unmanned aircraft infrastructure. The technology is capable of being integrated into the existing detection and radar infrastructure to provide an autonomous response for the interception of hostile, small drones, which pose real threats to strategic facilities around the world. | AM23: Tel Aviv, Israel | AN23: www.irondrone.com
B24: Israel | C24: USA | D24: DataPath | E24: Gilat Satellite Networks | F24: Israel | G24: DataPath shareholders | H24: 2023-03-09 | I24: 2023-11-15 | J24: 2023 | K24: M&A | L24: Full acquisition | M24: Completed | N24: Not disclosed | O24: USD | P24: Hardware/Services | Q24: Satellite/Space | R24: Core A&D | S24: US satellite communications systems provider serving defense and government customers acquired by Israeli satcom group. | T24: High | U24: https://www.gilat.com/pressreleases/gilat-completes-acquisition-of-datapath/ | V24: Company press release
B25: Israel | C25: Israel | D25: Dig Security | E25: Palo Alto Networks | F25: USA | H25: 2023-10-31 | J25: 2023 | K25: M&A | L25: Acquisition | M25: Completed | N25: 350 | O25: USD | P25: Software | Q25: Cybersecurity | R25: Adjacent cyber-security | S25: Israeli cybersecurity acquisition; relevant to security/dual-use cyber but not pure defense. | T25: Medium-High | U25: https://www.paloaltonetworks.com/company/press/2023/palo-alto-networks-completes-acquisition-of-dig-security?utm_source=chatgpt.com | V25: Legal adviser / business press | W25: Value usually reported as $300m-$400m; use midpoint.
B26: Israel | C26: Israel | D26: Talon Cyber Security | E26: Palo Alto Networks | F26: USA | H26: 2023-11-06 | J26: 2023 | K26: M&A | L26: Acquisition | M26: Completed | N26: 625 | O26: USD | P26: Software | Q26: Cybersecurity | R26: Adjacent cyber-security | S26: Browser-security acquisition; relevant to cyber/security consolidation. | T26: Medium-High | U26: https://www.calcalistech.com/ctechnews/article/r1hd0o87a?utm_source=chatgpt.com | V26: Business press | W26: Reported value.
B27: Israel | C27: Israel | D27: Perimeter 81 | E27: Check Point Software Technologies | F27: Israel | H27: 2023-08-10 | I27: 2023-09-11 | J27: 2023 | K27: M&A | L27: Acquisition | M27: Completed | N27: 490 | O27: USD | P27: Software | Q27: Cybersecurity | R27: Adjacent cyber-security | S27: Israeli network-security/SASE acquisition; relevant to homeland-security and enterprise-cyber landscape. | T27: High | U27: https://www.checkpoint.com/press-releases/check-point-to-acquire-perimeter-81-to-deliver-the-fastest-and-most-secure-sase-solution-in-the-industry/?utm_source=chatgpt.com | V27: Company press release
B28: Israel | C28: Israel | D28: Ermetic | E28: Tenable | F28: USA | H28: 2023-09-07 | I28: 2023-10-02 | J28: 2023 | K28: M&A | L28: Acquisition | M28: Completed | N28: 265 | O28: USD | P28: Software | Q28: Cybersecurity | R28: Adjacent cyber-security | S28: Cloud security and identity-risk platform; dual-use cyber relevance. | T28: High | U28: https://www.tenable.com/press-releases/tenable-announces-intent-to-acquire-ermetic?utm_source=chatgpt.com | V28: Company press release
B29: Israel | C29: Israel | D29: Axis Security | E29: Hewlett Packard Enterprise | F29: USA | H29: 2023-03-02 | I29: 2023-03-31 | J29: 2023 | K29: M&A | L29: Acquisition | M29: Completed | N29: 500 | O29: USD | P29: Software | Q29: Cybersecurity | R29: Adjacent cyber-security | S29: Secure access / edge cybersecurity relevant to security infrastructure; not pure A&D. | T29: Medium-High | U29: https://en.globes.co.il/en/article-hpe-buys-israeli-co-axis-security-for-500m-1001440101?utm_source=chatgpt.com | V29: Company press release | W29: Reported value from business press; official release may not disclose price.
B30: Israel | C30: Israel | D30: Laminar | E30: Rubrik | F30: USA | H30: 2023-08-08 | J30: 2023 | K30: M&A | L30: Acquisition | M30: Completed | N30: 200 | O30: USD | P30: Software | Q30: Cybersecurity | R30: Adjacent cyber-security | S30: Cloud data-security acquisition; dual-use cyber relevance. | T30: High | V30: Company press release | W30: Reported value around $200m-$250m.
B31: Israel | C31: Israel | D31: Bionic | E31: CrowdStrike | F31: USA | H31: 2023-09-19 | J31: 2023 | K31: M&A | L31: Acquisition | M31: Completed | N31: 350 | O31: USD | P31: Software | Q31: Cybersecurity | R31: Adjacent cyber-security | S31: Israeli app-security company acquired by CrowdStrike; security-adjacent. | T31: High | V31: Company press release
B32: Israel | C32: Israel | D32: SCADAfence | E32: Honeywell | F32: USA | H32: 2023-07-10 | I32: 2023-08-14 | J32: 2023 | K32: M&A | L32: Acquisition | M32: Completed | N32: Not disclosed | O32: USD | P32: Software | Q32: Cybersecurity | R32: Adjacent cyber / critical infrastructure | S32: OT cybersecurity for industrial and critical infrastructure environments; strong homeland-security relevance. | T32: High | V32: Company press release
B33: Israel | C33: Israel | D33: Enso Security | E33: Snyk | F33: UK / USA | H33: 2023-06-20 | J33: 2023 | K33: M&A | L33: Acquisition | M33: Completed | N33: 32.7 | O33: USD | P33: Software | Q33: Cybersecurity | R33: Adjacent cyber-security | S33: Israeli application-security posture management acquired by Snyk; cyber-security fit. | T33: High | V33: Company press release
B34: Israel | C34: Greece | D34: Intracom Defense (IDE) | E34: Israel Aerospace Industries (IAI) | F34: Israel | G34: Intracom Holdings / shareholders | H34: 2023-05-09 | I34: Expected Q2 2023 | J34: 2023 | K34: M&A | L34: MAJORITY — 90.91% stake | M34: Signed / expected close | N34: 66 | O34: USD | P34: Hardware / Software | Q34: Defense Electronics/Sensors | R34: Core A&D | S34: Adds a non-cyber Israeli-acquirer transaction. Useful only if the Israel dataset includes Israeli buyers, not just Israeli targets. | T34: Medium-High | U34: https://www.iai.co.il/press/iai-has-acquired-greek-defence-company-intracom-defence/ | V34: Company press release + press estimate | W34: Target country is Greece, not Israel; include only under Israeli-acquirer logic.
B35: Israel | C35: Israel | D35: S.P.O. Smart Precision Optics | E35: Ondas Inc. | F35: USA | G35: Shamir Investment Entrepreneurship ACS Ltd. | H35: 2025-08-26 | I35: 2025-10-03 | J35: 2025 | K35: M&A | L35: MINORITY / controlling stake | M35: Completed | N35: 6 | O35: USD | P35: Hardware | Q35: Defense Electronics/Sensors | R35: Core A&D | S35: Precision optics are relevant to electro-optical systems, missile defense and counter-drone applications. | T35: High | U35: https://ir.ondas.com/press-releases/detail/233/ondas-holdings-enters-definitive-agreement-to-acquire | V35: Company press release / SEC filing | W35: Ondas annual report states SPO acquisition completed Oct. 3, 2025; value shown from pasted list, verify against filings if used. | AE35: 3.48 | AF35: The company was acquired by Ondas (NAS: ONDS) for approximately ILS 6 million on October 3, 2025. Ondas Holdings aims to strengthen its leadership in advanced defense technologies. | AG35: Corporate Backed or Acquired | AH35: Generating Revenue | AI35: Ondas (NAS: ONDS) (Eric Brock) | AJ35: Other Commercial Products | AK35: Augmented Reality, Manufacturing | AL35: Manufacturer and developer of precision optical components intended for various high-tech applications based in Shamir, Israel. The company designs, produces, and measures cylindrical, acylindrical, toric, atoric, and freeform optics using contour fabrication techniques, serving industries such as space, defense, medical, Augmented Reality/Visual Reality, and automotive. | AM35: Shamir, Israel | AN35: www.spo.tech
B36: Israel | C36: Israel | D36: Insight Intelligent Sensors | E36: Ondas Inc. | F36: USA | H36: 2025-10-29 | I36: 2025 | J36: 2025 | K36: M&A | L36: MINORITY / controlling stake | M36: Completed | N36: 3.5 | O36: USD | P36: Hardware | Q36: Defense Electronics/Sensors | R36: Core A&D | S36: AI-powered electro-optical sensing strengthens counter-UAS, surveillance and early-warning capabilities. | T36: High | U36: https://www.ondas.com/post/ondas-expands-its-ai-sensing-capabilities-with-the-acquisition-of-a-controlling-interest-in-insight | V36: Company press release | W36: Value from pasted list; source confirms acquisition/relevance, value should be double-checked in filing if needed. | AE36: 6.86 | AF36: The company was acquired by Ondas (NAS: ONDS) for $3.5 million on October 27, 2025. This acquisition strengthens Ondas' ability to deliver advanced autonomy and sensing across multiple domains and positions the Company for new government and commercial programs in autonomous detection and environmental intelligence. | AG36: Corporate Backed or Acquired | AH36: Generating Revenue | AI36: Ondas (NAS: ONDS) (Eric Brock) | AJ36: Aerospace and Defense | AK36: Manufacturing | AL36: Manufacturer and designer of artificial intelligence-powered electro-optical systems for real-time anomaly detection in complex environments serving the military and defence industries. The company offers technology-integrated security solutions addressing emerging needs in ISR, border security, critical infrastructure protection, and environmental resilience. | AM36: Rehovot, Israel
B37: Israel | C37: Israel | D37: Opgal | E37: Gevasol Group | F37: Israel | H37: 2025-08-01 | I37: 2025-08-01 | J37: 2025 | K37: M&A | L37: FULL | M37: Completed | N37: Not disclosed | O37: USD | P37: Hardware | Q37: Defense Electronics/Sensors | R37: Defense-adjacent | S37: Opgal develops thermal cameras and electro-optical systems for industrial, HLS/security and defense uses; acquisition is less pure defense but relevant electro-optics. | T37: Medium-High | U37: https://www.opgal.com/blog/%D7%9B%D7%9C%D7%9C%D7%99/gevasol-acquires-opgal-to-expand-portfolio-into-advanced-emission-monitoring-and-reduction-technologies/ | V37: Company announcement | W37: Source focuses on emission monitoring; keep as defense-adjacent, not core A&D. | AF37: The company was acquired by Gevasol for an undisclosed amount on August 1, 2025. The acquisition enhances Gevasol's portfolio of engineered systems and precision components. | AG37: Corporate Backed or Acquired | AH37: Generating Revenue | AI37: Gevasol (Gideon Yadin) | AJ37: Electrical Equipment | AK37: Manufacturing | AL37: Manufacturer of infrared imaging systems and optical gas detection technologies serving industrial, oil and gas, environmental, and defense sectors. The company offers optical gas imaging cameras, thermographic imaging systems, multi-spectral filters, gas quantification software, real-time streaming tools, and wireless connectivity features, helping users detect volatile organic compounds, monitor emissions, and ensure safety and compliance in harsh operating environments. | AM37: Karmiel, Israel | AN37: www.opgal.com
B38: Israel | C38: Israel | D38: Enercon Technologies | E38: Bel Fuse | F38: USA | G38: Fortissimo Capital / shareholders | H38: 2024-09-18 | I38: 2024-11-14 | J38: 2024 | K38: M&A | L38: MINORITY / controlling 80% stake | M38: Completed | N38: 324 | O38: USD | P38: Hardware | Q38: Power/Components | R38: Core A&D | S38: Enercon designs power conversion/networking solutions for military and aerospace applications; Bel acquired majority stake. | T38: High | U38: https://ir.belfuse.com/news-releases/news-release-details/bel-announces-agreement-acquire-enercon-technologies | V38: Company press release / SEC filing | W38: Use 80% stake / majority acquisition, not full acquisition. | AE38: 324 | AF38: The company was acquired by Bel Fuse (NASDAQ: BELFB) for approximately $324 million on November 14, 2024. The company will receive a contingent payout of $10 million based on earnout payments for the 2025-2026 period. The acquisition will allow Bel Fuse to extend its product portfolio, supporting the aerospace and defense markets. | AG38: Formerly PE-Backed | AH38: Generating Revenue | AI38: Bel Fuse (NAS: BELFB) (Daniel Bernstein) | AJ38: Aerospace and Defense | AK38: Manufacturing | AL38: Manufacturer of power supplies intended to serve the military, civilian aerospace and aircraft markets. The company offers ethernet switches, routers, inverters, storage devices, universal serial bus (USB) hubs and embedded accessories, enabling clients to have customized power supplies produced in accordance with specific requests and constraints. | AM38: Netanya, Israel | AN38: www.enercon.co.il
B39: Israel | C39: Israel | D39: Israeli Industrial Batteries | E39: Sunlight Group | F39: Greece / EU | H39: 2023-02-14 | I39: 2023-02-14 | J39: 2023 | K39: M&A | L39: MINORITY / 51% stake | M39: Completed | N39: Not disclosed | O39: USD | P39: Hardware | Q39: Power/Components | R39: Defense-adjacent | S39: Battery company relevant to defense/industrial power supply chain; include only as defense-adjacent, not core platform A&D. | T39: Medium | U39: https://www.linkedin.com/posts/sunlight-group-energy-storage-systems_partnership-acquisition-growth-activity-7031232903506255873-khvk | V39: Company LinkedIn / secondary source | W39: Source says Sunlight acquired 51% stake; no deal value disclosed. | AF39: The company was acquired by The Sunlight Group for an undisclosed amount on February 14, 2023. The acquisition will help in The Sunlight Group's objective for global leadership in motive power batteries for the intralogistics sector and energy storage systems for renewables and expands their geographical reach in the MENA region. | AG39: Corporate Backed or Acquired | AH39: Generating Revenue | AI39: Systems Sunlight (Lampros Bisalas) | AJ39: Electrical Equipment | AK39: Manufacturing | AL39: Manufacturer and supplier of industrial batteries catering to telecom, aerospace and defense sectors. The company offers chargers, solar systems, ups, traction, telecom, railway, special and lithium-ion batteries as well as battery room equipment. | AM39: Nahariya, Israel | AN39: eng.iib.co.il
B40: Israel | C40: Israel | D40: DSIT Solutions | E40: IPO / Public listing | F40: Israel | H40: 2026-03-12 | I40: 2026-03-12 | J40: 2026 | K40: IPO | L40: OTHER | M40: Completed / listed | N40: Not disclosed | O40: USD | P40: Hardware | Q40: Maritime Systems | R40: Core A&D public-market transaction | S40: Rafael underwater surveillance subsidiary; sonar, diver detection, ASW and underwater security systems. | T40: Medium-High | U40: https://www.tradingview.com/symbols/TASE-DSIT/ | V40: Market data / company profile | W40: IPO/public-market row, not M&A. Deal value from pasted list was blank; fill only from prospectus/TASE if needed. | AF40: The company completed its initial public offering on the Tel Aviv Stock Exchange under the ticker symbol of DSIT on March 13, 2026. | AG40: Corporate Backed or Acquired | AH40: Profitable | AJ40: Aerospace and Defense | AK40: Industrials | AL40: DSIT Solutions Ltd is a technological company specializing in underwater technology solutions. It has developed and implemented comprehensive defense and protection solutions against various underwater threats, focusing on six main types of solutions: Underwater Domain Awareness, Underwater Security, Anti-Submarine Warfare (ASW) Systems for Surface Ships, Trainers, PAR & Acoustic Signal Analysis (ASA) Systems, and Underwater Communication Systems. | AM40: Givat Shmuel, Israel | AN40: www.dsit.co.il
B41: Israel | C41: Israel | D41: Smart Shooter | E41: IPO / Public listing | F41: Israel | H41: 2026-03-02 | I41: 2026-03-02 | J41: 2026 | K41: IPO | L41: OTHER | M41: Completed / listed | N41: 65 | O41: USD | P41: Hardware | Q41: Weapons/Munitions | R41: Core A&D public-market transaction | S41: Israeli defense-tech company developing SMASH electro-optical fire-control systems for small arms and drone threats. | T41: Medium-High | U41: https://en.globes.co.il/en/article-smart-shooter-raises-nis-200m-in-tase-ipo-1001536422 | V41: Reputable press | W41: Public-market pricing/IPO; not M&A. Verify USD conversion/valuation before using in totals. | AB41: 3.03 | AC41: 27.7 | AE41: 290.09 | AF41: The company raised ILS 260 million in its initial public offering on the Tel Aviv Stock Exchange under the ticker symbol of SMSH on March 5, 2026. After the offering, the company was valued at ILS 900 million. The total proceeds, before expenses, to the company was ILS 200 million and to the selling shareholders was ILS 60 million. In the offering, the company and the selling shareholders sold shares. | AG41: Formerly VC-backed | AH41: Generating Revenue | AJ41: Aerospace and Defense | AK41: Industrials, Manufacturing | AL41: Smart Shooter Ltd is engaged in the development, production, and sale of electro-optical fire control. It develops Fire Control Systems for small arms that significantly increase weapon accuracy and lethality when engaging static and moving targets, on the ground and in the air, day and night. With effective One Shot - One Hit precision, its product line empowers defense and security forces by maximizing rifle effectiveness against enemy targets while minimizing friendly casualties and collateral damage. Based on Artificial Intelligence, Computer Vision, and Machine Learning technologies, it is also designed to interconnect with other operational resources to form a micro-tactical network. Its systems solutions are SMASH 2000L (3000), SMASH Hopper 5000, and others. | AM41: Israel | AN41: www.smart-shooter.com
A42: IL-IPO-2025-001 | B42: Israel | C42: Israel | D42: Reshef Technologies | E42: N/A – IPO | F42: N/A | G42: Aryt Industries / existing parent | H42: 45994 | J42: 2025 | K42: IPO | L42: IPO / public listing transaction | M42: Announced / In process | N42: 295.12 | O42: USD | P42: Hardware / Defense electronics | Q42: Weapons/Munitions | R42: Cybersecurity | S42: Relevant as an Israeli defense-electronics and munitions company focused on electronic fuzes; not an M&A transaction and has no acquirer. | T42: Medium – PitchBook screenshot-based; public verification recommended | U42: PitchBook export / user screenshot | V42: PitchBook | W42: No acquirer because this is an IPO/public-listing row, not M&A. Keep only if the database includes IPOs. | AF42: The company filed to go public on the Tel Aviv Stock Exchange under an undisclosed ticker symbol on December 3, 2025. They intend to sell 102,444,800 shares at a price of ILS 9.38 per share. The expected offering amount is ILS 960.93 million. | AG42: Corporation | AH42: Generating Revenue | AJ42: Aerospace and Defense | AK42: Manufacturing | AL42: Manufacturer of advanced electronic fuzes based in Or-Yehuda, Israel. The company combines in-house R&D and manufacturing to design next-generation fuzes, employing expertise in electronics, miniaturization, and ruggedized design meeting military standards. | AM42: Or-Yehuda, Israel | AN42: www.reshefuzes.com
A43: IL-MA-2024-002 | B43: Israel | C43: Israel | D43: Avalor | E43: Zscaler Inc. | F43: United States | G43: Avalor shareholders | H43: 45359 | I43: 45359 | J43: 2024 | K43: M&A | L43: Acquisition | M43: Completed | N43: 295 | O43: USD | P43: Software / Cybersecurity | Q43: Cybersecurity | R43: Tier 2 – cyber / dual-use | S43: Relevant as an Israeli cybersecurity acquisition with dual-use relevance; deal value shown in PitchBook screenshot. | T43: High – public source verified | U43: https://ir.zscaler.com/news-releases/news-release-details/future-security-risk-management-and-operations-data-and-ai | V43: Company press release + PitchBook | W43: Public source confirms Zscaler acquired Avalor; acquisition closed on March 13, 2024. PitchBook screenshot shows March 8/2024; keep PitchBook date if using PitchBook as primary. | AE43: 256.69 | AF43: The company was acquired by Zscaler (NAS: ZS) for $256.687 million on March 8, 2024. Zscaler plan to integrate this company's technology into our cloud platform. | AG43: Formerly VC-backed | AH43: Generating Revenue | AI43: Zscaler (NAS: ZS) | AJ43: Network Management Software | AK43: Cybersecurity | AL43: Developer of a data security platform designed to act as a source of truth for cybersecurity assets, controls, identities, vulnerabilities, bugs, and other data points. The company's platform can handle data from any source with its vulnerability risk management and prioritization tools and scalability, enabling security teams to aggregate, normalize, de-duplicate, and track risk data from discovery to remediation. | AM43: Ramat Gan, Israel | AN43: uvm.zscaler.com
A44: IL-IPO-2024-001 | B44: Israel | C44: Israel | D44: Gauzy Ltd. (NASDAQ: GAUZ) | E44: N/A – IPO | F44: N/A | G44: N/A | H44: 45450 | I44: 45450 | J44: 2024 | K44: IPO | L44: Initial public offering | M44: Completed | N44: 75 | O44: USD | P44: Hardware / Advanced materials / Vision systems | Q44: Vision Systems / Advanced Materials | R44: Tier 2 – dual-use adjacent | S44: Relevant as an Israeli advanced materials and vision-systems IPO with mobility-safety applications; not an M&A transaction and has no acquirer. | T44: High – public source verified | U44: https://www.gauzy.com/articles/gauzy-ltd-announces-closing-of-75-million-initial-public-offering/ | V44: Company press release + PitchBook | W44: No acquirer because this is an IPO row. Company press release confirms $75M IPO. | Z44: -1.42 | AA44: -52.9 | AB44: 0.88 | AC44: 85.28 | AE44: 323.92 | AF44: The company raised $75 million in its initial public offering on the Nasdaq stock exchange under the ticker symbol of GAUZ on June 7, 2024. A total of 4,411,765 shares were sold at $17 per share. After the offering, there was a total of 19,054,409 outstanding shares at $17 per share, valuing the company at $323.93 million. The underwriters were granted an option to purchase up to an additional 661,765 shares from the company to cover over-allotments, if any. | AG44: Formerly PE-Backed | AH44: Generating Revenue | AJ44: Electrical Equipment | AK44: Manufacturing, Nanotechnology | AL44: Gauzy Ltd is a fully integrated light and vision control company. Its products include suspended particle device and liquid crystal materials for smart glass applications and AI-powered driver assistance systems, or ADAS, solutions including camera monitoring systems. The company's operating segments are Architecture, Automotive, Safety tech, and Aeronautics. Maximum revenue is generated from its Safety tech segment, which focuses on sales of driver assistance systems for buses, coaches, recreational vehicles, and specific vehicles, such as camera and motion sensor systems, smart mirrors, and safety doors. Geographically, it derives maximum revenue from other European countries (excluding France), followed by the United States, France, Asia, Israel, and other regions. | AM44: Tel Aviv, Israel | AN44: www.gauzy.com
A45: IL-MA-2024-003 | B45: Israel | C45: Israel | D45: G1 Secure Solutions | E45: Universal Motors Israel / UMI | F45: Israel | G45: FIMI Opportunity Funds | H45: 45295 | I45: 45295 | J45: 2024 | K45: M&A | L45: Acquisition | M45: Completed | N45: 54.01 | O45: USD | P45: Services / Security services | Q45: Security services / homeland security | R45: Tier 2 – security services | S45: Relevant as an Israeli security-services acquisition; include only if the database covers broader security and HLS services beyond core defense tech. | T45: High – public source verified | U45: https://www.g1-group.com/about-us-en/ | V45: Company website / press coverage + PitchBook | W45: Public sources indicate G1 was purchased by UMI. Globes/IsraelDesks report FIMI sold its controlling stake to Universal Motors Israel. | X45: 0.22 | Y45: 2.57 | Z45: 2.67 | AA45: 20.25 | AB45: 0.23 | AC45: 237.16 | AE45: 54.01 | AF45: The company was acquired by UMI Service for ILS 200 million on January 4, 2024. | AG45: Private Equity-Backed | AH45: Profitable | AI45: UMI Service | AJ45: Security Services (B2B) | AL45: G1 Secure Solutions Ltd provides security and safety services. The company offers solutions such as physical security services, electronic security, low voltage systems, structure control, and security technologies among others. It provides its services to financial institutions, residential and office buildings, industry and defense industries, infrastructure and energy, tourism, and public space, among others. | AM45: Petah Tikva, Israel | AN45: www.g1-group.com
A46: IL-MA-2025-002 | B46: Israel | C46: Israel | D46: Solar Drone | E46: VisionWave Holdings Inc. | F46: United States | G46: BladeRanger Ltd. | H46: 46006 | I46: 46006 | J46: 2025 | K46: M&A | L46: Corporate divestiture | M46: Completed | N46: 21.6 | O46: USD | P46: Hardware / Drone systems | Q46: UAVs / Autonomous Systems | R46: Tier 1 – core defense / dual-use | S46: Relevant because drone systems are a core defense-tech and dual-use capability area; acquirer not visible in screenshot. | T46: High – public source verified | U46: https://www.nasdaq.com/press-release/visionwave-holdings-acquires-solar-drone-ltd-advancing-autonomous-systems-defense-and | V46: Press release + PitchBook | W46: Public source confirms VisionWave acquired Solar Drone from BladeRanger. This appears to be a corporate divestiture. | AD46: Corporate Divestiture | AE46: 21.6 | AF46: The company was acquired by VisionWave Holdings (NAS: VWAV) for $21.6 million on December 15, 2025. | AG46: Formerly Angel backed | AH46: Generating Revenue | AI46: VisionWave Holdings (NAS: VWAV) | AJ46: Electronic Equipment and Instruments | AK46: Artificial Intelligence & Machine Learning, Big Data, CleanTech, Climate Tech, CloudTech & DevOps, LOHAS & Wellness, Mobility Tech, Robotics and Drones | AL46: Developer of an affordable drone-based system designed to offer cloud, AI, and drone-based solar panel cleaning. The company's drone offers features like image generation, artificial intelligence, machine learning, data mining, and real-time analysis, enabling clients to have the ability to plan, monitor, maintain, secure and clean solar panels. | AM46: Petah Tiqva, Israel | AN46: www.solardrones.net
A47: IL-IPO-2024-002 | B47: Israel | C47: Israel | D47: TSG IT Advanced Systems (TAE: TSG) | E47: N/A – IPO | F47: N/A | G47: N/A | H47: 45504 | I47: 45504 | J47: 2024 | K47: IPO | L47: IPO / public listing transaction | M47: Completed | N47: 16.78 | O47: USD | P47: Software / IT systems | Q47: C4I / Mission Systems | R47: Tier 1 – core defense / defense IT | S47: Relevant as an Israeli IT and defense-systems public listing; not an M&A transaction and has no acquirer. | T47: High – public source verified | U47: https://en.globes.co.il/en/article-defense-it-co-tsg-raises-nis-62m-in-tase-ipo-1001485608 | V47: Press coverage + PitchBook | W47: No acquirer because this is an IPO/public-listing row. Public source reports TSG raised NIS 62M in a TASE IPO. | Z47: 1.38 | AA47: 12.13 | AB47: 0.21 | AC47: 78.85 | AE47: 125.01 | AF47: The company raised NIS 62 million in its initial public offering under an undisclosed symbol on the Tel Aviv Stock Exchange on July 31, 2024. | AG47: Corporation | AH47: Generating Revenue | AJ47: Business/Productivity Software | AK47: Industrials, TMT | AL47: TSG IT Advanced Systems Ltd is a provider of C4ISTAR, Intelligence, HLS, and Cyber Security solutions that develop, integrate, and deliver mission-critical, turnkey solutions to various military forces, governmental agencies, and corporations. Its line of business are Command & Control, Intelligence, IT Systems & Telecom, Cyber Security, and Homeland Security. | AM47: Or Yehuda, Israel | AN47: www.tsgitsystems.com
A48: IL-MA-2025-003 | B48: Israel | C48: Israel | D48: Tiltan Software Engineering | E48: Nukkleus Inc. | F48: United States | G48: Tiltan shareholders | H48: 46021 | I48: 46021 | J48: 2025 | K48: M&A | L48: Acquisition | M48: Completed | N48: 14 | O48: USD | P48: Software / Engineering software | Q48: C4I / Mission Systems | R48: Tier 1 – core defense / dual-use | S48: Relevant as a software-engineering transaction with potential defense mapping, simulation, or operational-software relevance; verify exact domain. | T48: High – public source verified | U48: https://www.sec.gov/Archives/edgar/data/1787518/000121390025126417/ea027122001ex99-3_nukkleus.htm | V48: SEC filing / company press release + PitchBook | W48: Public SEC filing confirms Nukkleus completed the acquisition of Tiltan Software Engineering for approximately $14M. | AE48: 14 | AF48: The company was acquired by Nukkleus (NAS: NUKK) for approximately $14 million on December 30, 2025. The acquisition gives Nukkleus a position in defense technology's fastest-growing segments. | AG48: Corporate Backed or Acquired | AH48: Generating Revenue | AI48: T3 Defense (NAS: DFNS) | AJ48: Software Development Applications | AK48: Artificial Intelligence & Machine Learning | AL48: Developer of simulation, 3D engine, generative AI, GIS, and content production solutions intended for global clients requiring advanced visualization, training, and geo-systems. The company offers tools, such as simulation platforms, automated geo-mapping, synthetic data generation, situational awareness engines, and aerial autonomy systems, supporting defense, training, and geospatial industries. | AM48: Petach Tikva, Israel | AN48: www.tiltan-se.com
A49: IL-MA-2025-004 | B49: Israel | C49: Israel | D49: Apeiro Motion | E49: Ondas Holdings Inc. | F49: United States | G49: Apeiro shareholders | H49: 45900 | I49: 45900 | J49: 2025 | K49: M&A | L49: Acquisition | M49: Completed | N49: 12 | O49: USD | P49: Hardware / Motion technology | Q49: Ground / Robotic Systems | R49: Tier 2 – dual-use adjacent | S49: Potentially relevant as motion technology can support robotics, autonomous systems, and defense-adjacent applications; verify exact defense relevance. | T49: High – public source verified | U49: https://www.sec.gov/Archives/edgar/data/1646188/000121390025084734/ea0256166-8k_ondas.htm | V49: SEC filing + PitchBook | W49: Public SEC filing confirms Ondas completed the acquisition of Apeiro Motion Ltd. on August 31, 2025. | X49: 1 | AB49: 1 | AC49: 12 | AE49: 12 | AF49: The company was acquired by Ondas (NAS: ONDS) for approximately $12 million on August 31, 2025. The acquisition demonstrates Ondas commitment to leveraging its global operating platform to deliver a portfolio of advanced, AI-enabled capabilities to critical defense and security customers. | AG49: Corporate Backed or Acquired | AH49: Generating Revenue | AI49: Ondas (NAS: ONDS) (Eric Brock) | AJ49: Aerospace and Defense | AK49: Manufacturing, Robotics and Drones | AL49: Manufacturer of robot based in Israel. The company provides products like fiber optic spools, spyder, EZAP and scout. | AM49: Tel Aviv, Israel | AN49: www.apeiro-motion.com
A50: IL-MA-2025-005 | B50: Israel | C50: Israel | D50: 4M Defense | E50: Ondas Holdings Inc. | F50: United States | G50: 4M Defense / HoldCo shareholders | H50: 45959 | I50: 45959 | J50: 2025 | K50: M&A | L50: Acquisition | M50: Completed | N50: 10.7 | O50: USD | P50: Hardware / Defense systems | Q50: Ground / Robotic Systems | R50: Tier 1 – core defense | S50: Relevant as a core defense company transaction; exact acquirer and specialization should be verified in PitchBook. | T50: High – public source verified | U50: https://www.sec.gov/Archives/edgar/data/1646188/000121390025102609/ea026245201ex99-2_ondas.htm | V50: SEC filing / company press release + PitchBook | W50: Public sources confirm Ondas acquired a controlling interest in 4M Defense. PitchBook value should be kept as PitchBook-based unless reconciled with the public cash/equity consideration. | AE50: 15.29 | AF50: The company was acquired by Ondas (NAS: ONDS) for $10.7 million on October 29, 2025. | AG50: Corporate Backed or Acquired | AH50: Generating Revenue | AI50: Ondas (NAS: ONDS) (Oshri Lugassy) | AJ50: Aerospace and Defense | AK50: Robotics and Drones | AL50: Provider of landmine and unexploded ordnance intelligence and clearance services intended to serve government, humanitarian and commercial stakeholders worldwide. The company offers geospatial data analysis, satellite imagery, drone surveys, historical threat data and field operations expertise to assess risk, plan clearance activities and support land release decisions, thereby enabling safer prioritization, reduced operational uncertainty and more efficient use of clearance resources. | AM50: Tel Aviv, Israel | AN50: www.4-mine.com
A51: IL-MA-2025-006 | B51: Israel | C51: Israel | D51: NSO Group | E51: U.S. investor group led by Robert Simonds | F51: United States | G51: NSO controlling shareholders / Omri Lavie-related ownership | H51: 45970 | I51: 45970 | J51: 2025 | K51: M&A | L51: Acquisition | M51: Completed | N51: 10 | O51: USD | P51: Software / Cyber intelligence | Q51: Cyber Intelligence | R51: Tier 1 – cyber / sensitive defense tech | S51: Relevant as a cyber-intelligence transaction, but highly sensitive and should be checked carefully before inclusion. | T51: Medium – public reporting verified; sensitive deal, verify in PitchBook | U51: https://www.calcalistech.com/ctechnews/article/s1jgvmitgx | V51: Press reporting + PitchBook | W51: Public reports say a U.S. investor group led by Robert Simonds acquired/was set to acquire control of NSO. Sensitive transaction; verify completion status and regulatory approvals before publication. | AE51: 10 | AF51: The company was acquired by Mr. Robert Simonds and other investors for $10 million on November 9, 2025. | AG51: Formerly PE-Backed | AH51: Profitable | AJ51: Network Management Software | AK51: Cybersecurity, Mobile, TMT | AL51: Developer of surveillance and security research software intended to help governments protect their people from terror and crime. The company's cybersecurity platform provides data intelligence, acquisition and analysis techniques that equip government intelligence agencies and law enforcement organizations around the world with strategic, tactical and analytical technological capabilities, ensuring the success of their operations in fighting crime and terrorism. | AM51: Herzliya, Israel | AN51: www.nsogroup.com
A52: IL-IPO-2023-001 | B52: Israel | C52: Israel | D52: ParaZero Technologies (NASDAQ: PRZO) | E52: N/A – IPO | F52: N/A | G52: N/A | H52: 45134 | I52: 45134 | J52: 2023 | K52: IPO | L52: IPO / public listing transaction | M52: Completed | N52: 9.75 | O52: USD | P52: Hardware / Drone safety systems | Q52: UAVs / Autonomous Systems | R52: Tier 1 – core defense / dual-use | S52: Relevant as an Israeli drone-safety and unmanned-systems IPO; not an M&A transaction and has no acquirer. | T52: High – public source verified | U52: https://www.nasdaq.com/press-release/parazero-technologies-ltd.-announces-pricing-of-%247.8-million-initial-public-offering | V52: Company press release / Nasdaq + PitchBook | W52: No acquirer because this is an IPO row. Public source confirms ParaZero priced its Nasdaq IPO in July 2023. | Z52: -9.49 | AA52: -1.03 | AB52: 12.83 | AC52: 0.76 | AE52: 21.79 | AF52: The company raised $9.75 million in its initial public offering on the Nasdaq stock exchange under the ticker symbol of PRZO on July 27, 2023. A total of 1,950,000 shares were sold at $4 per share. After the offering, there was a total of 6,052,418 outstanding shares (excluding the over-allotment option) at $4 per share, valuing the company at $21.79 million. The underwriters were granted an option to purchase up to an additional 292,500 shares from the company to cover over-allotments, if any. | AG52: Formerly VC-backed | AH52: Generating Revenue | AJ52: Other Hardware | AK52: Industrials, Manufacturing, Robotics and Drones | AL52: ParaZero Technologies Ltd operates as an aerospace defense company focused on the development of smart, autonomous solutions for the manned and unmanned aerial systems (UAS) industry. The Company develops, manufactures, markets, and sells counter-UAS net-launching platforms designed to protect against hostile drones in both battlefield and urban environments, precision aerial delivery systems for military applications, and smart, autonomous parachute safety systems designed to enable safe flight operations over populated areas and beyond visual line-of-sight. The Company sells its products internationally. | AM52: Kfar Saba, Israel | AN52: www.parazero.com
A53: IL-MA-2023-001 | B53: Israel | C53: Israel | D53: Airobotics | E53: Ondas Holdings Inc. | F53: United States | G53: Airobotics shareholders | H53: 44949 | I53: 44949 | J53: 2023 | K53: M&A | L53: Acquisition | M53: Completed | N53: 5.96 | O53: USD | P53: Hardware / Software / Drone systems | Q53: UAVs / Autonomous Systems | R53: Tier 1 – core defense / dual-use | S53: Relevant as an Israeli autonomous-drone transaction with direct dual-use and security relevance. | T53: High – public source verified | U53: https://ir.ondas.com/press-releases/detail/108/ondas-holdings-completes-acquisition-of-airobotics | V53: Company press release + PitchBook | W53: Public source confirms Ondas completed the acquisition of Airobotics on January 23, 2023. | AE53: 5.96 | AF53: The company was acquired by Ondas Holdings (NAS: ONDS) for $5.96 million on January 23, 2023. The acquisition enables Ondas Networks to strengthens its position in the drone market with the capabilities to design, develop, and market commercial drone solutions via the Scout System™ and Optimus System™. | AG53: Formerly VC-backed | AH53: Generating Revenue | AI53: Ondas (NAS: ONDS) (Eric Brock) | AJ53: Other Hardware | AK53: Manufacturing, Robotics and Drones | AL53: Manufacturer of autonomous unmanned aerial drones and technology solutions intended to serve government, industrial and commercial industries. The company specializes in automated data capture and analysis, real-time videos, disaster and scene assessment, compliance audits, land investigations, inspections, surveillance, progress monitoring and survey services. | AM53: Petah Tikva, Israel | AN53: www.airoboticsdrones.com
A54: IL-IPO-2024-002 | B54: Israel | C54: Israel | D54: Silynx Communications | E54: N/A – IPO | F54: N/A | G54: Existing shareholders | H54: 45303 | I54: 45308 | J54: 2024 | K54: IPO | L54: IPO / public listing transaction | M54: Completed | N54: 5 | O54: USD | P54: Hardware / Tactical communications | Q54: C4I / Mission Systems | R54: Tier 1 – core defense | S54: Relevant as an Israeli defense communications company IPO; no acquirer because this is an IPO. | T54: High – company IPO release verified | U54: https://silynxcom.com/silynxcom-ltd-announces-pricing-of-initial-public-offering/ | V54: Company press release | W54: PitchBook screenshot also showed adjacent valuation figure of 21.00. | Z54: -1.88 | AA54: -2.66 | AB54: 0.66 | AC54: 7.63 | AE54: 21 | AF54: The company raised $5 million in its initial public offering on the NYSE MKT LLC stock exchange under the ticker symbol of SYNX on January 12, 2024. A total of 1,250,000 shares were sold at $4 per share. After the offering, there was a total of 5,250,000 outstanding shares at $4 per share, valuing the company at $21 million. The underwriters were granted an option to purchase up to an additional 187,500 shares from the company to cover over-allotments, if any. | AG54: Corporation | AH54: Profitable | AJ54: Aerospace and Defense | AK54: Industrials, Manufacturing | AL54: Silynxcom Ltd is engaged in developing, manufacturing, marketing, and selling ruggedized Personal Headset Devices as well as other communications accessories, all of which have been battlefield-tested and combat proved. It specializes in developing the In-Ear Headset device, a subsegment of the Personal Headset Device market. The In-Ear Headset device is used in both training and operations by the military, law enforcement, and disaster recovery industry professionals. It also develops, markets, and sells push-to-talk devices, communication controllers, and communication device cables and connectors. Geographically, it generates the majority of its revenue from Israel. | AM54: Netanya, Israel | AN54: www.silynxcom.com
A55: IL-MA-2025-015 | B55: Israel | C55: Israel | D55: Aerospace Insurance Brokers | E55: Howden Israel | F55: Israel | G55: Aerospace Insurance Brokers shareholders | H55: 45901 | I55: 45901 | J55: 2025 | K55: M&A | L55: Acquisition | M55: Completed | N55: Not disclosed | O55: USD | P55: Services / Insurance brokerage | Q55: Insurance Services | R55: Tier 3 – adjacent aerospace services | S55: Relevant as aviation/aerospace insurance services rather than core defense technology; keep only if services are included. | T55: Medium – public transaction listing verified; limited details | U55: https://globalscopepartners.com/all-transactions/howde-aerospace-insurance-broker/ | V55: Transaction listing | W55: No deal value visible in screenshot. | AF55: The company was acquired by Howden Broking Group, a subsidiary of Howden Group Holdings, for an undisclosed amount on September 1, 2025. | AG55: Corporate Backed or Acquired | AH55: Generating Revenue | AI55: Howden Broking Group | AJ55: Insurance Brokers | AL55: Provider of aviation insurance brokerage services intended to serve commercial airlines, airports, defense contractors, and aerospace companies across Israel and international markets. The company offers tailored risk management solutions for drones, satellites, and pilot coverage through boutique expertise and multilingual claims handling, thereby ensuring high-quality protection and global service reliability. | AM55: Herzliya, Israel | AN55: www.aerospace.co.il
A56: IL-MA-2025-016 | B56: Israel | C56: Israel | D56: Caja Robotics | E56: Fives Group | F56: France | G56: Caja Robotics shareholders | H56: 45925 | I56: 45925 | J56: 2025 | K56: M&A | L56: Acquisition | M56: Completed | N56: Not disclosed | O56: USD | P56: Hardware / Software / Warehouse robotics | Q56: Warehouse Robotics | R56: Tier 2 – dual-use robotics | S56: Relevant as Israeli robotics and automation technology; adjacent/dual-use rather than strictly defense. | T56: High – company/investor source verified | U56: https://www.fivesgroup.com/ru/newspress/detail-view/fives-reinforces-its-solution-portfolio-in-intralogistics-with-caja-robotics-technologies | V56: Company press release | W56: No deal value visible in screenshot. | AF56: The company was acquired for an undisclosed amount on September 25, 2025. | AG56: Formerly VC-backed | AH56: Generating Revenue | AI56: Fives | AJ56: Logistics | AK56: Advanced Manufacturing, Artificial Intelligence & Machine Learning, Big Data, Internet of Things, Manufacturing, Robotics and Drones, Supply Chain Tech | AL56: Developer of an order fulfillment technology intended to facilitate the transition to automated warehouses with systems and flexible robotics. The company's technology improves the efficiency of e-commerce retailers who require delivery and do not require any preliminary infrastructure, enabling clients to increase order picking efficiency and storage capacity of warehouses, whilst improving the work environment of warehouse employees. | AM56: Binyamina, Israel | AN56: www.cajarobotics.com
A57: IL-MA-2025-017 | B57: Israel | C57: Israel | D57: Camel Grinding Wheels | E57: ATLANTIC GmbH Bonn | F57: Germany | G57: Camel Grinding Wheels / CGW shareholders | H57: 45905 | I57: 45905 | J57: 2025 | K57: M&A | L57: Merger / acquisition of vitrified-bonded grinding wheel operations | M57: Completed | N57: Not disclosed | O57: USD | P57: Hardware / Manufacturing / Abrasives | Q57: Industrial Supply Chain | R57: Tier 3 – aerospace/industrial adjacency | S57: Relevant as aerospace/turbine/industrial manufacturing supply-chain exposure, but not a pure defense-tech transaction. | T57: Medium – public source verified; structure should be checked in PitchBook | U57: https://www.prnewswire.com/news-releases/atlantic-expands-global-capabilities-through-strategic-integration-with-cgw-302549591.html | V57: Company press release | W57: No deal value visible in screenshot. | AF57: The company was acquired by ATLANTIC GmbH Bonn for an undisclosed amount on September 5, 2025. The combination creates a premier manufacturer of bonded abrasive products serving industry through its global sales and marketing teams. | AG57: Corporate Backed or Acquired | AH57: Generating Revenue | AI57: ATLANTIC GmbH Bonn (Marco Weber) | AJ57: Industrial Supplies and Parts | AK57: Manufacturing | AL57: Manufacturer and supplier of grinding wheels and abrasive products for aerospace, automotive, gas turbine, construction, and other industries. The company's range of grinding wheel products include vitrified, cylindrical, toolroom, mounted points, cut off wheels, grinding and flap discs, and other related products for precision grinding of ferrous and non-ferrous metals, glass, ceramics, stone, marble, steel, wood, and other materials. | AM57: Israel | AN57: www.cgwheels.com
A58: IL-MA-2023-004 | B58: Israel | C58: Israel | D58: General Robotics | E58: SIG Sauer Inc. | F58: United States | G58: General Robotics shareholders | H58: 44986 | I58: 45001 | J58: 2023 | K58: M&A | L58: Acquisition | M58: Completed | N58: Not disclosed | O58: USD | P58: Hardware / Robotics / Remote weapon stations | Q58: Ground / Robotic Systems | R58: Tier 1 – core defense | S58: Relevant as an Israeli tactical robotics and remote weapon station acquisition by a global defense manufacturer. | T58: High – company source verified | U58: https://www.sigsauer.com/blog/sig-sauer-acquires-general-robotics | V58: Company press release | W58: PitchBook screenshot showed 01-Mar-2023; SIG Sauer announced the acquisition on Mar. 16, 2023. | AF58: The company was acquired by Sig Sauer for an undisclosed amount in March 2023. | AG58: Formerly VC-backed | AH58: Generating Revenue | AI58: Sig Sauer | AJ58: Aerospace and Defense | AK58: Industrials, Manufacturing, Robotics and Drones | AL58: Developer of robotic systems designed to offer current and future operational needs in defense and homeland security. The company's robotic systems offer mobile robots that are used for military counter-terrorism operations, with the help of video data collected from most remote places, secret shelters, and bunkers, enabling security markets to avail enhanced robots to quality fight the enemy. | AM58: Beit Nehemia, Israel | AN58: www.glrobotics.com
A59: IL-MA-2024-010 | B59: Israel | C59: Israel | D59: Get SAT | E59: Thales | F59: France | G59: Get SAT shareholders | H59: 45413 | I59: 45437 | J59: 2024 | K59: M&A | L59: Acquisition | M59: Completed | N59: Not disclosed | O59: USD | P59: Hardware / Satellite communications | Q59: Satellite / Space | R59: Tier 1 – core defense / aerospace | S59: Relevant as an Israeli satellite communications acquisition by a major defense and aerospace group. | T59: High – public source verified | U59: https://runwaygirlnetwork.com/2024/05/thales-acquires-get-sat/ | V59: News / company-confirmed report | W59: No deal value visible in screenshot. | AF59: The company was acquired by Thales Group (PAR: HO) for an undisclosed amount on May 1, 2024. | AG59: Formerly VC-backed | AH59: Generating Revenue | AI59: Thales (Aerospace and Defence) (PAR: HO) | AJ59: Wireless Communications Equipment | AK59: Manufacturing | AL59: Developer of micronized satellite terminals designed to provide satellite communication for ground, air, and maritime applications. The company's micronized satellite terminals provide high-efficiency performance, control, and tracking mechanisms and are powerful and fully contained satellite terminal systems, enabling defense, commercial, and technology companies to get portable, full-duplex, wide-band satellite communications. | AM59: Rehovot, Israel | AN59: www.getsat.com
A60: IL-MA-2023-007 | B60: Israel | C60: Israel | D60: KOI Products Solutions | E60: IMCD N.V. | F60: Netherlands | G60: KOI Products Solutions shareholders | H60: 45084 | I60: 45084 | J60: 2023 | K60: M&A | L60: Acquisition of 100% of shares | M60: Completed | N60: Not disclosed | O60: USD | P60: Services / Materials distribution / Composites | Q60: Industrial Supply Chain | R60: Tier 3 – materials / industrial adjacency | S60: Relevant only if composite/materials supply-chain transactions are included; not a core defense technology target. | T60: High – company source verified | U60: https://www.imcdgroup.com/media-centre/press-releases/imcd-enters-israeli-industrial-market-with-the-acquisition-of-koi-pro-MC32PCX2I5YNA55LQN6NJEFHRWMQ | V60: Company press release | W60: No deal value visible in screenshot. | AC60: 8.41 | AF60: The company was acquired by IMCD (AMS: IMCD) for an undisclosed amount on June 7, 2023. The acquisition represents another important step into the expansion of IMCD (AMS: IMCD)'s industrial business in Israel. | AG60: Corporate Backed or Acquired | AH60: Generating Revenue | AI60: IMCD (AMS: IMCD) (Frank Schneider) | AJ60: Industrial Supplies and Parts | AK60: Manufacturing | AL60: Manufacturer of raw materials intended to offer materials that can be recycled and promote environmental value. The company's products include pigments, composite materials, adhesives, aerospace and aviation materials, enabling industries to get a wide range of raw materials. | AM60: Petah Tikva, Israel | AN60: www.koi.co.il
A61: IL-MA-2025-018 | B61: Israel | C61: Israel | D61: Light & Strong | E61: Polyrit | F61: Israel | G61: Light & Strong shareholders | H61: 45912 | I61: 46000 | J61: 2025 | K61: Merger/Acquisition | L61: Corporate divestiture / acquisition | M61: Completed | N61: Not disclosed | O61: USD | P61: Hardware / Advanced composites | Q61: Industrial Supply Chain | R61: Tier 1 – core defense / aerospace materials | S61: Relevant as an Israeli advanced-composites company serving defense/aerospace applications. | T61: Medium – source verified, date discrepancy vs screenshot | U61: https://www.israeldefense.co.il/en/node/67107 | V61: News / industry report | W61: PitchBook screenshot showed 12-Sep-2025; public source reported completion in Dec. 2025. | AD61: Corporate Divestiture | AF61: The company, a subsidiary of Lohia Group, was acquired by Polyrit for an undisclosed amount on September 12, 2025. The acquisition represents a significant step in Polyrit's growth strategy and marks its deeper expansion into the defense and aerospace sectors. | AG61: Corporate Backed or Acquired | AH61: Generating Revenue | AI61: Polyrit (Patricia Grumberg) | AJ61: Aerospace and Defense | AK61: Manufacturing | AL61: Manufacturer of composite material components intended for the aerospace and defense industries. The company specializes in aerospace and military carbon fiber and glass fiber composite components production, providing its clients with low-cost solutions for the production of small amounts of products. | AM61: Gedera, Israel | AN61: www.light-and-strong.com
A62: IL-MA-2023-008 | B62: Israel | C62: Israel | D62: NSO Group | E62: Omri Lavie / founder-controlled holding company | F62: Luxembourg / Israel | G62: Lender syndicate / prior ownership structure | H62: 44986 | I62: 44986 | J62: 2023 | K62: Merger/Acquisition | L62: Restructuring / ownership transfer | M62: Completed | N62: Not disclosed | O62: USD | P62: Software / Cyber intelligence | Q62: Cyber Intelligence | R62: Tier 2 – cyber / sensitive dual-use | S62: Relevant as a cyber-intelligence ownership change; sensitive and not a standard strategic acquisition. | T62: Medium – public reporting verified; structure complex | U62: https://www.theguardian.com/technology/2023/mar/01/one-of-nso-groups-founders-emerges-as-new-majority-owner | V62: News report | W62: Separate from the 2025 NSO acquisition row already in the file. | AC62: 150 | AF62: The company was acquired by Mr. Omri Lavie for an undisclosed amount in March 2023. | AG62: Formerly PE-Backed | AH62: Profitable | AJ62: Network Management Software | AK62: Cybersecurity, Mobile, TMT | AL62: Developer of surveillance and security research software intended to help governments protect their people from terror and crime. The company's cybersecurity platform provides data intelligence, acquisition and analysis techniques that equip government intelligence agencies and law enforcement organizations around the world with strategic, tactical and analytical technological capabilities, ensuring the success of their operations in fighting crime and terrorism. | AM62: Herzliya, Israel | AN62: www.nsogroup.com
A63: IL-IPO-2025-002 | B63: Israel | C63: Israel | D63: RP Optical Lab | E63: N/A – IPO | F63: N/A | G63: Existing shareholders / founders | H63: 45812 | I63: 45812 | J63: 2025 | K63: IPO | L63: IPO / public listing transaction | M63: Completed | N63: Not disclosed | O63: USD | P63: Hardware / Electro-optics | Q63: Defense Electronics / Sensors | R63: Tier 1 – core defense / HLS | S63: Relevant as Israeli electro-optical/thermal-imaging IPO; no acquirer because this is an IPO. | T63: High – public/TASE IPO source verified | U63: https://shimonov.com/category/prospectuses-ipos/ | V63: Legal adviser / IPO note | W63: PitchBook screenshot did not show the deal value column for this row; public source says approximately NIS 150m raised. | AA63: 6.78 | AC63: 33.47 | AF63: The company completed its initial public offering on the Tel Aviv Stock Exchange under the ticker symbol of RPOL on June 4, 2025. | AG63: Formerly PE-Backed | AH63: Generating Revenue | AJ63: Electronic Equipment and Instruments | AK63: Manufacturing | AL63: RP Optical Lab Ltd is engaged in developing and producing Electro-Optical modules. It is in the field of thermal imaging and is involved in the defense, homeland security, medical, and commercial markets. Its products and services are Opto-Mechanical Design, Lenses, Video Engine, Cameras & Cores, and Multi-Sensor Systems. | AM63: Petah Tikva, Israel | AN63: www.rp-optical-lab.com
A64: IL-MA-2024-012 | B64: Israel | C64: Israel | D64: Sital Technology | E64: Not verified in public sources | F64: Not verified | G64: Sital Technology shareholders | H64: 45413 | I64: 45413 | J64: 2024 | K64: Merger/Acquisition | L64: Acquisition | M64: Completed | N64: Not disclosed | O64: USD | P64: Hardware / Semiconductor IP / Avionics bus | Q64: Defense Electronics / Sensors | R64: Tier 1 – core aerospace electronics | S64: Relevant as avionics/defense electronics technology, but acquirer could not be verified publicly. | T64: Low – PitchBook screenshot only; public acquirer not verified | U64: PitchBook export / user screenshot | V64: PitchBook screenshot | W64: Public search found a 2024 Micross partnership, not an acquisition; verify acquirer in PitchBook. | AF64: The company was acquired for an undisclosed amount approximately in May 2024. | AG64: Formerly PE-Backed | AH64: Generating Revenue | AJ64: Aerospace and Defense | AL64: Provider of hardware and software solutions intended to serve the aerospace, defense, and space companies. The company offers solutions and services like predictive maintenance, airworthiness and mission readiness based on wiring fault detection, enabling clients to get affordable solutions for their technical tasks. | AM64: Kfar-Saba, Israel | AN64: www.sitaltech.com
A65: IL-MA-2025-023 | B65: Israel | C65: Israel | D65: Starlight Technologies | E65: Accel Solutions Ltd. | F65: Israel | G65: Starlight Technologies shareholders | H65: 46002 | J65: 2025 | K65: Merger/Acquisition | L65: Acquisition | M65: Announced / In process | N65: Not disclosed | O65: USD | P65: Hardware / RF & microwave representative services | Q65: Defense Electronics / Sensors | R65: Tier 2 – defense-electronics adjacency | S65: Relevant as Israeli RF/microwave supplier/representative organization supporting military and commercial electronics customers. | T65: Medium – public reporting verified; completion not confirmed | U65: https://en.globes.co.il/en/article-accel-solutions-buys-starlight-and-nextwave-for-nis-90m-1001528932 | V65: News report | W65: PitchBook screenshot shows pending/announced; public source says Accel is acquiring Starlight and Nextwave for up to NIS 90m. | AF65: The company reached a definitive agreement to be acquired by Accel Solutions (TAE: ACCL) for an undisclosed amount on December 11, 2025. | AG65: Pending Transaction (M&A) | AH65: Generating Revenue | AI65: Accel Solutions (TAE: ACCL) (Ronen Shor) | AJ65: Aerospace and Defense | AL65: Provider of radio frequency and microwave components and systems for the military and commercial industry in Israel. The company collaborates with various suppliers to offer standard and custom products such as security applications, remote control applications, data acquisition, an integrated data link system, video and telemetry transmitters, and more. | AM65: Tel Aviv, Israel | AN65: www.starlight.co.il
A66: IL-MA-2025-024 | B66: Israel | C66: Israel | D66: Trim Robotics | E66: UVision USA | F66: United States | G66: Trim Robotics shareholders | H66: 45754 | I66: 45754 | J66: 2025 | K66: Merger/Acquisition | L66: Acquisition | M66: Completed | N66: Not disclosed | O66: USD | P66: Hardware / Software / Loitering munitions | Q66: UAVs / Autonomous Systems | R66: Tier 1 – core defense | S66: Relevant as an Israeli loitering-munition / UAV transaction, expanding UVision's portfolio with Trim Robotics' QuadiKaze rotary-wing loitering munition capability. | T66: High – company source verified | U66: https://uvisionuav.com/uvision-acquires-trim-robotics-expanding-its-loitering-munition-capabilities/ | V66: Company press release + PitchBook screenshot | W66: PitchBook screenshot shows 07-Apr-2025 and completed status; public source confirms UVision USA announced the acquisition of Trim Robotics on April 7, 2025. | AF66: The company was acquired by UVision USA for an undisclosed amount on April 7, 2025. This strategic acquisition strengthens UVision's operational portfolio by integrating the HERO series with Trim's innovative Quadikaze missile, creating a more versatile and synergized loitering munition portfolio. | AG66: Corporate Backed or Acquired | AH66: Generating Revenue | AI66: UVision-USA (Ran Gozali) | AJ66: Aerospace and Defense | AK66: Robotics and Drones | AL66: Developer of advanced unmanned systems designed for enhancing tactical operations and precision strikes. The company offers products such as rotary-wing loitering munitions, dual-fuselage designs, and autonomous target identification systems, enabling defense forces to achieve superior maneuverability, extended mission durations, and rapid engagement capabilities in complex operational environments. | AM66: Yaqum, Israel | AN66: www.trim-robotics.com
A67: IL-MA-2025-025 | B67: Israel | C67: Israel | D67: Zickel Engineering | E67: Ondas Holdings Inc. | F67: United States | G67: Zickel Engineering shareholders | H67: 45839 | I67: 45839 | J67: 2025 | K67: Merger/Acquisition | L67: Acquisition | M67: Completed | N67: Not disclosed | O67: USD | P67: Services / Engineering / Aeronautics | Q67: Defense Engineering Services | R67: Tier 1 – core defense engineering | S67: Relevant as an Israeli defense/aeronautics engineering acquisition; Ondas described Zickel as adding an elite engineering team and expanding capabilities for defense systems. | T67: Medium-high – public source verified; deal value not visible | U67: https://ir.ondas.com/all-sec-filings/content/0001213900-25-074654/ea025264901ex99-2_ondas.htm ; https://pitchbook.com/profiles/company/144481-15 | V67: Ondas investor filing + PitchBook screenshot/profile | W67: PitchBook screenshot shows 01-Jul-2025 and completed status; Ondas public investor filing confirms Zickel was acquired in July 2025. | AF67: The company was acquired by Ondas Holdings (NAS: ONDS) for an undisclosed amount on July 1, 2025. | AG67: Corporate Backed or Acquired | AH67: Generating Revenue | AI67: Ondas (NAS: ONDS) | AJ67: Construction and Engineering | AL67: Provider of multidisciplinary engineering services intended to serve aerospace, defense, and industrial technology markets. The company develops advanced drones, navigation systems, and remote-operated vehicles while integrating hardware, software, and algorithms into turnkey services, thereby enabling clients to ramp up a project with minimal risk. | AM67: Haifa, Israel | AN67: www.zickel.net
B68: Israel | C68: Israel | D68: D-Fend Solutions | E68: Motorola Solutions | F68: United States | G68: Not disclosed | H68: 46174 | J68: 2026 | K68: M&A | L68: Definitive agreement to acquire | M68: Announced / Pending completion | N68: 1500 | O68: USD | P68: Hardware & Software | Q68: Counter-UAS / Drone Defense | R68: Tier 1 | S68: Major strategic acquisition of an Israeli counter-UAS company with non-kinetic RF cyber-takeover technology, reflecting demand for multilayered drone-defense solutions. | T68: High | U68: https://www.motorolasolutions.com/newsroom/press-releases/motorola-solutions-to-acquire-dfend-solutions.html | V68: Official company press release | W68: Purchase price of $1.5B. Transaction subject to required regulatory approvals and customary closing conditions; expected to close in Q4 2026.
B69: Israel | C69: Israel | D69: Mentee Robotics | E69: Mobileye Global (NAS: MBLY) | F69: Israel / USA | H69: 46059 | I69: 46059 | J69: 2026 | K69: M&A | L69: Full acquisition | M69: Completed | N69: 900 | O69: USD | P69: Hardware | Q69: Ground/Robotic Systems | R69: Core A&D | S69: Developer of AI-powered humanoid robots for autonomous automation; acquired by Mobileye for advanced robotics and AI capabilities. | T69: High | V69: Company / reputable press | AE69: 900 | AF69: The company was acquired by Mobileye Global (NAS: MBLY), a subsidiary of Intel (NAS: INTC), for $900 million on February 6, 2026. | AG69: Formerly VC-backed | AH69: Generating Revenue | AI69: Mobileye Global (NAS: MBLY) (Amnon Shashua) | AJ69: Other Hardware | AK69: Advanced Manufacturing, Artificial Intelligence & Machine Learning, Robotics and Drones | AL69: Developer of AI-powered humanoid robots designed to redefine humanoid automation by delivering highly adaptable, autonomous robots. The company integrates robotics, sensing and artificial intelligence into a humanoid robot with human-like dexterity and perception, enhancing productivity and daily operations, enabling businesses with warehouses to automate tasks such as lifting and carrying heavy objects, organizing and packing. | AM69: Herzliya, Israel | AN69: www.menteebot.com
B70: Israel | C70: Israel | D70: KOI | E70: Palo Alto Networks (NAS: PANW) | F70: USA | H70: 46126 | I70: 46126 | J70: 2026 | K70: M&A | L70: Full acquisition | M70: Completed | N70: 300 | O70: USD | P70: Software | Q70: Cybersecurity | R70: Adjacent cyber-security | S70: Developer of suspicious IDE extension analysis platform for securing software supply chain from malicious VSCode extensions. | T70: High | V70: Company / reputable press | AE70: 300 | AF70: The company was acquired by Palo Alto Networks (NAS: PANW) for $300 million on April 14, 2026. | AG70: Formerly VC-backed | AH70: Generating Revenue | AI70: Palo Alto Networks (NAS: PANW) (Lee Klarich) | AJ70: Network Management Software | AK70: Artificial Intelligence & Machine Learning, Cybersecurity, SaaS, Supply Chain Tech | AL70: Developer of a suspicious IDE extension analysis platform designed to secure the software supply chain from malicious and risky VSCode extensions. The company's platform continuously analyzes extensions listed on the Visual Studio Code marketplace to detect malicious, risky, or vulnerable third-party extensions quickly and automates it with API access, enabling clients with cyber risk and vulnerability detection. | AM70: Tel Aviv, Israel | AN70: www.koi.ai
B71: Israel | C71: Israel | D71: DFSL | E71: BiomX (ASE: PHGE) | F71: Israel / USA | H71: 46125 | J71: 2026 | K71: M&A | L71: Acquisition | M71: Announced / In Progress | N71: 9.29 | O71: USD | P71: Hardware | Q71: Defense Electronics/Sensors | R71: Core A&D | S71: Manufacturer of precision detection technologies for defense applications; advanced sensing systems and analytical tools. | T71: Medium-High | V71: Company / reputable press | W71: Pending / announced as definitive agreement. | AE71: 15.48 | AF71: The company reached a definitive agreement to be acquired by BiomX (ASE: PHGE) for $9.29 million on April 13, 2026. The acquisition expands BiomX's defense portfolio with aligned capabilities designed to integrate across detection, analysis, and response, reinforcing its position in artificial intelligence enabled security systems. | AG71: Pending Transaction (M&A) | AH71: Generating Revenue | AI71: BiomX (ASE: PHGE) (Michael Oster) | AJ71: Aerospace and Defense | AK71: Manufacturing | AL71: Manufacturer of precision detection technologies intended for defense applications. The company offers advanced sensing systems, analytical tools, and data-driven detection capabilities. | AM71: Akko, Israel | AN71: www.dfs-ltd.com
B72: Israel | C72: Israel | D72: Cyclops Security | E72: Check Point Software Technologies (NAS: CHKP) | F72: Israel | H72: 46065 | I72: 46065 | J72: 2026 | K72: M&A | L72: Full acquisition | M72: Completed | O72: USD | P72: Software | Q72: Cybersecurity | R72: Adjacent cyber-security | S72: Israeli cybersecurity company acquired by Check Point; cyber risk and exposure management platform. | T72: High | V72: Company / reputable press | W72: Deal value not disclosed. | AF72: The company was acquired by Check Point Software Technologies for an undisclosed amount on February 12, 2026. | AG72: Formerly VC-backed | AH72: Generating Revenue | AI72: Check Point Software Technologies (NAS: CHKP) | AJ72: Network Management Software | AK72: Artificial Intelligence & Machine Learning, Cybersecurity | AL72: Operator of a cybersecurity platform intended to fortify an organization's cybersecurity defenses, safeguarding valuable and sensitive assets. The company's platform collects metadata from the cybersecurity stack and develops artificial intelligence algorithms that enhance agility and facilitate getting context on every entity in the organization, enabling security practitioners and security teams to reduce their mean time to detect and time to repair and focus on their critical cyber risk. | AM72: Tel Aviv, Israel | AN72: www.cyclops.security
B73: Israel | C73: Israel | D73: C.M. Composite Materials | E73: VisionWave Holdings (NAS: VWAV) | F73: USA | H73: 46073 | J73: 2026 | K73: M&A | L73: Acquisition | M73: Announced / In Progress | N73: 2.5 | O73: USD | P73: Hardware | Q73: Manufacturing | R73: Adjacent A&D | S73: Israeli composite materials manufacturer; acquisition adds advanced materials capabilities to VisionWave portfolio. | T73: Medium | V73: Company / reputable press | X73: 0.28 | AB73: 0.14 | AC73: 17.3 | AE73: 4.9 | AF73: The company reached a definitive agreement to be acquired by VisionWave Holdings (NAS: VWAV) for $2.5 million on February 20, 2026. | AG73: Pending Transaction (M&A) | AH73: Generating Revenue | AI73: VisionWave Holdings (NAS: VWAV) (Doug Davis) | AJ73: Aerospace and Defense | AK73: Manufacturing, Robotics and Drones | AL73: Manufacturer of composite parts and assemblies intended for aerospace, civil, and defense applications. The company offers UAVs, drones, radomes, tooling, and parts for its customers, thereby helping them to maintain structural strength and performance requirements. | AM73: Modiin, Israel | AN73: www.c-mltd.com
B74: Israel | C74: Israel | D74: Maradin | E74: Energy Technologies (ASX: EGY) | F74: Australia | H74: 46104 | I74: 46104 | J74: 2026 | K74: M&A | L74: Full acquisition | M74: Completed | O74: USD | P74: Hardware | Q74: Defense Electronics/Sensors | R74: Adjacent A&D | S74: Israeli technology company acquired by Australian Energy Technologies. | T74: Medium | V74: Company / reputable press | W74: Deal value not disclosed. | AF74: The company was acquired by Energy Technologies (ASX: EGY) for an undisclosed amount on March 23, 2026. The acquisition positions Cogenic as a developer of full laser projection optical engineering, with applications ranging from ultra-near eye and direct retina displays to defence, aerospace, virtual reality (VR), augmented reality (AR), and lifestyle markets. | AG74: Corporate Backed or Acquired | AH74: Generating Revenue | AI74: Energy Technologies (Australia) (ASX: EGY) | AJ74: Electrical Equipment | AK74: Industrials, Manufacturing, TMT | AL74: Manufacturer of miniature laser scanning projectors intended to serve automotive, consumer electronics, and sensor markets worldwide. The company offers various products, including MEMS mirrors, mirror-to-laser synchronization chips, and scanning mirror controllers to the medical and defense industries. | AM74: Yokneam, Israel | AN74: www.maradin.co.il
B75: Israel | C75: Israel | D75: Visual Layer | E75: Camtek (NAS: CAMT) | F75: Israel | H75: 46126 | J75: 2026 | K75: M&A | L75: Acquisition | M75: Announced / In Progress | O75: USD | P75: Software | Q75: Defense Electronics/Sensors | R75: Adjacent A&D | S75: Israeli AI-powered visual data platform acquired by Camtek; machine vision and imaging capabilities. | T75: Medium | V75: Company / reputable press | W75: Deal value not disclosed. | AF75: The company reached a definitive agreement to be acquired by Camtek (NAS: CAMT) for an undisclosed amount on April 14, 2026. The acquisition will help the company to marks a significant step up in the depth and pace of its development. | AG75: Pending Transaction (M&A) | AH75: Generating Revenue | AI75: Camtek (NAS: CAMT) (Rafi Amit) | AJ75: Media and Information Services (B2B) | AK75: Artificial Intelligence & Machine Learning, Big Data, SaaS | AL75: Developer of a visual intelligence platform intended to support forensic search and investigation across video and imagery. The company's platform offers multimodal search, graph-based correlation, and traceable audit-ready outputs, enabling investigators and analysts to connect entities and scenes across secure deployments with defensible results. | AM75: Tel Aviv, Israel | AN75: www.visual-layer.com
B76: Israel | C76: Israel | D76: Advanced Real-Time Systems | E76: TSG IT Advanced Systems (TAE: TSG) | F76: Israel | H76: 45292 | I76: 45292 | J76: 2024 | K76: M&A | L76: Full acquisition | M76: Completed | O76: USD | P76: Software / Hardware | Q76: C4I/Mission Software | R76: Core A&D | S76: Israeli advanced real-time systems company acquired by TSG IT; strengthens C4ISTAR and defense systems integration capabilities. | T76: Medium-High | V76: Company / reputable press | W76: Deal value not disclosed. | AF76: The company was acquired by TSG IT Advanced Systems (TAE: TSG) for an undisclosed amount approximately in 2024. | AG76: Corporate Backed or Acquired | AH76: Generating Revenue | AI76: TSG IT Advanced Systems (TAE: TSG) | AJ76: Electrical Equipment | AK76: Manufacturing | AL76: Manufacturer of real-time electronic monitoring systems intended to support mission-critical surveillance and operational readiness. The company specializes in defense-related hardware and software such as testers, computers, isolators, splitters, and voltage filters, thereby enabling enhanced situational awareness, threat detection, and decision-making. | AM76: Yavne, Israel | AN76: www.arts.co.il
B77: Israel | C77: Israel | D77: Solar Drone | E77: BladeRanger (TAE: BLRN) | F77: Israel | H77: 45470 | I77: 45470 | J77: 2024 | K77: M&A | L77: Full acquisition | M77: Completed | O77: USD | P77: Hardware | Q77: UAVs/Autonomous Systems | R77: Adjacent dual-use | S77: Drone-based solar panel cleaning system acquired by BladeRanger; subsequently divested to VisionWave Holdings in 2025. | T77: Medium | V77: Company / reputable press | W77: Deal value undisclosed. Company later re-acquired by VisionWave (Dec 2025). | AF77: The company was acquired by BladeRanger (TAE: BLRN) for an undisclosed amount on June 27, 2024. | AG77: Formerly Angel backed | AH77: Generating Revenue | AI77: BladeRanger (TAE: BLRN) (Oded Fruchtman) | AJ77: Electronic Equipment and Instruments | AK77: Artificial Intelligence & Machine Learning, Big Data, CleanTech, Climate Tech, CloudTech & DevOps, LOHAS & Wellness, Mobility Tech, Robotics and Drones | AL77: Developer of an affordable drone-based system designed to offer cloud, AI, and drone-based solar panel cleaning. The company's drone offers features like image generation, artificial intelligence, machine learning, data mining, and real-time analysis, enabling clients to have the ability to plan, monitor, maintain, secure and clean solar panels. | AM77: Petah Tiqva, Israel | AN77: www.solardrones.net
B78: Israel | C78: Israel | D78: Comtech Satellite & Space Communications segment | E78: Gilat Satellite Networks | F78: Israel | G78: Comtech Telecommunications Corp. | H78: 46188 | J78: 2026 | K78: Merger/Acquisition | L78: Asset / business-segment acquisition | M78: Announced / Pending regulatory approval | N78: 157.5 | O78: USD | P78: Hardware / Software / Services | Q78: Satellite communications / space communications | S78: Israeli acquirer purchasing a US satellite and space communications business with defense and space infrastructure relevance; expands Gilat’s defense communications and US market presence | T78: High | U78: https://www.gilat.com/pressreleases/gilat-to-acquire-comtechs-satellite-space-communications-segment-creating-a-leading-provider-of-advanced-defense-and-satellite-communications-solutions/

Sheet USA
A1: Deal ID | B1: Region | C1: Target Country | D1: Target / Asset | E1: Acquirer | F1: Acquirer Country | G1: Seller | H1: Announcement Date | I1: Completion Date | J1: Deal Year | K1: Transaction Type | L1: Deal Structure | M1: Deal Status | N1: Deal Value (USD mn) | O1: Currency | P1: Implied EV/Revenue | Q1: Implied EV/EBITDA | R1: Deal Size/EBITDA | S1: EBITDA | T1: Deal Size/Revenue | U1: Revenue | V1: Deal Type 2 | W1: Post Valuation | X1: Deal Synopsis | Y1: Financing Status | Z1: Business Status | AA1: Investors | AB1: Primary PitchBook Industry Code | AC1: Verticals | AD1: Description | AE1: HQ Location | AF1: Company Website
A2: USA-001 | B2: USA | C2: USA | D2: Qorvo (NAS: QRVO) | E2: Skyworks Solutions | H2: 45957 | J2: 2025 | K2: Merger/Acquisition | M2: Announced/In Progress | N2: 22000 | O2: USD | P2: 2.79 | Q2: 16.87 | R2: 36.33 | S2: 605.58 | T2: 6.01 | U2: 3663.07 | W2: 22000 | X2: The company reached a definitive agreement to be acquired by Skyworks Solutions (NAS: SWKS) for $22 billion on October 27, 2025. The acquisition will strengthen Skyworks' ability to meet growing customer demand across mobile and diversified broad markets. | Y2: Pending Transaction (M&A) | Z2: Profitable | AA2: Skyworks Solutions (NAS: SWKS) (Philip Brace) | AB2: General Purpose Semiconductors | AC2: Manufacturing, TMT | AD2: Qorvo represents the combined entity of RF Micro Devices and TriQuint Semiconductor, which merged in January 2015. The company specializes in radio frequency filters, power amplifiers, and front-end modules used in many of the world's most advanced smartphones. Qorvo also has a suite of products sold into a variety of non-smartphone end markets, such as wireless base stations, cable TV and networking equipment, and infrastructure and military applications. | AE2: Greensboro, NC | AF2: www.qorvo.com
A3: USA-002 | B3: USA | C3: USA | D3: Spirit Aero Systems | E3: Boeing | H3: 45999 | J3: 2025 | K3: Merger/Acquisition | M3: Completed | N3: 8495.46 | O3: USD | P3: 1.49 | R3: -4.38 | S3: -1940.8 | T3: 1.33 | U3: 6393.6 | W3: 8495.46 | X3: The company was acquired by Boeing (NYS: BA) for $8.495 billion on December 8, 2025. Bringing Spirit and Boeing together will enable greater integration of both companies' manufacturing and engineering capabilities, including safety and quality systems. | Y3: Formerly PE-Backed | Z3: Generating Revenue | AA3: Boeing (NYS: BA) (Robert Ortbeg) | AB3: Aerospace and Defense | AC3: Manufacturing | AD3: Spirit AeroSystems manufactures aerostructures, particularly fuselages, cockpits, wing sections, engine pylons, and nacelles for commercial and military aircraft. The company was spun out of Boeing in 2005 to become the largest independent supplier of aerostructures for commercial aircraft. Boeing and Airbus are the firm's primary customers-Boeing represented roughly 60% and Airbus roughly 20% of revenue in recent years. The company is highly exposed to Boeing's beleaguered 737 program, which accounts for nearly half the company's revenue. The company plans to be acquired by and reintegrated into Boeing by the end of 2025. | AE3: Wichita, KS | AF3: www.spiritaero.com
A4: USA-003 | B4: USA | C4: USA | D4: National Instruments | E4: Emerson Electric | H4: 45210 | J4: 2023 | K4: Merger/Acquisition | M4: Completed | N4: 8200 | O4: USD | P4: 4.82 | T4: 4.82 | U4: 1700 | W4: 8200 | X4: The company was acquired by Emerson Electric (NYS: EMR) for $8.2 billion on October 11, 2023. The acquisition will result in increasing growth, cohesiveness and end market diversification across Emerson's portfolio. | Y4: Corporate Backed or Acquired | Z4: Generating Revenue | AA4: Emerson Electric (NYS: EMR) (Surendralal Karsanbhai) | AB4: Electronic Equipment and Instruments | AD4: National Instruments provides testing and measurement equipment and integrated, software-led solutions to serve high-complexity automated testing in late product development. NI serves a long tail of more than 30,000 customers in myriad end markets but focuses on the semiconductor, transportation, and aerospace and defense verticals. | AE4: Austin, TX | AF4: www.ni.com
A5: USA-004 | B5: USA | C5: USA | D5: Space & Mission Systems | E5: BAE Systems | H5: 45338 | J5: 2024 | K5: Merger/Acquisition | M5: Completed | N5: 5500 | O5: USD | P5: 2.5 | Q5: 17.74 | R5: 17.74 | S5: 310 | T5: 2.5 | U5: 2200 | V5: Corporate Divestiture | W5: 5500 | X5: The company was acquired by BAE Systems (LON: BA.) for $5.5 billion on February 16, 2024. This acquisition will enable BAE Systems to offer a broader range of products and differentiated technologies across spacecraft, instruments, ground systems, sensors, tactical systems, operations, data analytics, and other defense and civil systems. The company was renamed Space & Mission Systems following the acquisition. | Y5: Formerly Accelerator/Incubator backed | Z5: Generating Revenue | AA5: BAE Systems (LON: BA.) | AB5: Aerospace and Defense | AC5: Manufacturing, Space Technology | AD5: Developer of aerospace systems intended to offer space exploration products. The company is engaged in offering space-based instruments and sensors, tactical electro-optical, antennas, microwave systems and aerospace components, along with technical services such as engineering services and technical support co-located with customers like modeling and simulation, geospatial intelligence processing and exploitation, systems engineering, space situational awareness and threat detection, avionics software support and other related services, helping space agencies with critical missions. | AE5: Boulder, CO | AF5: www.ballaerospace.com
A6: USA-005 | B6: USA | C6: USA | D6: L3Harris Missile Unit (Aerospace and Defence) | E6: L3 Harris Technologies | H6: 45135 | J6: 2023 | K6: Merger/Acquisition | M6: Completed | N6: 4715 | O6: USD | P6: 1.93 | Q6: 25.9 | R6: 27.56 | S6: 171.1 | T6: 2.06 | U6: 2292.8 | W6: 4715 | X6: The company was acquired by L3 Harris Technologies (NYS: LHX) for $4.71 billion on July 28, 2023. This acquisition enables L3Harris to drive continuous process improvement, enhance business operations and elevate the performance of crucial national assets. | Y6: Corporate Backed or Acquired | Z6: Generating Revenue | AA6: L3 Harris Technologies (NYS: LHX) (Christopher Kubasik) | AB6: Aerospace and Defense | AC6: Industrials, Manufacturing, Space Technology, TMT | AD6: Manufacturer of aerospace and defense products based in El Segundo, California. The company produces driving and launch systems for defense and space applications, weapons, and weapons systems for tactical missions. | AE6: El Segundo, CA | AF6: www.aerojetrocketdyne.com
A7: USA-006 | B7: USA | C7: USA | D7: BlueHalo | E7: AeroVironment | H7: 45778 | J7: 2025 | K7: Merger/Acquisition | M7: Completed | N7: 3484.95 | O7: USD | P7: 3.48 | T7: 3.48 | U7: 1000 | W7: 3484.95 | X7: The company was acquired by AeroVironment (NAS: AVAV) for $3.48 billion on May 1, 2025. The acquisition will help to advance AeroVironment as the combined company as a global defense technology leader across air, land, sea, space, and cyber. | Y7: Formerly PE-Backed | Z7: Generating Revenue | AA7: AeroVironment (NAS: AVAV) (Wahid Nawabi) | AB7: Government | AC7: Manufacturing, TMT | AD7: Manufacturer of advanced engineering products for the national security community. The company offers products including autonomous systems, test instruments, laser weapons, rate sensors and extended reality products as well as services in the domain of space superiority, directed energy, air and missile defense, cyber, specialized training and simulation and technical expertise from research and development through deployment, helping to address the complex challenges of clients critical missions and reestablish national security posture in the near-peer contested arena. | AE7: Arlington, VA | AF7: www.bluehalo.com
A8: USA-007 | B8: USA | C8: USA | D8: Reorganized ISA | E8: SES | H8: 45855 | J8: 2025 | K8: Merger/Acquisition | M8: Completed | N8: 3100 | O8: USD | W8: 3100 | X8: The company was acquired by SES (LUX: SESGL) for $3.1 billion on July 17, 2025. The acquisition helps SES to leverage its skilled teams with deep vertical expertise to deliver integrated multi-orbit, multi-band satellite and connectivity solutions to businesses and governments around the world. | Y8: Formerly PE-Backed | Z8: Generating Revenue | AA8: SES (LUX: SESGL) (Adel Al-Saleh) | AB8: Telecommunications Service Providers | AC8: Mobile, Robotics and Drones | AD8: Operator of integrated satellite and terrestrial network providing communications services for telecommunications operators, media companies, and internet service providers. The company offers diversified communications services such as 5G software-defined networks, satellite networks, terrestrial networks and C-bank resource centers, enabling clients to avail global coverage services. | AE8: McLean, VA | AF8: www.intelsat.com
A9: USA-008 | B9: USA | C9: USA | D9: ARKA Group | E9: CACI International | H9: 46090 | J9: 2026 | K9: Merger/Acquisition | M9: Completed | N9: 2600 | O9: USD | W9: 2600 | X9: The company was acquired by CACI International (NYS: CACI) for $2.6 billion on March 9, 2026. | Y9: Formerly PE-Backed | Z9: Generating Revenue | AA9: CACI International (NYS: CACI) (John Mengucci) | AB9: Aerospace and Defense | AC9: Manufacturing, SaaS, Space Technology | AD9: Developer of a space technology platform intended to strengthen visionary aerospace and defense companies. The company offers technologies for national security space, defense, space science, and communication systems, thereby enabling Earth reconnaissance satellites to deliver imagery that helped avert the Cuban missile crisis, end the Cold War, and keep nations and allies safe. | AE9: Danbury, CT | AF9: www.arka.org
A10: USA-009 | B10: USA | C10: USA | D10: ILC Dover (Frederica) | E10: Ingersoll Rand | H10: 45446 | J10: 2024 | K10: Merger/Acquisition | M10: Completed | N10: 2424.7 | O10: USD | W10: 2424.7 | X10: The company was acquired by Ingersoll Rand (NYS: IR) for $2424.7 million on March 25, 2024. The acquisition extends its portfolio in sustainable end markets, including life sciences, food and beverage, medical and wastewater treatment. The company will receive contingent payout of $75 million. | Y10: Formerly PE-Backed | Z10: Profitable | AA10: Ingersoll Rand (NYS: IR) (Vicente Reynal) | AB10: Other Devices and Supplies | AC10: HealthTech, Manufacturing | AD10: Designer and manufacturer of engineered products for pharmaceutical, personal care, food and beverage, chemical, aerospace, healthcare, and government agencies. The company's products include enclosures, automated dispensing units, blenders, canisters, charge bags, cones, fasteners, drum liners, drum sleeves, isolators, mixers, lifting jars, tray dryers, and other related products. | AE10: Frederica, DE | AF10: www.ilcdover.com
A11: USA-010 | B11: USA | C11: USA | D11: Multiven | E11: PhotonAI | H11: 45811 | J11: 2025 | K11: Merger/Acquisition | M11: Completed | N11: 2200 | O11: USD | W11: 2200 | X11: The company was acquired by PhotonAI for $2.2 billion on June 3, 2025. The acquisition helps PhotonAI to becomes the builder and the guardian of Africa's AI future-securing it end-to-end for the age of intelligent economies, digital governance and data sovereignty. | Y11: Corporate Backed or Acquired | Z11: Generating Revenue | AA11: PhotonAI (Peter Alfred-Adekeye) | AB11: Systems and Information Management | AC11: Internet of Things | AD11: Provider of cyber-defense and software maintenance services intended for all internet network hardware. The company offers various services such as software integrity maintenance, monetization, IT asset management, cyber attack isolation, creating device profiles, managing devices and tasks, hardware replacement and task visibility. | AE11: Palo Alto, CA | AF11: www.multiven.com
A12: USA-011 | B12: USA | C12: USA | D12: SpartanNash | E12: C&S Wholesale Grocers | H12: 45922 | J12: 2025 | K12: Merger/Acquisition | M12: Completed | N12: 2025.36 | O12: USD | P12: 0.2 | Q12: 13.02 | R12: 13.57 | S12: 149.2 | T12: 0.21 | U12: 9693.07 | W12: 2025.36 | X12: The company was acquired by C&S Wholesale Grocers for $2.025 billion on September 22, 2025. The merger will enable the combined company to more efficiently serve customers and communities across the United States. | Y12: Corporate Backed or Acquired | Z12: Generating Revenue | AA12: C&S Wholesale Grocers (Eric Winn) | AB12: Distributors/Wholesale | AD12: SpartanNash Co is a food solutions company that delivers the ingredients. Its principal business activities include, distributing grocery products to a diverse group of independent and chain retailers, its corporate-owned retail stores, and U.S. military commissaries and exchanges; as well as operating a fresh produce distribution network and the Family private label brand. The company operates in two segments: Retail and Wholesale. Majority of the revenue is earned from its Wholesale segment which uses a multi-channel sales approach to distribute national brand and private brand products to independent retailers, national accounts, food service distributors, e-commerce providers, and the Company's corporate owned retail stores. | AE12: Byron Center, MI | AF12: www.spartannash.com
A13: USA-012 | B13: USA | C13: USA | D13: Amphenol CIT | E13: Amphenol | H13: 45433 | J13: 2024 | K13: Merger/Acquisition | M13: Completed | N13: 2025 | O13: USD | P13: 92.05 | T13: 92.05 | U13: 22 | V13: Corporate Divestiture | W13: 2025 | X13: The company, a subsidiary of Carlisle Companies (NYS: CSL), was acquired by Amphenol (NYS: APH) for $2.025 billion on May 21, 2024. The acquisition enhances Amphenol's product offerings for highly engineered harsh environment interconnect solutions and will enable it to deliver a more comprehensive technology offering for our customers in the commercial air, defense and industrial markets. | Y13: Corporate Backed or Acquired | Z13: Generating Revenue | AA13: Amphenol (NYS: APH) (Richard Norwitt) | AB13: Connectivity Products | AC13: Manufacturing | AD13: Manufacturer of electrical products intended to cater to the aerospace, military, space, test and measurement, industrial, and medical technology markets. The company designs and produces wire and cable assemblies, fiber optic systems, specialty connectors, sensors, racks, trays, and installation kits with precision engineering and robust integration, thereby enabling reliable connectivity in harsh and mission-critical environments. | AE13: Saint Augustine, FL | AF13: www.amphenol-cit.com
A14: USA-013 | B14: USA | C14: USA | D14: Precision Aviation Group | E14: VSE | H14: 46147 | J14: 2026 | K14: Merger/Acquisition | M14: Completed | N14: 2025 | O14: USD | P14: 3.29 | Q14: 135 | R14: 135 | S14: 15 | T14: 3.29 | U14: 615 | W14: 2025 | X14: The company was acquired by VSE (NAS: VSEC) for an estimated $2.025 billion on May 5, 2026. The company will receive a contingent payout of $125 million linked to adjusted EBITDA performance. | Y14: Formerly PE-Backed | Z14: Generating Revenue | AA14: VSE (Aerospace and Defense) (NAS: VSEC) (John Cuomo) | AB14: Aerospace and Defense | AC14: Manufacturing | AD14: Manufacturer of aircraft parts and a provider of maintenance, repair and overhaul (MRO) services intended for rotary and fixed-wing aircraft. The company provides repairs and sales support services for avionics, instruments, electronics and electrical accessories used in helicopters and turboprop aircraft internationally to the aerospace and defense industry. | AE14: Atlanta, GA | AF14: www.precisionaviationgroup.com
A15: USA-014 | B15: USA | C15: USA | D15: Aechelon Technology | E15: Shield AI | H15: 46106 | J15: 2026 | K15: Merger/Acquisition | M15: Announced/In Progress | N15: 2000 | O15: USD | W15: 12700 | X15: The company reached a definitive agreement to be acquired by Shield AI for $2 billion on March 25, 2026. | Y15: Pending Transaction (M&A) | Z15: Generating Revenue | AA15: Shield AI (Gary Steele) | AB15: Aerospace and Defense | AC15: SaaS, Virtual Reality | AD15: Developer of a defense software designed for simulation and geo-specific databases, supporting both manned and unmanned systems across all major Department of War service branches. The company's three-dimensional (3D) platform offers optical simulation image generation, associated specific visual and sensor databases, realistic 3D models and related integration features, enabling its clients to train both warfighters and autonomous systems in hyper-realistic, physics-based synthetic environments. | AE15: South San Francisco, CA | AF15: www.aechelon.com
A16: USA-015 | B16: USA | C16: USA | D16: Viasat (Military Communications Unit) | E16: L3 Harris Technologies | H16: 44929 | J16: 2023 | K16: Merger/Acquisition | M16: Completed | N16: 1974 | O16: USD | V16: Corporate Divestiture | W16: 1974 | X16: The Military Communications Unit of ViaSat (NAS: VSAT) was acquired by L3 Harris Technologies (NYS: LHX) for $1.974 billion on January 3, 2023. The acquisition enables L3 Harris Technologies to better align with U.S. defense spending priorities like cybersecurity and sensors. | Y16: Corporate Backed or Acquired | Z16: Generating Revenue | AA16: L3 Harris Technologies (NYS: LHX) (Christopher Kubasik) | AB16: Telecommunications Service Providers | AD16: Provider of secure communication systems catering to the military sector. The company provides secured sharing of voice and data and is integrated on military aircraft, ground vehicles, surface vessels and operating bases. | AE16: CA
A17: USA-016 | B17: USA | C17: USA | D17: Power Solutions (United States) | E17: Dycom Industries | H17: 46014 | J17: 2025 | K17: Merger/Acquisition | M17: Completed | N17: 1950 | O17: USD | P17: 1.95 | T17: 1.95 | U17: 1000 | W17: 1950 | X17: The company was acquired by Dycom Industries (NYS: DY) for an estimated $1.95 billion on December 23, 2025. The purchase consideration comprised of approximately $1.63 billion of cash, including an estimated working capital adjustment, and approximately 1.0 million shares of Dycom common stock. With this acquisition, Dycom Industries diversifies its business and significantly enhances the potential to generate long-term growth and value creation. | Y17: Corporate Backed or Acquired | Z17: Generating Revenue | AA17: Dycom Industries (NYS: DY) (Daniel Peyovich) | AB17: Construction and Engineering | AD17: Provider of electrical contracting services for mission-critical environments based in Bowie, Maryland. The company offers designing, building, construction, testing, and maintenance services for hospitals, data centers, medical laboratories, telecommunications centers, and government and military institutions. | AE17: Bowie, MD | AF17: powersolutions-llc.com
A18: USA-017 | B18: USA | C18: USA | D18: CAES | E18: Honeywell | H18: 45534 | J18: 2024 | K18: Merger/Acquisition | M18: Completed | N18: 1930 | O18: USD | V18: Corporate Divestiture | W18: 1930 | X18: The company, a subsidiary of Cobham was acquired by Honeywell (NAS: HON) for $1.930 billion on August 30, 2024. The acquisition enhances Honeywell's defense technology solutions across land, sea, air and space, including new electromagnetic defense solutions for end-to-end radio frequency (RF) signal management. | Y18: Corporate Backed or Acquired | Z18: Generating Revenue | AA18: Honeywell (NAS: HON) (Vimal Kapur) | AB18: Aerospace and Defense | AC18: Manufacturing | AD18: Manufacturer of advanced electronics intended to support critical missions in the aerospace and defense industry. The company offers products such as antennas, missile flight instrumentation, precision positioning systems, RF assemblies and subsystems, RF microwaves and components. | AE18: Arlington, VA | AF18: caes.com
A19: USA-018 | B19: USA | C19: USA | D19: Collins Aerospace (Flight Control and Actuation Business) | E19: Safran | H19: 45859 | J19: 2025 | K19: Merger/Acquisition | M19: Completed | N19: 1800 | O19: USD | V19: Corporate Divestiture | W19: 1800 | X19: The company was acquired by Safran (Paris) (PAR: SAF) for $1.8 billion on July 21, 2025. | Y19: Corporate Backed or Acquired | Z19: Generating Revenue | AA19: Safran (Paris) (PAR: SAF) | AB19: Aerospace and Defense | AC19: Manufacturing | AD19: Manufacturer of flight controls, high-lift systems, nacelle and stabilizer actuators intended for commercial and business aviation aircraft. | AE19: Arlington, VA
A20: USA-019 | B20: USA | C20: USA | D20: Consolidated Aerospace Manufacturing | E20: Howmet Aerospace | H20: 46118 | J20: 2026 | K20: Merger/Acquisition | M20: Completed | N20: 1800 | O20: USD | P20: 4.39 | T20: 4.39 | U20: 410 | V20: Corporate Divestiture | W20: 1800 | X20: The company, a subsidiary of Stanley Black & Decker (NYS: SWK), was acquired by Howmet Aerospace (NYS: HWM) for $1.80 billion on April 6, 2026. | Y20: Formerly PE-Backed | Z20: Generating Revenue | AA20: Howmet Aerospace (NYS: HWM) (John Plant) | AB20: Aerospace and Defense | AC20: Industrials, Manufacturing | AD20: Manufacturer of fitting systems and supplying components catering to the aerospace industry. The company's systems and products include high and low-pressure fluid fittings, precision-machined hardware, fasteners, fitting systems, and allied components for the aerospace, marine, nuclear, and other critical industries. | AE20: Brea, CA | AF20: www.camaerospace.com
A21: USA-020 | B21: USA | C21: USA | D21: StandardAero (NYS: SARO) | H21: 45567 | J21: 2024 | K21: IPO | M21: Completed | N21: 1440 | O21: USD | R21: 2.54 | S21: 567.81 | T21: 0.29 | U21: 4985.32 | W21: 8027.08 | X21: The company raised $1.44 billion in its initial public offering on the New York Stock Exchange under the ticker symbol of SARO on October 2, 2024. A total of 60,000,000 shares were sold at $24 per share. After the offering, there was a total of 334,461,630 outstanding shares (excluding the over-allotment option) priced at $24 per share, valuing the company at $8.03 billion. The total proceeds, before expenses, to the company was $1.28 billion and to the selling shareholders was $162 million. In the offering, the company sold 53,250,000 shares and the selling shareholders sold 6,750,000 shares. The underwriters were granted an option to purchase up to an additional 9,000,000 shares from the selling shareholders to cover over-allotments, if any. | Y21: Private Equity-Backed | Z21: Generating Revenue | AB21: Aerospace and Defense | AC21: Industrials | AD21: StandardAero is one of the largest independent providers of maintenance, repair, and overhaul services for aircraft engines. It supports leading engine platforms in the commercial, military, and business jet end markets, securing licenses from original equipment manufacturers to perform work on their respective engine families. The company organizes itself into two reportable segments: engine services and component repair Services. As a go-to MRO partner for both engine manufacturers and aircraft operators, StandardAero operates a global network of service facilities, with most of its revenue generated in North America and Europe. | AE21: Scottsdale, AZ | AF21: www.standardaero.com
A22: USA-021 | B22: USA | C22: USA | D22: CPI Electron Device Business | E22: TransDigm Group | H22: 45449 | J22: 2024 | K22: Merger/Acquisition | M22: Completed | N22: 1385 | O22: USD | V22: Corporate Divestiture | W22: 1385 | X22: The company, a subsidiary of CPI International, was acquired by TransDigm Group (NYS: TDG) for an estimated $1.385 billion on June 6, 2024. | Y22: Corporate Backed or Acquired | Z22: Generating Revenue | AA22: TransDigm Group (NYS: TDG) (Kevin Stein) | AB22: Aerospace and Defense | AC22: Manufacturing | AD22: Manufacturer of electronic components and subsystems primarily serving the aerospace and defense market. | AE22: Beverly, MA | AF22: www.cpi-edb.com
A23: USA-022 | B23: USA | C23: USA | D23: Applied Technical Services (Georgia) | E23: SGS | H23: 46034 | J23: 2026 | K23: Merger/Acquisition | M23: Completed | N23: 1336.77 | O23: USD | W23: 1336.77 | X23: The company was acquired by SGS (SWX: SGSN) for CHF 1.062 billion on January 12, 2026. | Y23: Formerly PE-Backed | Z23: Generating Revenue | AA23: SGS (SWX: SGSN) (Geraldine Picaud) | AB23: Other Commercial Services | AD23: Provider of consulting engineering, testing, and inspection services serving aerospace, automotive, construction, defense, manufacturing, and nuclear industries. The company specializes in uncovering facts in metallurgy and materials testing, chemical analysis, non-destructive testing, forensic and consulting engineering, fire and explosion investigations, and calibration services, enabling clients to get required advice and consultations on industrial projects. | AE23: Marietta, GA | AF23: www.atslab.com
A24: USA-023 | B24: USA | C24: USA | D24: Azure Summit Technology | E24: CACI International | H24: 45595 | J24: 2024 | K24: Merger/Acquisition | M24: Completed | N24: 1310.2 | O24: USD | W24: 1310.2 | X24: The company was acquired by CACI International (NYS: CACI) for $1.31 billion on October 30, 2024. The acquisition is compelling both strategically and financially and enhances CACI International offerings in areas of enduring national security priorities and also brings an installed base of fielded mature technology. | Y24: Corporate Backed or Acquired | Z24: Generating Revenue | AA24: CACI International (NYS: CACI) (John Mengucci) | AB24: Aerospace and Defense | AD24: Operator of an RF engineering company intended to serve the defense, wireless communication, open architecture, Satcom, radio astronomy, spectrum monitoring and critical asset protection sectors. The company provides a wide range of multi-channel software-defined radio solutions for applications including wireless communication, critical asset protection, satellite communications, spectral monitoring and analysis, radio astronomy and defense systems that can be tailored to meet a variety of requirements for bandwidth, dynamic range, number of channels and computational resources, to deliver cutting-edge solutions for its customers. | AE24: Fairfax, VA | AF24: www.azuresummit.com
A25: USA-024 | B25: USA | C25: USA | D25: Belcan | E25: Cognizant Technology Solutions | H25: 45530 | J25: 2024 | K25: Merger/Acquisition | M25: Completed | N25: 1308 | O25: USD | P25: 1.64 | T25: 1.64 | U25: 800 | W25: 1308 | X25: The company was acquired by Cognizant Technology Solutions (NAS: CTSH) for $1.308 billion on August 26, 2024. The acquisition strengthens Cognizant's engineering capabilities, builds on its leadership in the Internet of Things (IoT) and Digital Engineering practice areas, and increases its presence in the high-growth aerospace and defense (A&D) services market. As a part of the transaction, the company paid $1,195 million in cash, net of cash acquired, and issued 1,470,589 shares of our Class A common stock, valued at $113 million. | Y25: Formerly PE-Backed | Z25: Generating Revenue | AA25: Cognizant Technology Solutions (NAS: CTSH) (Ravi Kumar Singisetti) | AB25: Human Capital Services | AD25: Provider of engineering project management and technical staffing services intended to serve the aerospace, automotive, industrial, pharmaceutical, electronics, and government sectors. The company is engaged in providing engineering consultancy, supply chain services, data analytics, and technical recruiting services with the support of an experienced team of employees, enabling clients to get services that are flexible, scalable, and cost-effective. | AE25: Cincinnati, OH | AF25: www.belcan.com
A26: USA-025 | B26: USA | C26: USA | D26: Arxis (NAS: ARXS) | H26: 46128 | J26: 2026 | K26: IPO | M26: Completed | N26: 1134 | O26: USD | R26: 3.08 | S26: 368.05 | T26: 0.68 | U26: 1679.85 | W26: 11321.26 | X26: The company raised $1.13 billion in its initial public offering on the Nasdaq stock exchange under the ticker symbol of ARXS on April 16, 2026. A total of 40,500,000 class A shares (excluding the over-allotment option) were sold at $28 per class A share. After the offering, there was a total of 404,330,766 outstanding shares (excluding the over-allotment option) priced at $28 per share, valuing the company at $11.32 billion. The underwriters were granted an option to purchase up to an additional 6,075,000 class A shares from the company to cover over-allotments, if any. | Y26: Private Equity-Backed | Z26: Profitable | AB26: Electrical Equipment | AC26: Manufacturing | AD26: Arxis Inc designs and manufactures proprietary electronic and mechanical components used in applications that require performance in extreme environments. The company operates in two reportable segments: i) Electronic Components: It provides specialized, engineered electronic components and interconnect solutions, including connectors, cable assemblies, microelectronic packaging, RF and microwave products, power products, sensors, capacitors and resistors. and ii) Mechanical Components: It provides precision and self-lubricating bearings, seals, springs, gaskets and ducting, and radar absorbing materials. The majority of the company's revenue is derived from the Mechanical Components segment. Geographically, it generates the maximum revenue from the United States. | AE26: Bloomfield, CT | AF26: www.arxis.com
A27: USA-026 | B27: USA | C27: USA | D27: Edge Autonomy | E27: Redwire | H27: 45821 | J27: 2025 | K27: Merger/Acquisition | M27: Completed | N27: 1024.73 | O27: USD | P27: 5.26 | T27: 5.26 | U27: 195 | W27: 1024.73 | X27: The company was acquired by Redwire (NYS: RDW) for $1.025 billion on June 13, 2025. | Y27: Formerly PE-Backed | Z27: Generating Revenue | AA27: Redwire (NYS: RDW) (Peter Cannito) | AB27: Aerospace and Defense | AC27: Manufacturing, Robotics and Drones | AD27: Manufacturer of unmanned aircraft vehicles intended for the government and private companies including the navy and aerospace. The company specializes in autonomous flight control software, avionics, ground control station software, systems integration, design engineering, imaging payloads and airframe fabrication, providing endurance and performance of a diverse set of customer missions in challenging environments with minimal requirements on the ground. | AE27: San Luis Obispo, CA | AF27: www.edgeautonomy.io
A28: USA-027 | B28: USA | C28: USA | D28: FARO Technologies | E28: AMETEK | H28: 45859 | J28: 2025 | K28: Merger/Acquisition | M28: Completed | N28: 1023.7 | O28: USD | P28: 2.45 | Q28: 30.22 | R28: 37.05 | S28: 27.63 | T28: 3 | U28: 341.05 | V28: Public to Private | W28: 1023.7 | X28: The company was acquired by AMETEK (NYS: AME) for $ 1023.7 million on July 21, 2025 through a public-to-private transaction. | Y28: Formerly PE-Backed | Z28: Generating Revenue | AA28: AMETEK (NYS: AME) (David Zapico) | AB28: Other Hardware | AC28: 3D Printing, Artificial Intelligence & Machine Learning, Manufacturing | AD28: Developer of artificial intelligence machinery and systems intended for defense, aerospace, and industrial customers. The company designs, develops, manufactures, markets, and supports software-driven, three-dimensional (3-D) measurement, imaging, and realization aid for the 3D metrology, architecture, engineering and construction (AEC), Operations and Maintenance (O&M), and public safety analytics markets, enabling its customers to capture, measure, manipulate, interact with and share 3D and 2D data from the physical world in a virtual environment and then translate the information back into the physical domain. | AE28: Lake Mary, FL | AF28: www.faro.com
A29: USA-028 | B29: USA | C29: USA | D29: BETA Technologies (NYS: BETA) | H29: 45965 | J29: 2025 | K29: IPO | M29: Completed | N29: 1015 | O29: USD | R29: -1.57 | S29: -648.02 | T29: 35.1 | U29: 28.92 | W29: 7609.46 | X29: The company raised $1.02 billion in its initial public offering on the New York Stock Exchange under the ticker symbol of BETA on November 4, 2025. A total of 29,852,941 Class A shares were sold at $34 per share. After the offering, there was a total of 223,807,603 outstanding shares at $34 per share, valuing the company at $7.61 billion. The underwriters were granted an option to purchase up to an additional 4,477,941 Class A shares from the company to cover over-allotments, if any. | Y29: Formerly VC-backed | Z29: Generating Revenue | AB29: Aerospace and Defense | AC29: CleanTech, Manufacturing, Mobility Tech, Robotics and Drones | AD29: BETA Technologies Inc is an aerospace company. The group has developed an electric aircraft platform and propulsion systems that are positioned to transform the aviation industry forward into a new phase of growth. It designs, manufactures, and sells high-performance electric aircraft, modern electric propulsion systems, charging systems, and components. The group also invested in the underlying infrastructure of this breakthrough technology, which is critical to bringing electric aviation to life. The group has developed a differentiated presence in North America and is well-positioned to expand globally. Its products and services are Aircraft, Charge, Motor, Battery, Flight Controls, and Training. It has one operating segment: Development and Manufacturing of Electric Aircraft. | AE29: South Burlington, VT | AF29: www.beta.team
A30: USA-029 | B30: USA | C30: USA | D30: Mott | E30: IDEX | H30: 45540 | J30: 2024 | K30: Merger/Acquisition | M30: Completed | N30: 986.2 | O30: USD | P30: 4.93 | T30: 4.93 | U30: 200 | W30: 986.2 | X30: The company was acquired by IDEX (NYS: IEX) for $986.2 million on September 5, 2024. The acquisition helps IDEX to bring scale to its growing suite of material science technology capabilities and amplifies its ability to partner with customers to develop innovative solutions. | Y30: Corporate Backed or Acquired | Z30: Generating Revenue | AA30: IDEX (NYS: IEX) (Eric Ashleman) | AB30: Industrial Supplies and Parts | AC30: Manufacturing | AD30: Manufacturer of filtration and flow control products intended to serve the aerospace, automotive, food, and other industries. The company offers items including process filters, porous components, flow restrictors, gas diffusers, mixers, cartridges, wicks, and fluid mixers, enabling clients to avail of improved industrial supplies. | AE30: Farmington, CT | AF30: www.mottcorp.com
A31: USA-030 | B31: USA | C31: USA | D31: Haynes International | E31: North American Stainless | H31: 45617 | J31: 2024 | K31: Merger/Acquisition | M31: Completed | N31: 970 | O31: USD | P31: 1.71 | Q31: 14.67 | R31: 13.56 | S31: 71.55 | T31: 1.58 | U31: 614.33 | V31: Public to Private | W31: 970 | X31: The company was acquired by North American Stainless, a subsidiary of Acerinox (MAD: ACX), for $970 million on November 21, 2024. As a part of the transaction, the company will be delisted. | Y31: Formerly PE-Backed | Z31: Generating Revenue | AA31: North American Stainless | AB31: Other Metals, Minerals and Mining | AC31: Manufacturing | AD31: Haynes International Inc is a producer of high-performance nickel and cobalt-based alloys. The company is focused on developing, manufacturing, marketing, and distributing technology and high-performance alloys. The company operates in a single segment: the design, manufacture, marketing, and distribution of technologically advanced, high-performance alloys for use in the aerospace, industrial gas turbine, chemical processing, and other industries Geographically, it derives a majority of revenue from the United States and also has a presence in Europe, China, and other countries. | AE31: Kokomo, IN | AF31: www.haynesintl.com
A32: USA-031 | B32: USA | C32: USA | D32: Stellant Systems | E32: TransDigm Group | H32: 46022 | J32: 2025 | K32: Merger/Acquisition | M32: Announced/In Progress | N32: 960 | O32: USD | P32: 3.2 | T32: 3.2 | U32: 300 | W32: 960 | X32: The company reached a definitive agreement to be acquired by TransDigm Group (NYS: TDG) for $960 million on December 31, 2025. | Y32: Pending Transaction (M&A) | Z32: Generating Revenue | AA32: TransDigm Group (NYS: TDG) (Michael Lisman) | AB32: Aerospace and Defense | AC32: Manufacturing | AD32: Manufacturer of electron devices and spectrum-related products designed to offer power amplification devices for the space, electronic warfare, radar, medical, scientific and industrial end markets. The company's range of products includes satellite amplifiers, traveling wave tube amplifiers, microwave power modules and channelizers, enabling clients to benefit from amplification facilities with high reliability and durability. | AE32: Torrance, CA | AF32: www.stellantsystems.com
A33: USA-032 | B33: USA | C33: USA | D33: Firefly Aerospace (NAS: FLY) | H33: 45876 | J33: 2025 | K33: IPO | M33: Completed | N33: 868.32 | O33: USD | R33: -4.17 | S33: -208.05 | T33: 8.45 | U33: 102.81 | W33: 6464.2 | X33: The company raised $868.32 million in its initial public offering on the Nasdaq stock exchange under the ticker symbol of FLY on August 7, 2025. A total of 19,296,000 shares were sold at a price of $45 per share. After the offering, there was a total of 143,647,481 outstanding shares (excluding the over-allotment option) priced at $45 per share, valuing the company at $6.46 billion. The underwriters were granted an option to purchase up to an additional 2,894,400 shares from the company to cover over-allotments, if any. | Y33: Venture Capital-Backed | Z33: Generating Revenue | AB33: Aerospace and Defense | AC33: Space Technology | AD33: Firefly Aerospace Inc is a space and defense technology company with an established track record of success providing comprehensive mission solutions to national security, government, and commercial customers. The company develops and provides space and defense technologies, including launch vehicles and spacecraft systems, supporting launch, transit, and in-orbit operations for government, commercial, and national security customers. It has only one operating segment. The majority of the company's revenue is derived from Spacecraft Solutions. | AE33: Leander, TX | AF33: www.fireflyspace.com
A34: USA-033 | B34: USA | C34: USA | D34: JBT AeroTech | E34: Oshkosh | H34: 45139 | J34: 2023 | K34: Merger/Acquisition | M34: Completed | N34: 803.6 | O34: USD | V34: Corporate Divestiture | W34: 803.6 | X34: The company, a subsidiary of John Bean Technologies (NYS: JBT) was acquired by Oshkosh (NYS: OSK) for $803.6 million on August 1, 2023. The acquisition is expected to be accretive to Oshkosh's growth and margins and deliver solid recurring revenue from its aftermarket parts and services offerings. | Y34: Corporate Backed or Acquired | Z34: Generating Revenue | AA34: Oshkosh (NYS: OSK) (John Pfeifer) | AB34: Other Commercial Products | AD34: Distributor of aviation and aerospace components intended to serve commercial airlines, airports, air freight carriers, ground handling and military customers. The company offers cargo loaders, passenger steps, multi-bridge gates, regional aircraft bridges, elevating walks and rotundas, enabling clients to get a wide range of aviation and aerospace equipment. | AE34: Chicago, IL | AF34: www.oshkoshaerotech.com
A35: USA-034 | B35: USA | C35: USA | D35: Jnana Therapeutics | E35: Otsuka Pharmaceutical | H35: 45573 | J35: 2024 | K35: Merger/Acquisition | M35: Completed | N35: 800 | O35: USD | W35: 800 | X35: The company was acquired by Otsuka Pharmaceutical for $800 million on October 8, 2024. | Y35: Formerly VC-backed | Z35: Pre-Clinical Trials | AA35: Otsuka Pharmaceutical (Makoto Inoue) | AB35: Drug Discovery | AC35: Life Sciences | AD35: Developer of a drug discovery platform designed to target the solute carrier family of transporters and cell's metabolic gates. The company's platform addresses therapeutic targets across immune metabolism, lysosomal function, and mucosal defense, solute carrier cell transporters provide novel targets for immuno-oncology, inflammatory disorders, and neurological diseases, enabling companies to comprehensively address therapeutic targets across the vast member membrane protein family. | AE35: Boston, MA | AF35: www.jnanatx.com
A36: USA-035 | B36: USA | C36: USA | D36: Lanteris Space Systems | E36: Intuitive Machines | H36: 46035 | J36: 2026 | K36: Merger/Acquisition | M36: Completed | N36: 800 | O36: USD | P36: 1.27 | T36: 1.27 | U36: 630 | W36: 800 | X36: The company was acquired by Intuitive Machines (NAS: LUNR) for $800 million on January 13, 2026. The acquisition aligns with Intuitive Machines' vision, strengthening the company's position as a vertically integrated, next-generation space prime that can build, connect, and operate end-to-end mission solutions unique to the marketplace today. | Y36: Corporate Backed or Acquired | Z36: Generating Revenue | AA36: Intuitive Machines (NAS: LUNR) (Steven Altemus) | AB36: IT Consulting and Outsourcing | AC36: Space Technology | AD36: Provider of space technology and orbital infrastructure services intended to serve aerospace innovators, satellite operators, and global research institutions. The company offers satellite deployment, orbital logistics, space station modules, and mission support systems, thereby helping clients expand access to low Earth orbit and accelerate advancements in space-based applications. | AE36: Palo Alto, CA | AF36: www.lanterisspace.com
A37: USA-036 | B37: USA | C37: USA | D37: Simmonds Precision Products | E37: TransDigm Group | H37: 45936 | J37: 2025 | K37: Merger/Acquisition | M37: Completed | N37: 757 | O37: USD | P37: 2.16 | T37: 2.16 | U37: 350 | V37: Corporate Divestiture | W37: 757 | X37: The company, a subsidiary of Goodrich Corporation, was acquired by TransDigm Group (NYS: TDG) for approximately $757 million on October 6, 2025. | Y37: Corporate Backed or Acquired | Z37: Generating Revenue | AA37: TransDigm Group (NYS: TDG) (Kevin Stein) | AB37: Aerospace and Defense | AC37: Manufacturing | AD37: Manufacturer of fuel, proximity sensing and structural health monitoring solutions intended for the aerospace and defense end markets. The company develops engineered and proprietary components with significant aftermarket content and a strong presence across major aerospace and defense platforms. | AE37: Vergennes, VT | AF37: www.simmondsprecision.com
A38: USA-037 | B38: USA | C38: USA | D38: LinQuest | E38: KBR | H38: 45534 | J38: 2024 | K38: Merger/Acquisition | M38: Completed | N38: 739 | O38: USD | W38: 739 | X38: The company is acquired by KBR (NYS: KBR) for $739 million on August 30, 2024. This acquisition expands opportunities for revenue growth, meeting customer and market demands and enhances KBR's position in high-end, technically differentiated services across space, air dominance and battlespace missions. | Y38: Formerly PE-Backed | Z38: Generating Revenue | AA38: KBR (NYS: KBR) (Stuart Bradie) | AB38: Aerospace and Defense | AC38: Manufacturing | AD38: Manufacturer of surveillance and reconnaissance technology products intended to serve defense and intelligence communities. The company offers space systems, control, communications, computers, software and cyber systems development with complex systems modeling and simulation, enabling clients to fight through interfering signals at the tactical edge. | AE38: Herndon, VA | AF38: www.linquest.com
A39: USA-038 | B39: USA | C39: USA | D39: Calspan | E39: TransDigm Group | H39: 45054 | J39: 2023 | K39: Merger/Acquisition | M39: Completed | N39: 729 | O39: USD | W39: 729 | X39: The company was acquired by TransDigm Group (NYS: TDG) for $729 million on May 8, 2023. | Y39: Corporate Backed or Acquired | Z39: Generating Revenue | AA39: TransDigm Group (NYS: TDG) (Kevin Stein) | AB39: Aerospace and Defense | AD39: Provider of aerospace and automotive research and testing services based in Buffalo, New York. The company offers aerospace and automotive services including subsonic and transonic wind tunnel services, transportation testing, aerospace test equipment, flight operations, marine systems, force measurement systems and ground vehicles and motorsports testing, enabling clients to help in overcoming developmental and technical challenges. | AE39: Buffalo, NY | AF39: www.calspan.com
A40: USA-039 | B40: USA | C40: USA | D40: Triumph Group (Product Support Business) | E40: AAR | H40: 45352 | J40: 2024 | K40: Merger/Acquisition | M40: Completed | N40: 722.1 | O40: USD | P40: 2.69 | T40: 2.69 | U40: 268 | V40: Corporate Divestiture | W40: 722.1 | X40: The Product Support Business of Triumph Group (NYSE: TGI), was acquired by AAR (NYS: AIR) for $722.1 million on March 1, 2024. The acquisition will help AAR accelerate its deleveraging progress while placing its third-party Product Support business with a market-leading MRO company that has a proven track record of customer support. | Y40: Corporate Backed or Acquired | Z40: Generating Revenue | AA40: AAR (NYS: AIR) (John Holmes) | AB40: Aerospace and Defense | AD40: Provider of maintenance, repair and overhaul of structures-related services based in Radnor, Pennsylvania. The company specializes in airframe and engine accessories, servicing both the commercial and military aftermarkets. | AE40: Radnor, PA
